[{"ENTITY_ID": "32b078f4-037b-4df3-869b-066e82e082ba", "PAGE": 6, "CONTENT": {"CONTENT": {"word_ids": ["word_623_50"], "coordinates": {"y0": 971, "x0": 1293, "y1": 993, "x1": 1300}, "raw_text_unformatted": "1", "value": "1"}}, "CONFIDENCE": 0.8128055334091187, "ENTITY_TYPE": "CURRENCY"}, {"ENTITY_ID": "54e7db78-d400-45d9-b4df-d9627fa4c71e", "PAGE": 6, "CONTENT": {"CONTENT": {"word_ids": ["word_623_68"], "coordinates": {"y0": 1048, "x0": 316, "y1": 1069, "x1": 324}, "raw_text_unformatted": "1", "value": "1"}}, "CONFIDENCE": 0.767918586730957, "ENTITY_TYPE": "CURRENCY"}, {"ENTITY_ID": "abfaab39-119d-401f-b098-f57a2c5c1579", "PAGE": 6, "CONTENT": {"CONTENT": {"word_ids": ["word_623_126"], "coordinates": {"y0": 3113, "x0": 2099, "y1": 3136, "x1": 2274}, "raw_text_unformatted": "10118070528", "value": "10118070528"}}, "CONFIDENCE": 0.4375911056995392, "ENTITY_TYPE": "CURRENCY"}, {"ENTITY_ID": "c10ac75f-925a-4419-9f70-95c2c8662c14", "PAGE": 5, "CONTENT": {"CONTENT": {"word_ids": ["word_522_26"], "coordinates": {"y0": 398, "x0": 1046, "y1": 430, "x1": 1224}, "raw_text_unformatted": "$639,687.16", "value": "639687.16"}}, "CONFIDENCE": 0.9999338388442993, "ENTITY_TYPE": "CURRENCY"}, {"ENTITY_ID": "318072fa-c5d7-47f5-9267-164451cc366a", "PAGE": 5, "CONTENT": {"CONTENT": {"word_ids": ["word_522_38"], "coordinates": {"y0": 544, "x0": 1045, "y1": 574, "x1": 1221}, "raw_text_unformatted": "$294,224.07", "value": "294224.07"}}, "CONFIDENCE": 0.9997122287750244, "ENTITY_TYPE": "CURRENCY"}, {"ENTITY_ID": "5e37061f-5e59-45b2-a9b3-a5cc136c4eef", "PAGE": 5, "CONTENT": {"CONTENT": {"word_ids": ["word_522_52"], "coordinates": {"y0": 680, "x0": 1045, "y1": 711, "x1": 1221}, "raw_text_unformatted": "$332,159.25", "value": "332159.25"}}, "CONFIDENCE": 0.7340971231460571, "ENTITY_TYPE": "CURRENCY"}, {"ENTITY_ID": "008e979a-c47d-4c2a-8efd-9573ee341272", "PAGE": 5, "CONTENT": {"CONTENT": {"word_ids": ["word_522_74"], "coordinates": {"y0": 845, "x0": 1105, "y1": 871, "x1": 1185}, "raw_text_unformatted": "4,786", "value": "4786"}}, "CONFIDENCE": 0.998724639415741, "ENTITY_TYPE": "CURRENCY"}, {"ENTITY_ID": "755c654c-269d-4cf4-a023-12aaa0b0129b", "PAGE": 5, "CONTENT": {"CONTENT": {"word_ids": ["word_522_101"], "coordinates": {"y0": 1033, "x0": 1087, "y1": 1059, "x1": 1221}, "raw_text_unformatted": "82.531%", "value": "82.531"}}, "CONFIDENCE": 0.9991586208343506, "ENTITY_TYPE": "CURRENCY"}, {"ENTITY_ID": "87a16f44-99bc-496d-8212-df68de4d36f8", "PAGE": 5, "CONTENT": {"CONTENT": {"word_ids": ["word_522_165"], "coordinates": {"y0": 437, "x0": 1936, "y1": 462, "x1": 1951}, "raw_text_unformatted": "3", "value": "3"}}, "CONFIDENCE": 0.9815772175788879, "ENTITY_TYPE": "CURRENCY"}, {"ENTITY_ID": "5dec45e9-4e37-453f-bacb-f042ca232f27", "PAGE": 5, "CONTENT": {"CONTENT": {"word_ids": ["word_522_417"], "coordinates": {"y0": 2122, "x0": 582, "y1": 2158, "x1": 687}, "raw_text_unformatted": "103915", "value": "103915"}}, "CONFIDENCE": 0.7632983922958374, "ENTITY_TYPE": "CURRENCY"}, {"ENTITY_ID": "0294379e-6e06-4e02-92b0-41cb19040caa", "PAGE": 5, "CONTENT": {"CONTENT": {"word_ids": ["word_522_428"], "coordinates": {"y0": 2311, "x0": 582, "y1": 2346, "x1": 687}, "raw_text_unformatted": "144025", "value": "144025"}}, "CONFIDENCE": 0.9457592964172363, "ENTITY_TYPE": "CURRENCY"}, {"ENTITY_ID": "67cf999d-dccd-4a21-a5b4-6f2a65cc15c9", "PAGE": 5, "CONTENT": {"CONTENT": {"word_ids": ["word_522_434"], "coordinates": {"y0": 2374, "x0": 588, "y1": 2409, "x1": 685}, "raw_text_unformatted": "144025", "value": "144025"}}, "CONFIDENCE": 0.9433472752571106, "ENTITY_TYPE": "CURRENCY"}, {"ENTITY_ID": "7c299a62-dd9d-488e-ae67-7c8cbd50541c", "PAGE": 5, "CONTENT": {"CONTENT": {"word_ids": ["word_522_469", "word_522_470"], "coordinates": {"y0": 2032, "x0": 1975, "y1": 2223, "x1": 2228}, "raw_text_unformatted": "11234 411949", "value": "11234411949"}}, "CONFIDENCE": 0.6130343079566956, "ENTITY_TYPE": "CURRENCY"}, {"ENTITY_ID": "11124c36-290a-4862-bd24-47e716e0e89e", "PAGE": 5, "CONTENT": {"CONTENT": {"word_ids": ["word_522_474"], "coordinates": {"y0": 2377, "x0": 1975, "y1": 2412, "x1": 2082}, "raw_text_unformatted": "4110401", "value": "4110401"}}, "CONFIDENCE": 0.9303571581840515, "ENTITY_TYPE": "CURRENCY"}, {"ENTITY_ID": "3dca0a1e-6fce-43f4-8551-2ddc4b28457f", "PAGE": 5, "CONTENT": {"CONTENT": {"word_ids": ["word_522_527"], "coordinates": {"y0": 3130, "x0": 737, "y1": 3151, "x1": 798}, "raw_text_unformatted": "0617", "value": "0617"}}, "CONFIDENCE": 0.7592931389808655, "ENTITY_TYPE": "CURRENCY"}, {"ENTITY_ID": "d4450458-d35e-4584-8012-1a65def783eb", "PAGE": 5, "CONTENT": {"CONTENT": {"word_ids": ["word_522_540"], "coordinates": {"y0": 3134, "x0": 2093, "y1": 3157, "x1": 2267}, "raw_text_unformatted": "10118070528", "value": "10118070528"}}, "CONFIDENCE": 0.9600139260292053, "ENTITY_TYPE": "CURRENCY"}, {"ENTITY_ID": "702f97ea-198b-48a4-a3b8-2d1f8987630f", "PAGE": 1, "CONTENT": {"CONTENT": {"word_ids": ["word_118_42"], "coordinates": {"y0": 517, "x0": 1924, "y1": 541, "x1": 1958}, "raw_text_unformatted": "30", "value": "30"}}, "CONFIDENCE": 0.9943950772285461, "ENTITY_TYPE": "CURRENCY"}, {"ENTITY_ID": "d2c928dc-5c9c-4b54-9416-6f602fe260cc", "PAGE": 1, "CONTENT": {"CONTENT": {"word_ids": ["word_118_73"], "coordinates": {"y0": 680, "x0": 532, "y1": 706, "x1": 639}, "raw_text_unformatted": "108010", "value": "108010"}}, "CONFIDENCE": 0.5084289312362671, "ENTITY_TYPE": "CURRENCY"}, {"ENTITY_ID": "69af15e8-2caf-4197-8ff2-0f30ea5db716", "PAGE": 1, "CONTENT": {"CONTENT": {"word_ids": ["word_118_87"], "coordinates": {"y0": 727, "x0": 829, "y1": 751, "x1": 882}, "raw_text_unformatted": "202", "value": "202"}}, "CONFIDENCE": 0.4680961072444916, "ENTITY_TYPE": "CURRENCY"}, {"ENTITY_ID": "6fb878e4-3bf2-4708-9003-ceacf795f296", "PAGE": 1, "CONTENT": {"CONTENT": {"word_ids": ["word_118_101"], "coordinates": {"y0": 773, "x0": 1924, "y1": 799, "x1": 2118}, "raw_text_unformatted": "10118070528", "value": "10118070528"}}, "CONFIDENCE": 0.7758301496505737, "ENTITY_TYPE": "CURRENCY"}, {"ENTITY_ID": "deb53c7b-4500-4345-a7a9-ae13fa5d5394", "PAGE": 1, "CONTENT": {"CONTENT": {"word_ids": ["word_118_104"], "coordinates": {"y0": 805, "x0": 530, "y1": 862, "x1": 663}, "raw_text_unformatted": "$404,000", "value": "404000"}}, "CONFIDENCE": 0.9456053376197815, "ENTITY_TYPE": "CURRENCY"}, {"ENTITY_ID": "40d2a151-0ea6-48bb-889c-124e072534f3", "PAGE": 1, "CONTENT": {"CONTENT": {"word_ids": ["word_118_116"], "coordinates": {"y0": 988, "x0": 793, "y1": 1045, "x1": 997}, "raw_text_unformatted": "$343,400", "value": "343400"}}, "CONFIDENCE": 0.9997382760047913, "ENTITY_TYPE": "CURRENCY"}, {"ENTITY_ID": "08df17c2-eff6-4434-9a81-fe4824cda86e", "PAGE": 1, "CONTENT": {"CONTENT": {"word_ids": ["word_118_120"], "coordinates": {"y0": 1103, "x0": 788, "y1": 1141, "x1": 852}, "raw_text_unformatted": "4.5", "value": "4.5"}}, "CONFIDENCE": 0.9995818734169006, "ENTITY_TYPE": "CURRENCY"}, {"ENTITY_ID": "2668f8fe-199d-4da8-9f48-4e973c69386d", "PAGE": 1, "CONTENT": {"CONTENT": {"word_ids": ["word_118_127"], "coordinates": {"y0": 1261, "x0": 790, "y1": 1309, "x1": 1006}, "raw_text_unformatted": "$1,739.96", "value": "1739.96"}}, "CONFIDENCE": 0.9998282790184021, "ENTITY_TYPE": "CURRENCY"}, {"ENTITY_ID": "881522f7-4e7f-4faf-8781-9190094b467b", "PAGE": 1, "CONTENT": {"CONTENT": {"word_ids": ["word_118_174"], "coordinates": {"y0": 1931, "x0": 1450, "y1": 1966, "x1": 1603}, "raw_text_unformatted": "$1,739.96", "value": "1739.96"}}, "CONFIDENCE": 0.9964693784713745, "ENTITY_TYPE": "CURRENCY"}, {"ENTITY_ID": "5b5658de-e20a-483f-b644-f3f1902c24d2", "PAGE": 1, "CONTENT": {"CONTENT": {"word_ids": ["word_118_178"], "coordinates": {"y0": 2013, "x0": 1537, "y1": 2040, "x1": 1555}, "raw_text_unformatted": "0", "value": "0"}}, "CONFIDENCE": 0.5709869861602783, "ENTITY_TYPE": "CURRENCY"}, {"ENTITY_ID": "a8e4be17-c515-4ca9-897d-8d698c48b029", "PAGE": 1, "CONTENT": {"CONTENT": {"word_ids": ["word_118_182"], "coordinates": {"y0": 2092, "x0": 1496, "y1": 2119, "x1": 1603}, "raw_text_unformatted": "365.59", "value": "365.59"}}, "CONFIDENCE": 0.7823430895805359, "ENTITY_TYPE": "CURRENCY"}, {"ENTITY_ID": "24a397a0-38c2-412e-a771-f6905ba0b671", "PAGE": 1, "CONTENT": {"CONTENT": {"word_ids": ["word_118_193"], "coordinates": {"y0": 2221, "x0": 1509, "y1": 2259, "x1": 1628}, "raw_text_unformatted": "05.55", "value": "05.55"}}, "CONFIDENCE": 0.5050666928291321, "ENTITY_TYPE": "CURRENCY"}, {"ENTITY_ID": "9258d51e-5cf5-4d75-9a62-99615275ae4f", "PAGE": 1, "CONTENT": {"CONTENT": {"word_ids": ["word_118_209"], "coordinates": {"y0": 2410, "x0": 812, "y1": 2468, "x1": 988}, "raw_text_unformatted": "$589.59", "value": "589.59"}}, "CONFIDENCE": 0.9980589151382446, "ENTITY_TYPE": "CURRENCY"}, {"ENTITY_ID": "f4b023c3-e15e-4607-aa8a-077f3149c253", "PAGE": 1, "CONTENT": {"CONTENT": {"word_ids": ["word_118_227"], "coordinates": {"y0": 2540, "x0": 350, "y1": 2564, "x1": 366}, "raw_text_unformatted": "4", "value": "4"}}, "CONFIDENCE": 0.9336117506027222, "ENTITY_TYPE": "CURRENCY"}, {"ENTITY_ID": "37bcf6be-8662-4267-b397-b7be431e256d", "PAGE": 1, "CONTENT": {"CONTENT": {"word_ids": ["word_118_235"], "coordinates": {"y0": 2545, "x0": 1579, "y1": 2569, "x1": 1596}, "raw_text_unformatted": "4", "value": "4"}}, "CONFIDENCE": 0.9491447806358337, "ENTITY_TYPE": "CURRENCY"}, {"ENTITY_ID": "f3a2f5c3-a510-446d-9df1-e67817501fec", "PAGE": 1, "CONTENT": {"CONTENT": {"word_ids": ["word_118_253"], "coordinates": {"y0": 2839, "x0": 910, "y1": 2877, "x1": 1005}, "raw_text_unformatted": "436", "value": "436"}}, "CONFIDENCE": 0.8826298713684082, "ENTITY_TYPE": "CURRENCY"}, {"ENTITY_ID": "1b187120-9f56-4c17-b5ad-e3d5e8b1f5c1", "PAGE": 1, "CONTENT": {"CONTENT": {"word_ids": ["word_118_255"], "coordinates": {"y0": 2842, "x0": 1275, "y1": 2875, "x1": 1450}, "raw_text_unformatted": "$12,874.59", "value": "12874.59"}}, "CONFIDENCE": 0.9994804263114929, "ENTITY_TYPE": "CURRENCY"}, {"ENTITY_ID": "6a4d0c6f-b56e-4b29-89e9-c42d4f348fe8", "PAGE": 1, "CONTENT": {"CONTENT": {"word_ids": ["word_118_260"], "coordinates": {"y0": 2843, "x0": 1720, "y1": 2876, "x1": 1873}, "raw_text_unformatted": "$7,839.77", "value": "7839.77"}}, "CONFIDENCE": 0.9801198840141296, "ENTITY_TYPE": "CURRENCY"}, {"ENTITY_ID": "2d3adc99-8106-4505-beb0-c85854fd04b2", "PAGE": 1, "CONTENT": {"CONTENT": {"word_ids": ["word_118_265"], "coordinates": {"y0": 2845, "x0": 2141, "y1": 2877, "x1": 2178}, "raw_text_unformatted": "$0", "value": "0"}}, "CONFIDENCE": 0.9988122582435608, "ENTITY_TYPE": "CURRENCY"}, {"ENTITY_ID": "35b9ffb0-aced-4113-a00f-53ae648827a9", "PAGE": 1, "CONTENT": {"CONTENT": {"word_ids": ["word_118_271"], "coordinates": {"y0": 2888, "x0": 1582, "y1": 2916, "x1": 1605}, "raw_text_unformatted": "2", "value": "2"}}, "CONFIDENCE": 0.9893514513969421, "ENTITY_TYPE": "CURRENCY"}, {"ENTITY_ID": "363a3513-472f-4fb5-b17a-9ac507d5db30", "PAGE": 1, "CONTENT": {"CONTENT": {"word_ids": ["word_118_278"], "coordinates": {"y0": 2974, "x0": 760, "y1": 3022, "x1": 1003}, "raw_text_unformatted": "$75,635.90", "value": "75635.90"}}, "CONFIDENCE": 0.9982819557189941, "ENTITY_TYPE": "CURRENCY"}, {"ENTITY_ID": "e8f39f19-d9c7-48ee-b707-3e504c8f11a4", "PAGE": 1, "CONTENT": {"CONTENT": {"word_ids": ["word_118_289"], "coordinates": {"y0": 2978, "x0": 2069, "y1": 3026, "x1": 2093}, "raw_text_unformatted": "3", "value": "3"}}, "CONFIDENCE": 0.9842612147331238, "ENTITY_TYPE": "CURRENCY"}, {"ENTITY_ID": "6fdca6e1-ef13-4835-99f8-b08d0611672d", "PAGE": 1, "CONTENT": {"CONTENT": {"word_ids": ["word_118_309"], "coordinates": {"y0": 3139, "x0": 2096, "y1": 3162, "x1": 2271}, "raw_text_unformatted": "10118070528", "value": "10118070528"}}, "CONFIDENCE": 0.8583006262779236, "ENTITY_TYPE": "CURRENCY"}, {"ENTITY_ID": "32679d9f-ef1b-4db0-a25c-c4c8dbf1b8b9", "PAGE": 4, "CONTENT": {"CONTENT": {"word_ids": ["word_421_93"], "coordinates": {"y0": 1049, "x0": 646, "y1": 1074, "x1": 678}, "raw_text_unformatted": "75", "value": "75"}}, "CONFIDENCE": 0.6812021136283875, "ENTITY_TYPE": "CURRENCY"}, {"ENTITY_ID": "4f411748-ce6e-424e-b967-9f1978b430a2", "PAGE": 4, "CONTENT": {"CONTENT": {"word_ids": ["word_421_104"], "coordinates": {"y0": 1088, "x0": 347, "y1": 1113, "x1": 394}, "raw_text_unformatted": "2%", "value": "2"}}, "CONFIDENCE": 0.9949333667755127, "ENTITY_TYPE": "CURRENCY"}, {"ENTITY_ID": "3f758bc3-8aae-42d7-9d62-b8d6c02346a1", "PAGE": 4, "CONTENT": {"CONTENT": {"word_ids": ["word_421_176"], "coordinates": {"y0": 1507, "x0": 184, "y1": 1540, "x1": 219}, "raw_text_unformatted": "03", "value": "03"}}, "CONFIDENCE": 0.7406464219093323, "ENTITY_TYPE": "CURRENCY"}, {"ENTITY_ID": "371062c5-50ca-4b13-8d1c-533ec67046d3", "PAGE": 4, "CONTENT": {"CONTENT": {"word_ids": ["word_421_347"], "coordinates": {"y0": 3130, "x0": 739, "y1": 3151, "x1": 799}, "raw_text_unformatted": "0617", "value": "0617"}}, "CONFIDENCE": 0.49063223600387573, "ENTITY_TYPE": "CURRENCY"}, {"ENTITY_ID": "55f5269d-bca5-40d6-8ec4-5395952eaf60", "PAGE": 4, "CONTENT": {"CONTENT": {"word_ids": ["word_421_415"], "coordinates": {"y0": 908, "x0": 1688, "y1": 931, "x1": 1702}, "raw_text_unformatted": "2", "value": "2"}}, "CONFIDENCE": 0.45437750220298767, "ENTITY_TYPE": "CURRENCY"}, {"ENTITY_ID": "14b46717-a7b2-4249-8a5f-f6f8c63918e1", "PAGE": 4, "CONTENT": {"CONTENT": {"word_ids": ["word_421_421"], "coordinates": {"y0": 890, "x0": 2224, "y1": 911, "x1": 2232}, "raw_text_unformatted": "1", "value": "1"}}, "CONFIDENCE": 0.9012919664382935, "ENTITY_TYPE": "CURRENCY"}, {"ENTITY_ID": "becb6ac5-bbf2-47f0-b942-600fe27811b3", "PAGE": 4, "CONTENT": {"CONTENT": {"word_ids": ["word_421_425"], "coordinates": {"y0": 907, "x0": 1634, "y1": 934, "x1": 1758}, "raw_text_unformatted": "$4,021.49", "value": "4021.49"}}, "CONFIDENCE": 0.9963405132293701, "ENTITY_TYPE": "CURRENCY"}, {"ENTITY_ID": "a40f2bdf-38e9-4648-adfc-9802aeaed2ea", "PAGE": 4, "CONTENT": {"CONTENT": {"word_ids": ["word_421_432"], "coordinates": {"y0": 956, "x0": 1438, "y1": 978, "x1": 1446}, "raw_text_unformatted": "1", "value": "1"}}, "CONFIDENCE": 0.4656836688518524, "ENTITY_TYPE": "CURRENCY"}, {"ENTITY_ID": "872b0f9c-89d4-41e8-8172-717830cad4da", "PAGE": 4, "CONTENT": {"CONTENT": {"word_ids": ["word_421_446"], "coordinates": {"y0": 1049, "x0": 2223, "y1": 1072, "x1": 2231}, "raw_text_unformatted": "1", "value": "1"}}, "CONFIDENCE": 0.6401705145835876, "ENTITY_TYPE": "CURRENCY"}, {"ENTITY_ID": "5d7e5254-deed-481f-84d8-4e1bc6b63fea", "PAGE": 4, "CONTENT": {"CONTENT": {"word_ids": ["word_421_459"], "coordinates": {"y0": 1117, "x0": 1438, "y1": 1138, "x1": 1445}, "raw_text_unformatted": "1", "value": "1"}}, "CONFIDENCE": 0.8440130949020386, "ENTITY_TYPE": "CURRENCY"}, {"ENTITY_ID": "d009a992-7169-4f6e-a517-d8567514e39b", "PAGE": 4, "CONTENT": {"CONTENT": {"word_ids": ["word_421_477"], "coordinates": {"y0": 1268, "x0": 1631, "y1": 1296, "x1": 1754}, "raw_text_unformatted": "$1,113.37", "value": "1113.37"}}, "CONFIDENCE": 0.9995280504226685, "ENTITY_TYPE": "CURRENCY"}, {"ENTITY_ID": "a66f7b25-fb89-45f3-a084-a8b124380853", "PAGE": 4, "CONTENT": {"CONTENT": {"word_ids": ["word_421_489"], "coordinates": {"y0": 1293, "x0": 2271, "y1": 1315, "x1": 2291}, "raw_text_unformatted": "2.", "value": "2."}}, "CONFIDENCE": 0.790744423866272, "ENTITY_TYPE": "CURRENCY"}, {"ENTITY_ID": "7d0dff10-3f3a-48a6-aa4f-8bc8106ab609", "PAGE": 4, "CONTENT": {"CONTENT": {"word_ids": ["word_421_513"], "coordinates": {"y0": 1523, "x0": 1936, "y1": 1557, "x1": 1969}, "raw_text_unformatted": "1", "value": "1"}}, "CONFIDENCE": 0.6409676671028137, "ENTITY_TYPE": "CURRENCY"}, {"ENTITY_ID": "b6702e31-6d82-484b-af3c-80fcbb394d1f", "PAGE": 4, "CONTENT": {"CONTENT": {"word_ids": ["word_421_517"], "coordinates": {"y0": 1524, "x0": 2200, "y1": 1558, "x1": 2236}, "raw_text_unformatted": "3", "value": "3"}}, "CONFIDENCE": 0.7864166498184204, "ENTITY_TYPE": "CURRENCY"}, {"ENTITY_ID": "c6d4c293-8158-4b56-9b36-1f525900b562", "PAGE": 4, "CONTENT": {"CONTENT": {"word_ids": ["word_421_563"], "coordinates": {"y0": 1787, "x0": 2216, "y1": 1809, "x1": 2236}, "raw_text_unformatted": "1.", "value": "1."}}, "CONFIDENCE": 0.5250741839408875, "ENTITY_TYPE": "CURRENCY"}, {"ENTITY_ID": "0a436f3b-0051-434f-9574-35bd3f65b81a", "PAGE": 4, "CONTENT": {"CONTENT": {"word_ids": ["word_421_575"], "coordinates": {"y0": 1853, "x0": 1430, "y1": 1875, "x1": 1438}, "raw_text_unformatted": "1", "value": "1"}}, "CONFIDENCE": 0.7247622013092041, "ENTITY_TYPE": "CURRENCY"}, {"ENTITY_ID": "f84485b0-f814-4b74-8509-621028c7cbd1", "PAGE": 4, "CONTENT": {"CONTENT": {"word_ids": ["word_421_640"], "coordinates": {"y0": 2158, "x0": 2213, "y1": 2188, "x1": 2250}, "raw_text_unformatted": "1", "value": "1"}}, "CONFIDENCE": 0.5013601779937744, "ENTITY_TYPE": "CURRENCY"}, {"ENTITY_ID": "d4a910e6-3548-4af2-a3ad-4dc07a65e6a4", "PAGE": 4, "CONTENT": {"CONTENT": {"word_ids": ["word_421_646"], "coordinates": {"y0": 2196, "x0": 1723, "y1": 2227, "x1": 1758}, "raw_text_unformatted": "2", "value": "2"}}, "CONFIDENCE": 0.8168964385986328, "ENTITY_TYPE": "CURRENCY"}, {"ENTITY_ID": "eb50b5b2-0201-4cc9-a60a-6c9c86a72971", "PAGE": 4, "CONTENT": {"CONTENT": {"word_ids": ["word_421_667"], "coordinates": {"y0": 2240, "x0": 2140, "y1": 2271, "x1": 2173}, "raw_text_unformatted": "1", "value": "1"}}, "CONFIDENCE": 0.8319908976554871, "ENTITY_TYPE": "CURRENCY"}, {"ENTITY_ID": "5cf86bbb-4f16-4e56-bde8-fda2aacfad1c", "PAGE": 4, "CONTENT": {"CONTENT": {"word_ids": ["word_421_675"], "coordinates": {"y0": 2279, "x0": 1793, "y1": 2310, "x1": 1828}, "raw_text_unformatted": "2", "value": "2"}}, "CONFIDENCE": 0.7898488640785217, "ENTITY_TYPE": "CURRENCY"}, {"ENTITY_ID": "096f1bb8-ac56-45d0-8dda-23b0c10fee37", "PAGE": 4, "CONTENT": {"CONTENT": {"word_ids": ["word_421_684"], "coordinates": {"y0": 2318, "x0": 1400, "y1": 2349, "x1": 1435}, "raw_text_unformatted": "3", "value": "3"}}, "CONFIDENCE": 0.7465285658836365, "ENTITY_TYPE": "CURRENCY"}, {"ENTITY_ID": "1082a2c4-a1a9-4b77-a8d9-b96cb4c82dbc", "PAGE": 4, "CONTENT": {"CONTENT": {"word_ids": ["word_421_717"], "coordinates": {"y0": 3137, "x0": 1859, "y1": 3159, "x1": 1874}, "raw_text_unformatted": "4", "value": "4"}}, "CONFIDENCE": 0.7303236722946167, "ENTITY_TYPE": "CURRENCY"}, {"ENTITY_ID": "fa3afe86-b079-4a86-adab-8b9027279f90", "PAGE": 4, "CONTENT": {"CONTENT": {"word_ids": ["word_421_723"], "coordinates": {"y0": 3139, "x0": 2093, "y1": 3162, "x1": 2268}, "raw_text_unformatted": "10118070528", "value": "10118070528"}}, "CONFIDENCE": 0.9702966809272766, "ENTITY_TYPE": "CURRENCY"}, {"ENTITY_ID": "ed11c8d0-bdab-42f0-917c-0a41356a90ea", "PAGE": 3, "CONTENT": {"CONTENT": {"word_ids": ["word_320_28"], "coordinates": {"y0": 354, "x0": 843, "y1": 398, "x1": 984}, "raw_text_unformatted": "$25,070.00", "value": "25070.00"}}, "CONFIDENCE": 0.8026167750358582, "ENTITY_TYPE": "CURRENCY"}, {"ENTITY_ID": "755bc8cb-e59c-44e5-bc9e-06bf41169204", "PAGE": 3, "CONTENT": {"CONTENT": {"word_ids": ["word_320_29"], "coordinates": {"y0": 368, "x0": 1079, "y1": 395, "x1": 1221}, "raw_text_unformatted": "$20,714.36", "value": "20714.36"}}, "CONFIDENCE": 0.94243985414505, "ENTITY_TYPE": "CURRENCY"}, {"ENTITY_ID": "40219b55-39af-49bc-929a-3df961076852", "PAGE": 3, "CONTENT": {"CONTENT": {"word_ids": ["word_320_69"], "coordinates": {"y0": 622, "x0": 1077, "y1": 663, "x1": 1218}, "raw_text_unformatted": "550,500.00", "value": "550500.00"}}, "CONFIDENCE": 0.8149250149726868, "ENTITY_TYPE": "CURRENCY"}, {"ENTITY_ID": "a303957a-2fe5-4aaa-90dc-0a552147b792", "PAGE": 3, "CONTENT": {"CONTENT": {"word_ids": ["word_320_87"], "coordinates": {"y0": 746, "x0": 950, "y1": 772, "x1": 981}, "raw_text_unformatted": "$0", "value": "0"}}, "CONFIDENCE": 0.5093746781349182, "ENTITY_TYPE": "CURRENCY"}, {"ENTITY_ID": "cab5ea5d-5038-4842-a2a8-29e9ca55ec78", "PAGE": 3, "CONTENT": {"CONTENT": {"word_ids": ["word_320_94"], "coordinates": {"y0": 799, "x0": 950, "y1": 824, "x1": 980}, "raw_text_unformatted": "50", "value": "50"}}, "CONFIDENCE": 0.9134973883628845, "ENTITY_TYPE": "CURRENCY"}, {"ENTITY_ID": "95b384a9-b3a0-4edd-8e0c-9d2a415b69f5", "PAGE": 3, "CONTENT": {"CONTENT": {"word_ids": ["word_320_113"], "coordinates": {"y0": 841, "x0": 1093, "y1": 881, "x1": 1217}, "raw_text_unformatted": "$5,273.54", "value": "5273.54"}}, "CONFIDENCE": 0.9646630883216858, "ENTITY_TYPE": "CURRENCY"}, {"ENTITY_ID": "6611de0b-ff0c-4b7c-86f1-d604c918ffc3", "PAGE": 3, "CONTENT": {"CONTENT": {"word_ids": ["word_320_124"], "coordinates": {"y0": 907, "x0": 826, "y1": 945, "x1": 980}, "raw_text_unformatted": "$65,470.00", "value": "65470.00"}}, "CONFIDENCE": 0.9987652897834778, "ENTITY_TYPE": "CURRENCY"}, {"ENTITY_ID": "ea36b075-8764-4cdf-a998-5ba38b3e3130", "PAGE": 3, "CONTENT": {"CONTENT": {"word_ids": ["word_320_125"], "coordinates": {"y0": 911, "x0": 1061, "y1": 938, "x1": 1216}, "raw_text_unformatted": "$75,635.90", "value": "75635.90"}}, "CONFIDENCE": 0.9266585111618042, "ENTITY_TYPE": "CURRENCY"}, {"ENTITY_ID": "d5ddb183-9468-431f-9feb-0da9c0f49116", "PAGE": 3, "CONTENT": {"CONTENT": {"word_ids": ["word_320_162"], "coordinates": {"y0": 1162, "x0": 1016, "y1": 1204, "x1": 1187}, "raw_text_unformatted": "$429,035.90", "value": "429035.90"}}, "CONFIDENCE": 0.9995080828666687, "ENTITY_TYPE": "CURRENCY"}, {"ENTITY_ID": "f941184d-a37c-4647-8f54-3e5165a39e79", "PAGE": 3, "CONTENT": {"CONTENT": {"word_ids": ["word_320_169"], "coordinates": {"y0": 1171, "x0": 2123, "y1": 1200, "x1": 2296}, "raw_text_unformatted": "$409,273.54", "value": "409273.54"}}, "CONFIDENCE": 0.9997568726539612, "ENTITY_TYPE": "CURRENCY"}, {"ENTITY_ID": "3b152acc-2ad1-4c9a-95ca-4b47d5e80059", "PAGE": 3, "CONTENT": {"CONTENT": {"word_ids": ["word_320_175"], "coordinates": {"y0": 1213, "x0": 1031, "y1": 1258, "x1": 1188}, "raw_text_unformatted": "$404,000.00", "value": "404000.00"}}, "CONFIDENCE": 0.9987260103225708, "ENTITY_TYPE": "CURRENCY"}, {"ENTITY_ID": "c6584178-5c05-400e-a539-815989d29a6f", "PAGE": 3, "CONTENT": {"CONTENT": {"word_ids": ["word_320_182"], "coordinates": {"y0": 1220, "x0": 2138, "y1": 1258, "x1": 2295}, "raw_text_unformatted": "$404,000.00", "value": "404000.00"}}, "CONFIDENCE": 0.9994745254516602, "ENTITY_TYPE": "CURRENCY"}, {"ENTITY_ID": "0a19955f-19ec-4904-955f-f07feb14eb12", "PAGE": 3, "CONTENT": {"CONTENT": {"word_ids": ["word_320_203"], "coordinates": {"y0": 1305, "x0": 1047, "y1": 1340, "x1": 1188}, "raw_text_unformatted": "$19,762.36", "value": "19762.36"}}, "CONFIDENCE": 0.9967848658561707, "ENTITY_TYPE": "CURRENCY"}, {"ENTITY_ID": "c96b4bd3-3565-4e64-b1b6-04c484578410", "PAGE": 3, "CONTENT": {"CONTENT": {"word_ids": ["word_320_218"], "coordinates": {"y0": 1430, "x0": 1062, "y1": 1470, "x1": 1186}, "raw_text_unformatted": "$1,487.05", "value": "1487.05"}}, "CONFIDENCE": 0.9973288178443909, "ENTITY_TYPE": "CURRENCY"}, {"ENTITY_ID": "24e1cde8-6211-4b59-b677-4102239d3664", "PAGE": 3, "CONTENT": {"CONTENT": {"word_ids": ["word_320_226"], "coordinates": {"y0": 1476, "x0": 1063, "y1": 1512, "x1": 1188}, "raw_text_unformatted": "$250000", "value": "250000"}}, "CONFIDENCE": 0.9970508217811584, "ENTITY_TYPE": "CURRENCY"}, {"ENTITY_ID": "0090b8d3-d16a-4857-8426-84f833358210", "PAGE": 3, "CONTENT": {"CONTENT": {"word_ids": ["word_320_229"], "coordinates": {"y0": 1478, "x0": 2167, "y1": 1516, "x1": 2309}, "raw_text_unformatted": "$2,50000", "value": "250000"}}, "CONFIDENCE": 0.9964057207107544, "ENTITY_TYPE": "CURRENCY"}, {"ENTITY_ID": "b0d48e58-1d20-4a96-bb9d-4cde49e2bcbe", "PAGE": 3, "CONTENT": {"CONTENT": {"word_ids": ["word_320_252"], "coordinates": {"y0": 1605, "x0": 1117, "y1": 1631, "x1": 1185}, "raw_text_unformatted": "5243", "value": "5243"}}, "CONFIDENCE": 0.3526473045349121, "ENTITY_TYPE": "CURRENCY"}, {"ENTITY_ID": "a65fee01-dbde-4b46-a5c8-a5af8b09c87e", "PAGE": 3, "CONTENT": {"CONTENT": {"word_ids": ["word_320_259"], "coordinates": {"y0": 1612, "x0": 2224, "y1": 1639, "x1": 2293}, "raw_text_unformatted": "$243", "value": "243"}}, "CONFIDENCE": 0.9568893313407898, "ENTITY_TYPE": "CURRENCY"}, {"ENTITY_ID": "a0394c7f-f1b6-4511-bf6d-fb649b63d9f8", "PAGE": 3, "CONTENT": {"CONTENT": {"word_ids": ["word_320_267"], "coordinates": {"y0": 1690, "x0": 199, "y1": 1711, "x1": 228}, "raw_text_unformatted": "16", "value": "16"}}, "CONFIDENCE": 0.49823981523513794, "ENTITY_TYPE": "CURRENCY"}, {"ENTITY_ID": "e4ceda28-65aa-4213-b9a3-9783e81c2f7a", "PAGE": 3, "CONTENT": {"CONTENT": {"word_ids": ["word_320_270"], "coordinates": {"y0": 1680, "x0": 694, "y1": 1683, "x1": 697}, "raw_text_unformatted": "4", "value": "4"}}, "CONFIDENCE": 0.6885174512863159, "ENTITY_TYPE": "CURRENCY"}, {"ENTITY_ID": "b02ca1bf-4c5a-4545-8006-83ac9c2b0cff", "PAGE": 3, "CONTENT": {"CONTENT": {"word_ids": ["word_320_278"], "coordinates": {"y0": 1724, "x0": 1071, "y1": 1770, "x1": 1182}, "raw_text_unformatted": "551840", "value": "551840"}}, "CONFIDENCE": 0.4637525677680969, "ENTITY_TYPE": "CURRENCY"}, {"ENTITY_ID": "40cbcf69-b60d-4390-9aaa-fcd4f87b2139", "PAGE": 3, "CONTENT": {"CONTENT": {"word_ids": ["word_320_286"], "coordinates": {"y0": 1729, "x0": 2187, "y1": 1774, "x1": 2299}, "raw_text_unformatted": "$51840", "value": "51840"}}, "CONFIDENCE": 0.8662809729576111, "ENTITY_TYPE": "CURRENCY"}, {"ENTITY_ID": "2691f338-99b6-44cd-b52f-32f473fe9a9d", "PAGE": 3, "CONTENT": {"CONTENT": {"word_ids": ["word_320_290"], "coordinates": {"y0": 1768, "x0": 1099, "y1": 1804, "x1": 1185}, "raw_text_unformatted": "$83.66", "value": "83.66"}}, "CONFIDENCE": 0.9854339957237244, "ENTITY_TYPE": "CURRENCY"}, {"ENTITY_ID": "6e6b160a-5852-43d8-b089-00b666abb0d8", "PAGE": 3, "CONTENT": {"CONTENT": {"word_ids": ["word_320_304"], "coordinates": {"y0": 1862, "x0": 199, "y1": 1884, "x1": 226}, "raw_text_unformatted": "14", "value": "14"}}, "CONFIDENCE": 0.8121953010559082, "ENTITY_TYPE": "CURRENCY"}, {"ENTITY_ID": "cf71d41b-80b3-4df7-b028-cb2156cfbfe2", "PAGE": 3, "CONTENT": {"CONTENT": {"word_ids": ["word_320_306", "word_320_307"], "coordinates": {"y0": 1864, "x0": 1081, "y1": 1889, "x1": 1184}, "raw_text_unformatted": "$282 00", "value": "28200"}}, "CONFIDENCE": 0.9926190376281738, "ENTITY_TYPE": "CURRENCY"}, {"ENTITY_ID": "73031ecf-d484-4ae3-9fdf-e7af91e8ed63", "PAGE": 3, "CONTENT": {"CONTENT": {"word_ids": ["word_320_310"], "coordinates": {"y0": 1870, "x0": 2189, "y1": 1896, "x1": 2292}, "raw_text_unformatted": "$282.00", "value": "282.00"}}, "CONFIDENCE": 0.9995935559272766, "ENTITY_TYPE": "CURRENCY"}, {"ENTITY_ID": "13c16b9a-4e9f-44d1-a682-4478eca72ee8", "PAGE": 3, "CONTENT": {"CONTENT": {"word_ids": ["word_320_322"], "coordinates": {"y0": 1959, "x0": 1011, "y1": 1999, "x1": 1183}, "raw_text_unformatted": "$353,400.00", "value": "353400.00"}}, "CONFIDENCE": 0.9091479182243347, "ENTITY_TYPE": "CURRENCY"}, {"ENTITY_ID": "61bb781c-e626-49b9-a478-a46744ee7ad8", "PAGE": 3, "CONTENT": {"CONTENT": {"word_ids": ["word_320_329"], "coordinates": {"y0": 1969, "x0": 2134, "y1": 1996, "x1": 2291}, "raw_text_unformatted": "$12,466.00", "value": "12466.00"}}, "CONFIDENCE": 0.9975214600563049, "ENTITY_TYPE": "CURRENCY"}, {"ENTITY_ID": "3ef85a52-d226-4ea9-8d35-1a6c8032407b", "PAGE": 3, "CONTENT": {"CONTENT": {"word_ids": ["word_320_343"], "coordinates": {"y0": 2048, "x0": 1026, "y1": 2087, "x1": 1182}, "raw_text_unformatted": "$343,400.00", "value": "343400.00"}}, "CONFIDENCE": 0.9977389574050903, "ENTITY_TYPE": "CURRENCY"}, {"ENTITY_ID": "531de378-b1e9-4212-8060-0f35eb8fbd15", "PAGE": 3, "CONTENT": {"CONTENT": {"word_ids": ["word_320_368"], "coordinates": {"y0": 2137, "x0": 177, "y1": 2170, "x1": 207}, "raw_text_unformatted": "0", "value": "0"}}, "CONFIDENCE": 0.6946691870689392, "ENTITY_TYPE": "CURRENCY"}, {"ENTITY_ID": "77dbacdb-5cc4-4519-b694-0c815ec7de11", "PAGE": 3, "CONTENT": {"CONTENT": {"word_ids": ["word_320_381"], "coordinates": {"y0": 2186, "x0": 1014, "y1": 2218, "x1": 1195}, "raw_text_unformatted": "$10,000.00", "value": "10000.00"}}, "CONFIDENCE": 0.9952819347381592, "ENTITY_TYPE": "CURRENCY"}, {"ENTITY_ID": "ca211c3a-240e-4e09-9785-07a4b21468a8", "PAGE": 3, "CONTENT": {"CONTENT": {"word_ids": ["word_320_400"], "coordinates": {"y0": 2322, "x0": 2146, "y1": 2351, "x1": 2289}, "raw_text_unformatted": "$10,000.00", "value": "10000.00"}}, "CONFIDENCE": 0.9997371435165405, "ENTITY_TYPE": "CURRENCY"}, {"ENTITY_ID": "7c9a1714-e820-4437-8adb-cd58ca15fbb5", "PAGE": 3, "CONTENT": {"CONTENT": {"word_ids": ["word_320_435"], "coordinates": {"y0": 2618, "x0": 1309, "y1": 2638, "x1": 1336}, "raw_text_unformatted": "14", "value": "14"}}, "CONFIDENCE": 0.7134485244750977, "ENTITY_TYPE": "CURRENCY"}, {"ENTITY_ID": "09819041-7ac9-4ef7-9209-50eb34c146f7", "PAGE": 3, "CONTENT": {"CONTENT": {"word_ids": ["word_320_439"], "coordinates": {"y0": 2656, "x0": 195, "y1": 2689, "x1": 247}, "raw_text_unformatted": "12", "value": "12"}}, "CONFIDENCE": 0.9524765014648438, "ENTITY_TYPE": "CURRENCY"}, {"ENTITY_ID": "716b28f1-f343-4da7-99a9-8aaaba383fa3", "PAGE": 3, "CONTENT": {"CONTENT": {"word_ids": ["word_320_442"], "coordinates": {"y0": 2660, "x0": 1308, "y1": 2693, "x1": 1335}, "raw_text_unformatted": "15", "value": "15"}}, "CONFIDENCE": 0.8207615613937378, "ENTITY_TYPE": "CURRENCY"}, {"ENTITY_ID": "3acb2d7e-3a13-4e1a-8380-69d7e6290760", "PAGE": 3, "CONTENT": {"CONTENT": {"word_ids": ["word_320_446"], "coordinates": {"y0": 2701, "x0": 193, "y1": 2721, "x1": 217}, "raw_text_unformatted": "14", "value": "14"}}, "CONFIDENCE": 0.9810304045677185, "ENTITY_TYPE": "CURRENCY"}, {"ENTITY_ID": "559b2ab6-8bdd-4f9e-87a8-1d1b8c7142b1", "PAGE": 3, "CONTENT": {"CONTENT": {"word_ids": ["word_320_449"], "coordinates": {"y0": 2704, "x0": 1309, "y1": 2725, "x1": 1336}, "raw_text_unformatted": "6", "value": "6"}}, "CONFIDENCE": 0.984329342842102, "ENTITY_TYPE": "CURRENCY"}, {"ENTITY_ID": "8e395646-1b8d-4cd5-bc11-19fc51d04454", "PAGE": 3, "CONTENT": {"CONTENT": {"word_ids": ["word_320_466"], "coordinates": {"y0": 2936, "x0": 1020, "y1": 2973, "x1": 1177}, "raw_text_unformatted": "$429,035.90", "value": "429035.90"}}, "CONFIDENCE": 0.9989213943481445, "ENTITY_TYPE": "CURRENCY"}, {"ENTITY_ID": "14c425a6-d1ad-4ef6-b162-01608ce52128", "PAGE": 3, "CONTENT": {"CONTENT": {"word_ids": ["word_320_474"], "coordinates": {"y0": 2944, "x0": 2127, "y1": 2977, "x1": 2284}, "raw_text_unformatted": "5409,273.54", "value": "5409273.54"}}, "CONFIDENCE": 0.9031092524528503, "ENTITY_TYPE": "CURRENCY"}, {"ENTITY_ID": "d1e38ada-4b17-46c0-92f0-85da5cf98e8c", "PAGE": 3, "CONTENT": {"CONTENT": {"word_ids": ["word_320_501"], "coordinates": {"y0": 3020, "x0": 1022, "y1": 3066, "x1": 1176}, "raw_text_unformatted": "$75,635.90", "value": "75635.90"}}, "CONFIDENCE": 0.9999488592147827, "ENTITY_TYPE": "CURRENCY"}, {"ENTITY_ID": "7f12bf80-38c5-4426-a14c-4f47b0486026", "PAGE": 3, "CONTENT": {"CONTENT": {"word_ids": ["word_320_508"], "coordinates": {"y0": 3034, "x0": 2112, "y1": 3061, "x1": 2284}, "raw_text_unformatted": "$396,807.54", "value": "396807.54"}}, "CONFIDENCE": 0.9999142289161682, "ENTITY_TYPE": "CURRENCY"}, {"ENTITY_ID": "ff08e065-93ee-440c-8e40-a2ef03d8911d", "PAGE": 3, "CONTENT": {"CONTENT": {"word_ids": ["word_320_523"], "coordinates": {"y0": 3134, "x0": 1860, "y1": 3157, "x1": 1873}, "raw_text_unformatted": "3", "value": "3"}}, "CONFIDENCE": 0.7027952671051025, "ENTITY_TYPE": "CURRENCY"}, {"ENTITY_ID": "8e9da5bb-66ab-4d72-9660-9f0395662254", "PAGE": 3, "CONTENT": {"CONTENT": {"word_ids": ["word_320_529"], "coordinates": {"y0": 3137, "x0": 2092, "y1": 3160, "x1": 2268}, "raw_text_unformatted": "10118070528", "value": "10118070528"}}, "CONFIDENCE": 0.5366255044937134, "ENTITY_TYPE": "CURRENCY"}, {"ENTITY_ID": "4ab4e3c7-5be8-4cf6-928d-b507a84dc9aa", "PAGE": 2, "CONTENT": {"CONTENT": {"word_ids": ["word_219_48"], "coordinates": {"y0": 377, "x0": 1394, "y1": 406, "x1": 1531}, "raw_text_unformatted": "$9,071.50", "value": "9071.50"}}, "CONFIDENCE": 0.999934732913971, "ENTITY_TYPE": "CURRENCY"}, {"ENTITY_ID": "ad6025cd-3cfc-4e6c-bf44-9bd9c74b4c07", "PAGE": 2, "CONTENT": {"CONTENT": {"word_ids": ["word_219_50"], "coordinates": {"y0": 417, "x0": 249, "y1": 439, "x1": 302}, "raw_text_unformatted": "2.25", "value": "2.25"}}, "CONFIDENCE": 0.8166747689247131, "ENTITY_TYPE": "CURRENCY"}, {"ENTITY_ID": "01f9fdd6-3c48-4ca4-b741-6410026d250f", "PAGE": 2, "CONTENT": {"CONTENT": {"word_ids": ["word_219_56"], "coordinates": {"y0": 421, "x0": 1329, "y1": 449, "x1": 1453}, "raw_text_unformatted": "$7,726.50", "value": "7726.50"}}, "CONFIDENCE": 0.9998180270195007, "ENTITY_TYPE": "CURRENCY"}, {"ENTITY_ID": "4491c4aa-e580-4a08-8794-cfda237c9c3e", "PAGE": 2, "CONTENT": {"CONTENT": {"word_ids": ["word_219_59"], "coordinates": {"y0": 461, "x0": 1340, "y1": 494, "x1": 1453}, "raw_text_unformatted": "$350.00", "value": "350.00"}}, "CONFIDENCE": 0.9988523721694946, "ENTITY_TYPE": "CURRENCY"}, {"ENTITY_ID": "b1408377-a26c-4067-ae2c-dcd01ed05356", "PAGE": 2, "CONTENT": {"CONTENT": {"word_ids": ["word_219_62"], "coordinates": {"y0": 496, "x0": 1351, "y1": 547, "x1": 1453}, "raw_text_unformatted": "$995.00", "value": "995.00"}}, "CONFIDENCE": 0.999713122844696, "ENTITY_TYPE": "CURRENCY"}, {"ENTITY_ID": "64b7a641-5c44-44e1-8d87-c8f31728fee1", "PAGE": 2, "CONTENT": {"CONTENT": {"word_ids": ["word_219_71"], "coordinates": {"y0": 738, "x0": 1403, "y1": 765, "x1": 1515}, "raw_text_unformatted": "$873.76", "value": "873.76"}}, "CONFIDENCE": 0.9998923540115356, "ENTITY_TYPE": "CURRENCY"}, {"ENTITY_ID": "87856323-bd5c-4c41-80ed-afd1562ddcb7", "PAGE": 2, "CONTENT": {"CONTENT": {"word_ids": ["word_219_85"], "coordinates": {"y0": 816, "x0": 1348, "y1": 858, "x1": 1450}, "raw_text_unformatted": "$308.76", "value": "308.76"}}, "CONFIDENCE": 0.9959466457366943, "ENTITY_TYPE": "CURRENCY"}, {"ENTITY_ID": "c9983eb4-7571-4f69-bd9c-9260c82e6639", "PAGE": 2, "CONTENT": {"CONTENT": {"word_ids": ["word_219_94"], "coordinates": {"y0": 859, "x0": 1364, "y1": 885, "x1": 1449}, "raw_text_unformatted": "$12.00", "value": "12.00"}}, "CONFIDENCE": 0.9826408624649048, "ENTITY_TYPE": "CURRENCY"}, {"ENTITY_ID": "5f9a98f9-2d1f-43ef-9513-7731bca083a9", "PAGE": 2, "CONTENT": {"CONTENT": {"word_ids": ["word_219_105"], "coordinates": {"y0": 899, "x0": 1364, "y1": 925, "x1": 1449}, "raw_text_unformatted": "$78.00", "value": "78.00"}}, "CONFIDENCE": 0.9996996521949768, "ENTITY_TYPE": "CURRENCY"}, {"ENTITY_ID": "21fc67a5-985b-43a7-8af9-052821f88300", "PAGE": 2, "CONTENT": {"CONTENT": {"word_ids": ["word_219_121"], "coordinates": {"y0": 1177, "x0": 1386, "y1": 1204, "x1": 1523}, "raw_text_unformatted": "$2,929.33", "value": "2929.33"}}, "CONFIDENCE": 0.9998340010643005, "ENTITY_TYPE": "CURRENCY"}, {"ENTITY_ID": "330b8e61-695a-4b7b-bfdb-6a1a909e8d17", "PAGE": 2, "CONTENT": {"CONTENT": {"word_ids": ["word_219_154"], "coordinates": {"y0": 1298, "x0": 1345, "y1": 1331, "x1": 1446}, "raw_text_unformatted": "$250.00", "value": "250.00"}}, "CONFIDENCE": 0.9995114803314209, "ENTITY_TYPE": "CURRENCY"}, {"ENTITY_ID": "3d6637f0-00d5-4ced-99e3-e97fd36e9e2c", "PAGE": 2, "CONTENT": {"CONTENT": {"word_ids": ["word_219_164"], "coordinates": {"y0": 1337, "x0": 1360, "y1": 1363, "x1": 1446}, "raw_text_unformatted": "$50.00", "value": "50.00"}}, "CONFIDENCE": 0.9990247488021851, "ENTITY_TYPE": "CURRENCY"}, {"ENTITY_ID": "d13b9ec2-c25f-4632-9249-b11f387c3302", "PAGE": 2, "CONTENT": {"CONTENT": {"word_ids": ["word_219_175"], "coordinates": {"y0": 1376, "x0": 1344, "y1": 1402, "x1": 1446}, "raw_text_unformatted": "$463.00", "value": "463.00"}}, "CONFIDENCE": 0.9982507824897766, "ENTITY_TYPE": "CURRENCY"}, {"ENTITY_ID": "bea97486-c5a6-4e72-843e-7cf82470d4cd", "PAGE": 2, "CONTENT": {"CONTENT": {"word_ids": ["word_219_186"], "coordinates": {"y0": 1415, "x0": 1320, "y1": 1443, "x1": 1445}, "raw_text_unformatted": "$1,350.00", "value": "1350.00"}}, "CONFIDENCE": 0.9979121685028076, "ENTITY_TYPE": "CURRENCY"}, {"ENTITY_ID": "2e3f2579-0a5a-454d-a386-ca49f38753ee", "PAGE": 2, "CONTENT": {"CONTENT": {"word_ids": ["word_219_203"], "coordinates": {"y0": 1532, "x0": 1372, "y1": 1564, "x1": 1530}, "raw_text_unformatted": "$12,874.59", "value": "12874.59"}}, "CONFIDENCE": 0.9992852210998535, "ENTITY_TYPE": "CURRENCY"}, {"ENTITY_ID": "fef7753c-e53e-43be-9ea3-6d1e048aac2c", "PAGE": 2, "CONTENT": {"CONTENT": {"word_ids": ["word_219_214"], "coordinates": {"y0": 1580, "x0": 1557, "y1": 1606, "x1": 1659}, "raw_text_unformatted": "$475.00", "value": "475.00"}}, "CONFIDENCE": 0.9757640361785889, "ENTITY_TYPE": "CURRENCY"}, {"ENTITY_ID": "6acfe356-0285-4b80-a8c0-be0fdb102561", "PAGE": 2, "CONTENT": {"CONTENT": {"word_ids": ["word_219_221"], "coordinates": {"y0": 1746, "x0": 933, "y1": 1748, "x1": 935}, "raw_text_unformatted": "3", "value": "3"}}, "CONFIDENCE": 0.7263644337654114, "ENTITY_TYPE": "CURRENCY"}, {"ENTITY_ID": "9d4ed0cc-8339-4f5c-899b-4172bbf7a723", "PAGE": 2, "CONTENT": {"CONTENT": {"word_ids": ["word_219_224"], "coordinates": {"y0": 1731, "x0": 1382, "y1": 1759, "x1": 1519}, "raw_text_unformatted": "$1,848.15", "value": "1848.15"}}, "CONFIDENCE": 0.9919639825820923, "ENTITY_TYPE": "CURRENCY"}, {"ENTITY_ID": "e895086f-ab77-437c-b8f4-581834b3cfce", "PAGE": 2, "CONTENT": {"CONTENT": {"word_ids": ["word_219_232"], "coordinates": {"y0": 1774, "x0": 839, "y1": 1797, "x1": 876}, "raw_text_unformatted": "00", "value": "00"}}, "CONFIDENCE": 0.9796484112739563, "ENTITY_TYPE": "CURRENCY"}, {"ENTITY_ID": "d9bb8de9-7602-4240-9f25-c649b7d90750", "PAGE": 2, "CONTENT": {"CONTENT": {"word_ids": ["word_219_234"], "coordinates": {"y0": 1773, "x0": 1075, "y1": 1807, "x1": 1185}, "raw_text_unformatted": "$237.00", "value": "237.00"}}, "CONFIDENCE": 0.9994678497314453, "ENTITY_TYPE": "CURRENCY"}, {"ENTITY_ID": "f4c7544c-03ec-401e-8672-d4e549dee826", "PAGE": 2, "CONTENT": {"CONTENT": {"word_ids": ["word_219_235"], "coordinates": {"y0": 1775, "x0": 1341, "y1": 1807, "x1": 1445}, "raw_text_unformatted": "$609.00", "value": "609.00"}}, "CONFIDENCE": 0.9864665865898132, "ENTITY_TYPE": "CURRENCY"}, {"ENTITY_ID": "8e336ede-64d9-4a15-9f8e-ebeb6a50e6c3", "PAGE": 2, "CONTENT": {"CONTENT": {"word_ids": ["word_219_252"], "coordinates": {"y0": 1855, "x0": 1746, "y1": 1882, "x1": 1870}, "raw_text_unformatted": "$1,616.00", "value": "1616.00"}}, "CONFIDENCE": 0.9997522830963135, "ENTITY_TYPE": "CURRENCY"}, {"ENTITY_ID": "372367bb-faf8-425e-9be9-4fdfe466f579", "PAGE": 2, "CONTENT": {"CONTENT": {"word_ids": ["word_219_259"], "coordinates": {"y0": 1895, "x0": 1381, "y1": 1924, "x1": 1518}, "raw_text_unformatted": "$1,972.25", "value": "1972.25"}}, "CONFIDENCE": 0.9854373931884766, "ENTITY_TYPE": "CURRENCY"}, {"ENTITY_ID": "70f7632f-32fc-4e0a-a002-6eabe7189237", "PAGE": 2, "CONTENT": {"CONTENT": {"word_ids": ["word_219_265"], "coordinates": {"y0": 1937, "x0": 689, "y1": 1968, "x1": 733}, "raw_text_unformatted": "12", "value": "12"}}, "CONFIDENCE": 0.9309079051017761, "ENTITY_TYPE": "CURRENCY"}, {"ENTITY_ID": "bcbbc5d0-0c93-4697-8bf4-a06ce4415ff0", "PAGE": 2, "CONTENT": {"CONTENT": {"word_ids": ["word_219_278", "word_219_279"], "coordinates": {"y0": 2005, "x0": 469, "y1": 2046, "x1": 569}, "raw_text_unformatted": "$42 2.925", "value": "422.925"}}, "CONFIDENCE": 0.9520085453987122, "ENTITY_TYPE": "CURRENCY"}, {"ENTITY_ID": "ae29cd86-c252-4e8f-878d-7574b0996c3a", "PAGE": 2, "CONTENT": {"CONTENT": {"word_ids": ["word_219_284"], "coordinates": {"y0": 2017, "x0": 840, "y1": 2040, "x1": 855}, "raw_text_unformatted": "9", "value": "9"}}, "CONFIDENCE": 0.5413759350776672, "ENTITY_TYPE": "CURRENCY"}, {"ENTITY_ID": "39d762bd-7ecb-4a52-9395-6dff10c91d6e", "PAGE": 2, "CONTENT": {"CONTENT": {"word_ids": ["word_219_286", "word_219_287"], "coordinates": {"y0": 2006, "x0": 898, "y1": 2048, "x1": 982}, "raw_text_unformatted": "2 119", "value": "2119"}}, "CONFIDENCE": 0.9685831069946289, "ENTITY_TYPE": "CURRENCY"}, {"ENTITY_ID": "c55ec5cc-0c6b-42f7-bcf1-a7d46dfbe681", "PAGE": 2, "CONTENT": {"CONTENT": {"word_ids": ["word_219_288"], "coordinates": {"y0": 2009, "x0": 1313, "y1": 2050, "x1": 1439}, "raw_text_unformatted": "$42925", "value": "42925"}}, "CONFIDENCE": 0.9509624242782593, "ENTITY_TYPE": "CURRENCY"}, {"ENTITY_ID": "6db825d6-410d-42cb-a11e-64d447a7802e", "PAGE": 2, "CONTENT": {"CONTENT": {"word_ids": ["word_219_292"], "coordinates": {"y0": 2053, "x0": 437, "y1": 2080, "x1": 477}, "raw_text_unformatted": "12", "value": "12"}}, "CONFIDENCE": 0.8412981033325195, "ENTITY_TYPE": "CURRENCY"}, {"ENTITY_ID": "48a05164-68c9-4790-a39a-dacce4647f06", "PAGE": 2, "CONTENT": {"CONTENT": {"word_ids": ["word_219_298", "word_219_299", "word_219_300"], "coordinates": {"y0": 2047, "x0": 186, "y1": 2114, "x1": 1440}, "raw_text_unformatted": "$1 ,066.00 05", "value": "1066.0005"}}, "CONFIDENCE": 0.9099535942077637, "ENTITY_TYPE": "CURRENCY"}, {"ENTITY_ID": "b2a0fe0a-a55a-4aab-8612-d5ff81b717a5", "PAGE": 2, "CONTENT": {"CONTENT": {"word_ids": ["word_219_307"], "coordinates": {"y0": 2140, "x0": 1378, "y1": 2167, "x1": 1516}, "raw_text_unformatted": "$1,113.37", "value": "1113.37"}}, "CONFIDENCE": 0.9991515874862671, "ENTITY_TYPE": "CURRENCY"}, {"ENTITY_ID": "b0a07444-8c57-4dd4-88ba-843f24c18806", "PAGE": 2, "CONTENT": {"CONTENT": {"word_ids": ["word_219_311"], "coordinates": {"y0": 2179, "x0": 588, "y1": 2212, "x1": 695}, "raw_text_unformatted": "$39.75", "value": "39.75"}}, "CONFIDENCE": 0.9562898874282837, "ENTITY_TYPE": "CURRENCY"}, {"ENTITY_ID": "07092bfa-7ae0-4644-8bca-5b6107e00e4f", "PAGE": 2, "CONTENT": {"CONTENT": {"word_ids": ["word_219_315"], "coordinates": {"y0": 2175, "x0": 893, "y1": 2218, "x1": 908}, "raw_text_unformatted": "4", "value": "4"}}, "CONFIDENCE": 0.9749761819839478, "ENTITY_TYPE": "CURRENCY"}, {"ENTITY_ID": "5156c51b-ef8e-415c-9848-12e1048fa8fe", "PAGE": 2, "CONTENT": {"CONTENT": {"word_ids": ["word_219_330"], "coordinates": {"y0": 2248, "x0": 593, "y1": 2284, "x1": 694}, "raw_text_unformatted": "$80.73", "value": "80.73"}}, "CONFIDENCE": 0.9318249225616455, "ENTITY_TYPE": "CURRENCY"}, {"ENTITY_ID": "a0d41143-8509-4ce3-944d-10c18b872efd", "PAGE": 2, "CONTENT": {"CONTENT": {"word_ids": ["word_219_334"], "coordinates": {"y0": 2261, "x0": 895, "y1": 2283, "x1": 908}, "raw_text_unformatted": "3", "value": "3"}}, "CONFIDENCE": 0.9116923809051514, "ENTITY_TYPE": "CURRENCY"}, {"ENTITY_ID": "0ea9afc2-22e9-4987-a5a7-5095d95735b5", "PAGE": 2, "CONTENT": {"CONTENT": {"word_ids": ["word_219_336"], "coordinates": {"y0": 2261, "x0": 1336, "y1": 2287, "x1": 1438}, "raw_text_unformatted": "$242.19", "value": "242.19"}}, "CONFIDENCE": 0.9950835108757019, "ENTITY_TYPE": "CURRENCY"}, {"ENTITY_ID": "6050fe70-adb3-4ca7-afa8-e941c298d8d4", "PAGE": 2, "CONTENT": {"CONTENT": {"word_ids": ["word_219_340"], "coordinates": {"y0": 2297, "x0": 593, "y1": 2323, "x1": 695}, "raw_text_unformatted": "$201.29", "value": "201.29"}}, "CONFIDENCE": 0.8763458728790283, "ENTITY_TYPE": "CURRENCY"}, {"ENTITY_ID": "c31f16dd-fcef-4368-88f3-b20f64c74cec", "PAGE": 2, "CONTENT": {"CONTENT": {"word_ids": ["word_219_344"], "coordinates": {"y0": 2301, "x0": 895, "y1": 2323, "x1": 909}, "raw_text_unformatted": "7", "value": "7"}}, "CONFIDENCE": 0.9471402764320374, "ENTITY_TYPE": "CURRENCY"}, {"ENTITY_ID": "8cbb9959-d4a2-4f00-b899-282088e045e6", "PAGE": 2, "CONTENT": {"CONTENT": {"word_ids": ["word_219_346"], "coordinates": {"y0": 2301, "x0": 1313, "y1": 2333, "x1": 1437}, "raw_text_unformatted": "$1,409.03", "value": "1409.03"}}, "CONFIDENCE": 0.9929182529449463, "ENTITY_TYPE": "CURRENCY"}, {"ENTITY_ID": "7cf947d7-3910-44cf-916f-d8346e901eb8", "PAGE": 2, "CONTENT": {"CONTENT": {"word_ids": ["word_219_350"], "coordinates": {"y0": 2336, "x0": 609, "y1": 2363, "x1": 694}, "raw_text_unformatted": "$43.82", "value": "43.82"}}, "CONFIDENCE": 0.8706058859825134, "ENTITY_TYPE": "CURRENCY"}, {"ENTITY_ID": "1938820c-af49-4fed-bccc-cf7db8c1bfb0", "PAGE": 2, "CONTENT": {"CONTENT": {"word_ids": ["word_219_354"], "coordinates": {"y0": 2340, "x0": 896, "y1": 2362, "x1": 925}, "raw_text_unformatted": "10", "value": "10"}}, "CONFIDENCE": 0.9799095988273621, "ENTITY_TYPE": "CURRENCY"}, {"ENTITY_ID": "7b54b37a-f294-4bf0-87ef-bad38f91beea", "PAGE": 2, "CONTENT": {"CONTENT": {"word_ids": ["word_219_356"], "coordinates": {"y0": 2340, "x0": 1335, "y1": 2366, "x1": 1437}, "raw_text_unformatted": "$438.20", "value": "438.20"}}, "CONFIDENCE": 0.9950206875801086, "ENTITY_TYPE": "CURRENCY"}, {"ENTITY_ID": "48914fd6-a136-4897-be79-cefb283f0f26", "PAGE": 2, "CONTENT": {"CONTENT": {"word_ids": ["word_219_376"], "coordinates": {"y0": 2501, "x0": 1375, "y1": 2530, "x1": 1513}, "raw_text_unformatted": "$2,906.00", "value": "2906.00"}}, "CONFIDENCE": 0.999495804309845, "ENTITY_TYPE": "CURRENCY"}, {"ENTITY_ID": "3c47e1bb-7275-4c60-b375-940ba87c2442", "PAGE": 2, "CONTENT": {"CONTENT": {"word_ids": ["word_219_385"], "coordinates": {"y0": 2545, "x0": 1333, "y1": 2570, "x1": 1435}, "raw_text_unformatted": "$672.00", "value": "672.00"}}, "CONFIDENCE": 0.9974086284637451, "ENTITY_TYPE": "CURRENCY"}, {"ENTITY_ID": "201f734e-abd0-43da-ac27-31dd2cf76ea3", "PAGE": 2, "CONTENT": {"CONTENT": {"word_ids": ["word_219_407"], "coordinates": {"y0": 2623, "x0": 1333, "y1": 2656, "x1": 1437}, "raw_text_unformatted": "$448.00", "value": "448.00"}}, "CONFIDENCE": 0.9960414171218872, "ENTITY_TYPE": "CURRENCY"}, {"ENTITY_ID": "a86b1263-4d25-4d5e-84a7-3339f167c41e", "PAGE": 2, "CONTENT": {"CONTENT": {"word_ids": ["word_219_423"], "coordinates": {"y0": 2824, "x0": 1372, "y1": 2852, "x1": 1510}, "raw_text_unformatted": "$7,839.77", "value": "7839.77"}}, "CONFIDENCE": 0.9997566938400269, "ENTITY_TYPE": "CURRENCY"}, {"ENTITY_ID": "e1af9b0a-4236-4507-b6de-cf6339808553", "PAGE": 2, "CONTENT": {"CONTENT": {"word_ids": ["word_219_442"], "coordinates": {"y0": 2955, "x0": 1354, "y1": 2985, "x1": 1518}, "raw_text_unformatted": "$20,714.36", "value": "20714.36"}}, "CONFIDENCE": 0.999441385269165, "ENTITY_TYPE": "CURRENCY"}, {"ENTITY_ID": "ef632947-a1cd-4f42-b88a-b522db36bf93", "PAGE": 2, "CONTENT": {"CONTENT": {"word_ids": ["word_219_477"], "coordinates": {"y0": 3130, "x0": 2093, "y1": 3153, "x1": 2267}, "raw_text_unformatted": "10118070528", "value": "10118070528"}}, "CONFIDENCE": 0.8510686159133911, "ENTITY_TYPE": "CURRENCY"}, {"ENTITY_ID": "e8872a89-4e81-4ce8-8a15-db6d892b410b", "PAGE": 7, "CONTENT": {"CONTENT": {"word_ids": ["word_724_38"], "coordinates": {"y0": 3082, "x0": 1122, "y1": 3098, "x1": 1168}, "raw_text_unformatted": "1%", "value": "1"}}, "CONFIDENCE": 0.6681768894195557, "ENTITY_TYPE": "CURRENCY"}, {"ENTITY_ID": "85a31771-df99-4a52-86ea-9a756801dc77", "PAGE": 3, "CONTENT": {"CONTENT": {"word_ids": ["word_320_81", "word_320_82"], "coordinates": {"y0": 690, "x0": 952, "y1": 716, "x1": 1218}, "raw_text_unformatted": "50 $01", "value": "50 $01"}}, "CONFIDENCE": 0.7859300374984741, "ENTITY_TYPE": "OTHER"}, {"ENTITY_ID": "323284c9-59f1-44da-b2c2-d566cee55a4a", "PAGE": 2, "CONTENT": {"CONTENT": {"word_ids": ["word_219_448", "word_219_449"], "coordinates": {"y0": 2996, "x0": 553, "y1": 3034, "x1": 1432}, "raw_text_unformatted": "1 $19,762.36", "value": "1 $19,762.36"}}, "CONFIDENCE": 0.9994984269142151, "ENTITY_TYPE": "OTHER"}, {"ENTITY_ID": "c051d0c3-167e-409e-9200-7ee28b867505", "PAGE": 2, "CONTENT": {"CONTENT": {"word_ids": ["word_219_450", "word_219_451"], "coordinates": {"y0": 2997, "x0": 1544, "y1": 3035, "x1": 1860}, "raw_text_unformatted": "$952.00 $2,466.00", "value": "$952.00 $2,466.00"}}, "CONFIDENCE": 0.995691180229187, "ENTITY_TYPE": "OTHER"}, {"ENTITY_ID": "0878aadf-6fd4-4837-a4d0-4982586a27b9-ROUTE", "PAGE": 6, "CONTENT": {"CONTENT": {"word_ids": ["word_623_22", "word_623_23", "word_623_24"], "coordinates": {"y0": 539, "x0": 508, "y1": 567, "x1": 780}, "raw_text_unformatted": "64 Jefferson Street", "value": "64 Jefferson Street"}}, "CONFIDENCE": 0.9762228727340698, "ENTITY_TYPE": "ROUTE"}, {"ENTITY_ID": "ba6eee8e-3de6-406c-9cbe-d9b20241701e-ROUTE", "PAGE": 5, "CONTENT": {"CONTENT": {"word_ids": ["word_522_406", "word_522_407", "word_522_408"], "coordinates": {"y0": 1945, "x0": 586, "y1": 1981, "x1": 801}, "raw_text_unformatted": "1 Periman Drive", "value": "1 Periman Drive"}}, "CONFIDENCE": 0.8621417284011841, "ENTITY_TYPE": "ROUTE"}, {"ENTITY_ID": "e6307a10-aad8-45b4-a1f7-aca1954aafb3-ROUTE", "PAGE": 5, "CONTENT": {"CONTENT": {"word_ids": ["word_522_462", "word_522_463", "word_522_464"], "coordinates": {"y0": 1948, "x0": 2151, "y1": 1992, "x1": 2279}, "raw_text_unformatted": "s ?\u0080\u0099Ave nue,", "value": "s ?\u0080\u0099Ave nue,"}}, "CONFIDENCE": 0.9559615254402161, "ENTITY_TYPE": "ROUTE"}, {"ENTITY_ID": "7879dedb-c996-48e9-8e0e-c9f303becb59-ROUTE", "PAGE": 1, "CONTENT": {"CONTENT": {"word_ids": ["word_118_47", "word_118_48", "word_118_49"], "coordinates": {"y0": 554, "x0": 1099, "y1": 582, "x1": 1354}, "raw_text_unformatted": "281 Hewes Street", "value": "281 Hewes Street"}}, "CONFIDENCE": 0.9334012269973755, "ENTITY_TYPE": "ROUTE"}, {"ENTITY_ID": "16643436-b0e5-4d4e-ab02-dd5fe9c585e5-ROUTE", "PAGE": 1, "CONTENT": {"CONTENT": {"word_ids": ["word_118_74", "word_118_75", "word_118_76"], "coordinates": {"y0": 685, "x0": 1100, "y1": 715, "x1": 1257}, "raw_text_unformatted": "149 Elm St,", "value": "149 Elm St,"}}, "CONFIDENCE": 0.7222726941108704, "ENTITY_TYPE": "ROUTE"}, {"ENTITY_ID": "f8fc4e29-dcf1-48db-a1e8-45702a753982-ROUTE", "PAGE": 1, "CONTENT": {"CONTENT": {"word_ids": ["word_118_84", "word_118_85"], "coordinates": {"y0": 725, "x0": 554, "y1": 759, "x1": 750}, "raw_text_unformatted": "Teverya Way,", "value": "Teverya Way,"}}, "CONFIDENCE": 0.8734784126281738, "ENTITY_TYPE": "ROUTE"}, {"ENTITY_ID": "5c4d65df-4e90-4dcd-8584-b3c80e60c624-ROUTE", "PAGE": 4, "CONTENT": {"CONTENT": {"word_ids": ["word_421_316", "word_421_317", "word_421_318"], "coordinates": {"y0": 2305, "x0": 179, "y1": 2338, "x1": 399}, "raw_text_unformatted": "4 Teverya Way,", "value": "4 Teverya Way,"}}, "CONFIDENCE": 0.9226349592208862, "ENTITY_TYPE": "ROUTE"}, {"ENTITY_ID": "ad7c613a-fda6-4d26-8422-af31bd2849c4-ROUTE", "PAGE": 7, "CONTENT": {"CONTENT": {"word_ids": ["word_724_30", "word_724_31", "word_724_32"], "coordinates": {"y0": 530, "x0": 512, "y1": 559, "x1": 786}, "raw_text_unformatted": "64 Jefferson Street", "value": "64 Jefferson Street"}}, "CONFIDENCE": 0.952567458152771, "ENTITY_TYPE": "ROUTE"}, {"ENTITY_ID": "7e26ad61-5d9f-4928-b658-865a03ed3234", "PAGE": 6, "CONTENT": {"CONTENT": {"word_ids": ["word_623_127", "word_623_128", "word_623_129"], "coordinates": {"y0": 3158, "x0": 179, "y1": 3182, "x1": 459}, "raw_text_unformatted": "01/22/2019 07:23 AM", "value": "01/22/2019"}}, "CONFIDENCE": 0.9799090623855591, "ENTITY_TYPE": "DATE"}, {"ENTITY_ID": "336df745-97d8-45d3-b70d-5ec5a0678333", "PAGE": 5, "CONTENT": {"CONTENT": {"word_ids": ["word_522_514"], "coordinates": {"y0": 2977, "x0": 1100, "y1": 3037, "x1": 1126}, "raw_text_unformatted": "9", "value": "08/09/2020"}}, "CONFIDENCE": 0.5519296526908875, "ENTITY_TYPE": "DATE"}, {"ENTITY_ID": "952392d4-9c3f-4c41-9f76-55ec26f96e6a", "PAGE": 1, "CONTENT": {"CONTENT": {"word_ids": ["word_118_37"], "coordinates": {"y0": 509, "x0": 534, "y1": 536, "x1": 683}, "raw_text_unformatted": "1/22/2019", "value": "01/22/2019"}}, "CONFIDENCE": 0.9990948438644409, "ENTITY_TYPE": "DATE"}, {"ENTITY_ID": "5f2f343e-8140-46c3-9940-38636ffcfdc4", "PAGE": 1, "CONTENT": {"CONTENT": {"word_ids": ["word_118_46"], "coordinates": {"y0": 546, "x0": 533, "y1": 587, "x1": 682}, "raw_text_unformatted": "1/22/2019", "value": "01/22/2019"}}, "CONFIDENCE": 0.9994538426399231, "ENTITY_TYPE": "DATE"}, {"ENTITY_ID": "22a06145-c61b-4a64-b909-3381caba9567", "PAGE": 1, "CONTENT": {"CONTENT": {"word_ids": ["word_118_54"], "coordinates": {"y0": 595, "x0": 533, "y1": 622, "x1": 682}, "raw_text_unformatted": "1/22/2019", "value": "01/22/2019"}}, "CONFIDENCE": 0.9981333613395691, "ENTITY_TYPE": "DATE"}, {"ENTITY_ID": "8349aeb8-b9f6-40fe-a7ff-107e005cf365", "PAGE": 4, "CONTENT": {"CONTENT": {"word_ids": ["word_421_348", "word_421_349", "word_421_350"], "coordinates": {"y0": 3163, "x0": 169, "y1": 3187, "x1": 450}, "raw_text_unformatted": "01/22/2019 07:23 AM", "value": "01/22/2019"}}, "CONFIDENCE": 0.9300360679626465, "ENTITY_TYPE": "DATE"}, {"ENTITY_ID": "1f31e298-6cf6-4ee1-a674-6068f7ffc6b6", "PAGE": 3, "CONTENT": {"CONTENT": {"word_ids": ["word_320_249"], "coordinates": {"y0": 1594, "x0": 512, "y1": 1639, "x1": 628}, "raw_text_unformatted": "12/05/18", "value": "12/05/2018"}}, "CONFIDENCE": 0.986336350440979, "ENTITY_TYPE": "DATE"}, {"ENTITY_ID": "9d773bb1-c1be-4d5e-9630-23c4d43e12bb", "PAGE": 3, "CONTENT": {"CONTENT": {"word_ids": ["word_320_251"], "coordinates": {"y0": 1594, "x0": 679, "y1": 1630, "x1": 802}, "raw_text_unformatted": "12/31/18", "value": "12/31/2018"}}, "CONFIDENCE": 0.96504807472229, "ENTITY_TYPE": "DATE"}, {"ENTITY_ID": "a22853d4-155c-4114-8909-256753854654", "PAGE": 3, "CONTENT": {"CONTENT": {"word_ids": ["word_320_256"], "coordinates": {"y0": 1598, "x0": 1610, "y1": 1633, "x1": 1725}, "raw_text_unformatted": "12/05/18", "value": "12/05/2018"}}, "CONFIDENCE": 0.782585084438324, "ENTITY_TYPE": "DATE"}, {"ENTITY_ID": "8e553483-888f-450b-9ff4-f1c129f98e66", "PAGE": 3, "CONTENT": {"CONTENT": {"word_ids": ["word_320_258"], "coordinates": {"y0": 1610, "x0": 1792, "y1": 1633, "x1": 1906}, "raw_text_unformatted": "12/31/18", "value": "12/31/2018"}}, "CONFIDENCE": 0.9364147186279297, "ENTITY_TYPE": "DATE"}, {"ENTITY_ID": "30965bd0-af14-446a-9ec8-92d21f4a52ae", "PAGE": 3, "CONTENT": {"CONTENT": {"word_ids": ["word_320_282"], "coordinates": {"y0": 1726, "x0": 1519, "y1": 1771, "x1": 1801}, "raw_text_unformatted": "12/05/18", "value": "12/05/2018"}}, "CONFIDENCE": 0.8541441559791565, "ENTITY_TYPE": "DATE"}, {"ENTITY_ID": "e2997179-f47c-483c-a4bf-a046f0d89fc6", "PAGE": 3, "CONTENT": {"CONTENT": {"word_ids": ["word_320_284"], "coordinates": {"y0": 1726, "x0": 1679, "y1": 1771, "x1": 1799}, "raw_text_unformatted": "08/31/19", "value": "08/31/2019"}}, "CONFIDENCE": 0.3699354827404022, "ENTITY_TYPE": "DATE"}, {"ENTITY_ID": "dbbb83bd-ac81-4aea-8743-c2e1391dae9d", "PAGE": 3, "CONTENT": {"CONTENT": {"word_ids": ["word_320_294"], "coordinates": {"y0": 1769, "x0": 1517, "y1": 1815, "x1": 1642}, "raw_text_unformatted": "12/05/18", "value": "12/05/2018"}}, "CONFIDENCE": 0.9890521168708801, "ENTITY_TYPE": "DATE"}, {"ENTITY_ID": "4d163966-2034-45fa-be28-2a45f9b26b2b", "PAGE": 3, "CONTENT": {"CONTENT": {"word_ids": ["word_320_296"], "coordinates": {"y0": 1770, "x0": 1684, "y1": 1804, "x1": 1802}, "raw_text_unformatted": "05/31/19", "value": "05/31/2019"}}, "CONFIDENCE": 0.9870189428329468, "ENTITY_TYPE": "DATE"}, {"ENTITY_ID": "32a7a651-b3d1-4dfa-aefd-6f6883ba3c83", "PAGE": 3, "CONTENT": {"CONTENT": {"word_ids": ["word_320_515", "word_320_516", "word_320_517", "word_320_518"], "coordinates": {"y0": 3164, "x0": 169, "y1": 3189, "x1": 507}, "raw_text_unformatted": "01/22/2019 07:23 AM PST", "value": "01/22/2019"}}, "CONFIDENCE": 0.8938923478126526, "ENTITY_TYPE": "DATE"}, {"ENTITY_ID": "7f8fb80c-f786-4b62-a86f-5499a29fd5f4", "PAGE": 2, "CONTENT": {"CONTENT": {"word_ids": ["word_219_283"], "coordinates": {"y0": 2007, "x0": 757, "y1": 2047, "x1": 834}, "raw_text_unformatted": "1/22/1", "value": "01/22/2001"}}, "CONFIDENCE": 0.9933624267578125, "ENTITY_TYPE": "DATE"}, {"ENTITY_ID": "43416d6d-b654-4578-b1bf-5218dfe51816", "PAGE": 7, "CONTENT": {"CONTENT": {"word_ids": ["word_724_62", "word_724_63", "word_724_64"], "coordinates": {"y0": 3149, "x0": 196, "y1": 3177, "x1": 480}, "raw_text_unformatted": "01/22/2019 07:23 AM", "value": "01/22/2019"}}, "CONFIDENCE": 0.7593056559562683, "ENTITY_TYPE": "DATE"}, {"ENTITY_ID": "0878aadf-6fd4-4837-a4d0-4982586a27b9-CITY", "PAGE": 6, "CONTENT": {"CONTENT": {"word_ids": ["word_623_25", "word_623_26"], "coordinates": {"y0": 578, "x0": 508, "y1": 613, "x1": 724}, "raw_text_unformatted": "Highland Mills,", "value": "Highland Mills,"}}, "CONFIDENCE": 0.9762228727340698, "ENTITY_TYPE": "CITY"}, {"ENTITY_ID": "ba6eee8e-3de6-406c-9cbe-d9b20241701e-CITY", "PAGE": 5, "CONTENT": {"CONTENT": {"word_ids": ["word_522_411", "word_522_412"], "coordinates": {"y0": 2027, "x0": 592, "y1": 2058, "x1": 769}, "raw_text_unformatted": "Spring Valley,", "value": "Spring Valley,"}}, "CONFIDENCE": 0.8621417284011841, "ENTITY_TYPE": "CITY"}, {"ENTITY_ID": "455dcf3e-53ca-4ce6-a559-79d06e8c5de2-CITY", "PAGE": 1, "CONTENT": {"CONTENT": {"word_ids": ["word_118_55"], "coordinates": {"y0": 598, "x0": 1099, "y1": 631, "x1": 1234}, "raw_text_unformatted": "Brooklyn,", "value": "Brooklyn,"}}, "CONFIDENCE": 0.9444655776023865, "ENTITY_TYPE": "CITY"}, {"ENTITY_ID": "873c2f4d-4e99-4536-90dd-77579ca9f132-CITY", "PAGE": 1, "CONTENT": {"CONTENT": {"word_ids": ["word_118_88"], "coordinates": {"y0": 728, "x0": 1097, "y1": 757, "x1": 1219}, "raw_text_unformatted": "Monroe,", "value": "Monroe,"}}, "CONFIDENCE": 0.8319730162620544, "ENTITY_TYPE": "CITY"}, {"ENTITY_ID": "63594adb-0b44-4403-b8f5-cfe60940688c-CITY", "PAGE": 1, "CONTENT": {"CONTENT": {"word_ids": ["word_118_93"], "coordinates": {"y0": 768, "x0": 530, "y1": 798, "x1": 652}, "raw_text_unformatted": "Monroe,", "value": "Monroe,"}}, "CONFIDENCE": 0.7904177308082581, "ENTITY_TYPE": "CITY"}, {"ENTITY_ID": "5c4d65df-4e90-4dcd-8584-b3c80e60c624-CITY", "PAGE": 4, "CONTENT": {"CONTENT": {"word_ids": ["word_421_321"], "coordinates": {"y0": 2306, "x0": 548, "y1": 2337, "x1": 673}, "raw_text_unformatted": "Monroe,", "value": "Monroe,"}}, "CONFIDENCE": 0.9226349592208862, "ENTITY_TYPE": "CITY"}, {"ENTITY_ID": "4fd046b9-2b68-4acd-aa7b-084e34060194-CITY", "PAGE": 2, "CONTENT": {"CONTENT": {"word_ids": ["word_219_295"], "coordinates": {"y0": 2054, "x0": 585, "y1": 2077, "x1": 658}, "raw_text_unformatted": "Town", "value": "Town"}}, "CONFIDENCE": 0.7303526997566223, "ENTITY_TYPE": "CITY"}, {"ENTITY_ID": "ad7c613a-fda6-4d26-8422-af31bd2849c4-CITY", "PAGE": 7, "CONTENT": {"CONTENT": {"word_ids": ["word_724_33", "word_724_34"], "coordinates": {"y0": 569, "x0": 514, "y1": 606, "x1": 730}, "raw_text_unformatted": "Highland Mills,", "value": "Highland Mills,"}}, "CONFIDENCE": 0.952567458152771, "ENTITY_TYPE": "CITY"}, {"ENTITY_ID": "0878aadf-6fd4-4837-a4d0-4982586a27b9-ZIPCODE", "PAGE": 6, "CONTENT": {"CONTENT": {"word_ids": ["word_623_28"], "coordinates": {"y0": 578, "x0": 787, "y1": 604, "x1": 874}, "raw_text_unformatted": "10930", "value": "10930"}}, "CONFIDENCE": 0.9762228727340698, "ENTITY_TYPE": "ZIPCODE"}, {"ENTITY_ID": "ba6eee8e-3de6-406c-9cbe-d9b20241701e-ZIPCODE", "PAGE": 5, "CONTENT": {"CONTENT": {"word_ids": ["word_522_414"], "coordinates": {"y0": 2029, "x0": 824, "y1": 2052, "x1": 901}, "raw_text_unformatted": "10977", "value": "10977"}}, "CONFIDENCE": 0.8621417284011841, "ENTITY_TYPE": "ZIPCODE"}, {"ENTITY_ID": "455dcf3e-53ca-4ce6-a559-79d06e8c5de2-ZIPCODE", "PAGE": 1, "CONTENT": {"CONTENT": {"word_ids": ["word_118_57"], "coordinates": {"y0": 599, "x0": 1297, "y1": 625, "x1": 1378}, "raw_text_unformatted": "11211", "value": "11211"}}, "CONFIDENCE": 0.9444655776023865, "ENTITY_TYPE": "ZIPCODE"}, {"ENTITY_ID": "873c2f4d-4e99-4536-90dd-77579ca9f132-ZIPCODE", "PAGE": 1, "CONTENT": {"CONTENT": {"word_ids": ["word_118_90"], "coordinates": {"y0": 730, "x0": 1288, "y1": 754, "x1": 1377}, "raw_text_unformatted": "10950", "value": "10950"}}, "CONFIDENCE": 0.8319730162620544, "ENTITY_TYPE": "ZIPCODE"}, {"ENTITY_ID": "63594adb-0b44-4403-b8f5-cfe60940688c-ZIPCODE", "PAGE": 1, "CONTENT": {"CONTENT": {"word_ids": ["word_118_95"], "coordinates": {"y0": 769, "x0": 722, "y1": 795, "x1": 810}, "raw_text_unformatted": "10950", "value": "10950"}}, "CONFIDENCE": 0.7904177308082581, "ENTITY_TYPE": "ZIPCODE"}, {"ENTITY_ID": "5c4d65df-4e90-4dcd-8584-b3c80e60c624-ZIPCODE", "PAGE": 4, "CONTENT": {"CONTENT": {"word_ids": ["word_421_323"], "coordinates": {"y0": 2308, "x0": 738, "y1": 2334, "x1": 825}, "raw_text_unformatted": "10950", "value": "10950"}}, "CONFIDENCE": 0.9226349592208862, "ENTITY_TYPE": "ZIPCODE"}, {"ENTITY_ID": "ad7c613a-fda6-4d26-8422-af31bd2849c4-ZIPCODE", "PAGE": 7, "CONTENT": {"CONTENT": {"word_ids": ["word_724_36"], "coordinates": {"y0": 569, "x0": 793, "y1": 595, "x1": 879}, "raw_text_unformatted": "10930", "value": "10930"}}, "CONFIDENCE": 0.952567458152771, "ENTITY_TYPE": "ZIPCODE"}, {"ENTITY_ID": "91821b68-3f7e-472c-af13-b4989b787d02_1", "PAGE": 6, "CONTENT": {"CONTENT": {"word_ids": ["word_623_21"], "coordinates": {"y0": 500, "x0": 662, "y1": 526, "x1": 749}, "raw_text_unformatted": "Hecht", "value": "Hecht"}}, "CONFIDENCE": 0.8723762631416321, "ENTITY_TYPE": "PERSON NAME"}, {"ENTITY_ID": "f5e1ebd7-6a0c-4244-a176-bb714e0801b3_1", "PAGE": 6, "CONTENT": {"CONTENT": {"word_ids": ["word_623_106"], "coordinates": {"y0": 1487, "x0": 175, "y1": 1515, "x1": 321}, "raw_text_unformatted": "Yehoshua", "value": "Yehoshua"}}, "CONFIDENCE": 0.831982433795929, "ENTITY_TYPE": "PERSON NAME"}, {"ENTITY_ID": "f5e1ebd7-6a0c-4244-a176-bb714e0801b3_2", "PAGE": 6, "CONTENT": {"CONTENT": {"word_ids": ["word_623_107"], "coordinates": {"y0": 1487, "x0": 331, "y1": 1514, "x1": 418}, "raw_text_unformatted": "Hecht", "value": "Hecht"}}, "CONFIDENCE": 0.831982433795929, "ENTITY_TYPE": "PERSON NAME"}, {"ENTITY_ID": "8ea542cc-e154-464e-ac21-020005171416_1", "PAGE": 6, "CONTENT": {"CONTENT": {"word_ids": ["word_623_123"], "coordinates": {"y0": 3113, "x0": 1960, "y1": 3136, "x1": 2034}, "raw_text_unformatted": "LOAN", "value": "LOAN"}}, "CONFIDENCE": 0.9310346841812134, "ENTITY_TYPE": "PERSON NAME"}, {"ENTITY_ID": "8ea542cc-e154-464e-ac21-020005171416_2", "PAGE": 6, "CONTENT": {"CONTENT": {"word_ids": ["word_623_124"], "coordinates": {"y0": 3113, "x0": 2042, "y1": 3136, "x1": 2067}, "raw_text_unformatted": "D", "value": "D"}}, "CONFIDENCE": 0.9310346841812134, "ENTITY_TYPE": "PERSON NAME"}, {"ENTITY_ID": "8ea542cc-e154-464e-ac21-020005171416", "PAGE": 6, "CONTENT": {"CONTENT": {"word_ids": ["word_623_123", "word_623_124"], "coordinates": {"y0": 3113, "x0": 1960, "y1": 3136, "x1": 2067}, "raw_text_unformatted": "LOAND", "value": "LOAN D"}}, "CONFIDENCE": 0.9310346841812134, "ENTITY_TYPE": "PERSON NAME"}, {"ENTITY_ID": "f5e1ebd7-6a0c-4244-a176-bb714e0801b3", "PAGE": 6, "CONTENT": {"CONTENT": {"word_ids": ["word_623_106", "word_623_107"], "coordinates": {"y0": 1487, "x0": 175, "y1": 1515, "x1": 418}, "raw_text_unformatted": "YehoshuaHecht", "value": "Yehoshua Hecht"}}, "CONFIDENCE": 0.831982433795929, "ENTITY_TYPE": "PERSON NAME"}, {"ENTITY_ID": "b2e45cc0-bf8b-4f1b-949d-eb20e12324df_1", "PAGE": 5, "CONTENT": {"CONTENT": {"word_ids": ["word_522_396"], "coordinates": {"y0": 1771, "x0": 451, "y1": 1794, "x1": 511}, "raw_text_unformatted": "G", "value": "G"}}, "CONFIDENCE": 0.4802803695201874, "ENTITY_TYPE": "PERSON NAME"}, {"ENTITY_ID": "b2e45cc0-bf8b-4f1b-949d-eb20e12324df_2", "PAGE": 5, "CONTENT": {"CONTENT": {"word_ids": ["word_522_397"], "coordinates": {"y0": 1795, "x0": 567, "y1": 1798, "x1": 569}, "raw_text_unformatted": "T", "value": "T"}}, "CONFIDENCE": 0.4802803695201874, "ENTITY_TYPE": "PERSON NAME"}, {"ENTITY_ID": "3b0d0029-806a-4c5d-b83d-3cd71ef49072_1", "PAGE": 5, "CONTENT": {"CONTENT": {"word_ids": ["word_522_423"], "coordinates": {"y0": 2260, "x0": 592, "y1": 2290, "x1": 714}, "raw_text_unformatted": "Benjamin", "value": "Benjamin"}}, "CONFIDENCE": 0.9937743544578552, "ENTITY_TYPE": "PERSON NAME"}, {"ENTITY_ID": "3b0d0029-806a-4c5d-b83d-3cd71ef49072_2", "PAGE": 5, "CONTENT": {"CONTENT": {"word_ids": ["word_522_424"], "coordinates": {"y0": 2260, "x0": 724, "y1": 2284, "x1": 804}, "raw_text_unformatted": "Hirsch", "value": "Hirsch"}}, "CONFIDENCE": 0.9937743544578552, "ENTITY_TYPE": "PERSON NAME"}, {"ENTITY_ID": "18ffa622-fdcb-4e99-b26b-9daf84161143_1", "PAGE": 5, "CONTENT": {"CONTENT": {"word_ids": ["word_522_471"], "coordinates": {"y0": 2263, "x0": 1975, "y1": 2292, "x1": 2036}, "raw_text_unformatted": "Jerry", "value": "Jerry"}}, "CONFIDENCE": 0.9984696507453918, "ENTITY_TYPE": "PERSON NAME"}, {"ENTITY_ID": "18ffa622-fdcb-4e99-b26b-9daf84161143_2", "PAGE": 5, "CONTENT": {"CONTENT": {"word_ids": ["word_522_472"], "coordinates": {"y0": 2251, "x0": 2045, "y1": 2293, "x1": 2196}, "raw_text_unformatted": "W\ufffdinberger", "value": "W\ufffdinberger"}}, "CONFIDENCE": 0.9984696507453918, "ENTITY_TYPE": "PERSON NAME"}, {"ENTITY_ID": "18ffa622-fdcb-4e99-b26b-9daf84161143", "PAGE": 5, "CONTENT": {"CONTENT": {"word_ids": ["word_522_471", "word_522_472"], "coordinates": {"y0": 2251, "x0": 1975, "y1": 2293, "x1": 2196}, "raw_text_unformatted": "JerryW\ufffdinberger", "value": "Jerry W\ufffdinberger"}}, "CONFIDENCE": 0.9984696507453918, "ENTITY_TYPE": "PERSON NAME"}, {"ENTITY_ID": "3b0d0029-806a-4c5d-b83d-3cd71ef49072", "PAGE": 5, "CONTENT": {"CONTENT": {"word_ids": ["word_522_423", "word_522_424"], "coordinates": {"y0": 2260, "x0": 592, "y1": 2290, "x1": 804}, "raw_text_unformatted": "BenjaminHirsch", "value": "Benjamin Hirsch"}}, "CONFIDENCE": 0.9937743544578552, "ENTITY_TYPE": "PERSON NAME"}, {"ENTITY_ID": "b2e45cc0-bf8b-4f1b-949d-eb20e12324df", "PAGE": 5, "CONTENT": {"CONTENT": {"word_ids": ["word_522_396", "word_522_397"], "coordinates": {"y0": 1771, "x0": 451, "y1": 1798, "x1": 569}, "raw_text_unformatted": "GT", "value": "G T"}}, "CONFIDENCE": 0.4802803695201874, "ENTITY_TYPE": "PERSON NAME"}, {"ENTITY_ID": "60ad27d9-307f-4f5a-8cde-baa9a14cfe99-PERSON_1", "PAGE": 3, "CONTENT": {"CONTENT": {"word_ids": ["word_320_485"], "coordinates": {"y0": 2983, "x0": 778, "y1": 3013, "x1": 868}, "raw_text_unformatted": "Closmg", "value": "Closmg"}}, "CONFIDENCE": 0.6482003927230835, "ENTITY_TYPE": "PERSON NAME"}, {"ENTITY_ID": "60ad27d9-307f-4f5a-8cde-baa9a14cfe99-PERSON_2", "PAGE": 3, "CONTENT": {"CONTENT": {"word_ids": ["word_320_486"], "coordinates": {"y0": 2984, "x0": 877, "y1": 3011, "x1": 906}, "raw_text_unformatted": "L", "value": "L"}}, "CONFIDENCE": 0.6482003927230835, "ENTITY_TYPE": "PERSON NAME"}, {"ENTITY_ID": "60ad27d9-307f-4f5a-8cde-baa9a14cfe99-PERSON", "PAGE": 3, "CONTENT": {"CONTENT": {"word_ids": ["word_320_485", "word_320_486"], "coordinates": {"y0": 2983, "x0": 778, "y1": 3013, "x1": 906}, "raw_text_unformatted": "ClosmgL", "value": "Closmg L"}}, "CONFIDENCE": 0.6482003927230835, "ENTITY_TYPE": "PERSON NAME"}, {"ENTITY_ID": "7ef3d9c5-37a8-4782-8701-03370f0efe64_1", "PAGE": 7, "CONTENT": {"CONTENT": {"word_ids": ["word_724_27"], "coordinates": {"y0": 490, "x0": 176, "y1": 529, "x1": 309}, "raw_text_unformatted": "Borrower", "value": "Borrower"}}, "CONFIDENCE": 0.9864034652709961, "ENTITY_TYPE": "PERSON NAME"}, {"ENTITY_ID": "e16b380c-0969-4a25-8734-d128e3b33e30_1", "PAGE": 7, "CONTENT": {"CONTENT": {"word_ids": ["word_724_28"], "coordinates": {"y0": 493, "x0": 511, "y1": 519, "x1": 657}, "raw_text_unformatted": "Yehoshua", "value": "Yehoshua"}}, "CONFIDENCE": 0.7501497268676758, "ENTITY_TYPE": "PERSON NAME"}, {"ENTITY_ID": "e16b380c-0969-4a25-8734-d128e3b33e30_2", "PAGE": 7, "CONTENT": {"CONTENT": {"word_ids": ["word_724_29"], "coordinates": {"y0": 491, "x0": 667, "y1": 517, "x1": 754}, "raw_text_unformatted": "Hecht", "value": "Hecht"}}, "CONFIDENCE": 0.7501497268676758, "ENTITY_TYPE": "PERSON NAME"}, {"ENTITY_ID": "e16b380c-0969-4a25-8734-d128e3b33e30", "PAGE": 7, "CONTENT": {"CONTENT": {"word_ids": ["word_724_28", "word_724_29"], "coordinates": {"y0": 491, "x0": 511, "y1": 519, "x1": 754}, "raw_text_unformatted": "YehoshuaHecht", "value": "Yehoshua Hecht"}}, "CONFIDENCE": 0.7501497268676758, "ENTITY_TYPE": "PERSON NAME"}, {"ENTITY_ID": "0878aadf-6fd4-4837-a4d0-4982586a27b9-STATE", "PAGE": 6, "CONTENT": {"CONTENT": {"word_ids": ["word_623_27"], "coordinates": {"y0": 579, "x0": 736, "y1": 604, "x1": 776}, "raw_text_unformatted": "NY", "value": "NY"}}, "CONFIDENCE": 0.9762228727340698, "ENTITY_TYPE": "STATE"}, {"ENTITY_ID": "ba6eee8e-3de6-406c-9cbe-d9b20241701e-STATE", "PAGE": 5, "CONTENT": {"CONTENT": {"word_ids": ["word_522_413"], "coordinates": {"y0": 2029, "x0": 778, "y1": 2051, "x1": 814}, "raw_text_unformatted": "NY", "value": "NY"}}, "CONFIDENCE": 0.8621417284011841, "ENTITY_TYPE": "STATE"}, {"ENTITY_ID": "31f98ce2-8bab-431f-820f-45d4db961104-STATE", "PAGE": 5, "CONTENT": {"CONTENT": {"word_ids": ["word_522_418"], "coordinates": {"y0": 2196, "x0": 191, "y1": 2221, "x1": 235}, "raw_text_unformatted": "NY", "value": "NY"}}, "CONFIDENCE": 0.55413818359375, "ENTITY_TYPE": "STATE"}, {"ENTITY_ID": "d9fa300f-d381-4914-9d83-15eccec084fd-STATE", "PAGE": 5, "CONTENT": {"CONTENT": {"word_ids": ["word_522_430"], "coordinates": {"y0": 2373, "x0": 318, "y1": 2410, "x1": 359}, "raw_text_unformatted": "NY", "value": "NY"}}, "CONFIDENCE": 0.9655585885047913, "ENTITY_TYPE": "STATE"}, {"ENTITY_ID": "e6307a10-aad8-45b4-a1f7-aca1954aafb3-STATE", "PAGE": 5, "CONTENT": {"CONTENT": {"word_ids": ["word_522_468"], "coordinates": {"y0": 2032, "x0": 2107, "y1": 2053, "x1": 2140}, "raw_text_unformatted": "NY", "value": "NY"}}, "CONFIDENCE": 0.9559615254402161, "ENTITY_TYPE": "STATE"}, {"ENTITY_ID": "455dcf3e-53ca-4ce6-a559-79d06e8c5de2-STATE", "PAGE": 1, "CONTENT": {"CONTENT": {"word_ids": ["word_118_56"], "coordinates": {"y0": 599, "x0": 1245, "y1": 624, "x1": 1285}, "raw_text_unformatted": "NY", "value": "NY"}}, "CONFIDENCE": 0.9444655776023865, "ENTITY_TYPE": "STATE"}, {"ENTITY_ID": "873c2f4d-4e99-4536-90dd-77579ca9f132-STATE", "PAGE": 1, "CONTENT": {"CONTENT": {"word_ids": ["word_118_89"], "coordinates": {"y0": 728, "x0": 1229, "y1": 754, "x1": 1270}, "raw_text_unformatted": "NY", "value": "NY"}}, "CONFIDENCE": 0.8319730162620544, "ENTITY_TYPE": "STATE"}, {"ENTITY_ID": "63594adb-0b44-4403-b8f5-cfe60940688c-STATE", "PAGE": 1, "CONTENT": {"CONTENT": {"word_ids": ["word_118_94"], "coordinates": {"y0": 769, "x0": 662, "y1": 793, "x1": 703}, "raw_text_unformatted": "NY", "value": "NY"}}, "CONFIDENCE": 0.7904177308082581, "ENTITY_TYPE": "STATE"}, {"ENTITY_ID": "5c4d65df-4e90-4dcd-8584-b3c80e60c624-STATE", "PAGE": 4, "CONTENT": {"CONTENT": {"word_ids": ["word_421_322"], "coordinates": {"y0": 2308, "x0": 682, "y1": 2332, "x1": 729}, "raw_text_unformatted": "NY", "value": "NY"}}, "CONFIDENCE": 0.9226349592208862, "ENTITY_TYPE": "STATE"}, {"ENTITY_ID": "ad7c613a-fda6-4d26-8422-af31bd2849c4-STATE", "PAGE": 7, "CONTENT": {"CONTENT": {"word_ids": ["word_724_35"], "coordinates": {"y0": 571, "x0": 740, "y1": 595, "x1": 781}, "raw_text_unformatted": "NY", "value": "NY"}}, "CONFIDENCE": 0.952567458152771, "ENTITY_TYPE": "STATE"}, {"ENTITY_ID": "b0b4cf8c-08e5-40ed-9938-dcf64ffc8549", "PAGE": 4, "CONTENT": {"CONTENT": {"word_ids": ["word_421_414"], "coordinates": {"y0": 879, "x0": 1312, "y1": 917, "x1": 1434}, "raw_text_unformatted": "Escrowed", "value": "Escrowed"}}, "CONFIDENCE": 0.48376914858818054, "ENTITY_TYPE": "COMMERCIAL_ITEM"}, {"ENTITY_ID": "aab2eb69-5f39-4139-9f82-252ac1a264cc", "PAGE": 6, "CONTENT": {"CONTENT": {"word_ids": ["word_623_19", "word_623_20"], "coordinates": {"y0": 497, "x0": 175, "y1": 538, "x1": 652}, "raw_text_unformatted": "Borrower Yehoshua", "value": "Borrower Yehoshua"}}, "CONFIDENCE": 0.6228030920028687, "ENTITY_TYPE": "COMPANY NAME"}, {"ENTITY_ID": "4f3702d7-fa7c-42bc-9a26-22dd106b2117", "PAGE": 6, "CONTENT": {"CONTENT": {"word_ids": ["word_623_118"], "coordinates": {"y0": 3119, "x0": 526, "y1": 3147, "x1": 727}, "raw_text_unformatted": "GTRIDCDWS_S", "value": "GTRIDCDWS_S"}}, "CONFIDENCE": 0.7474766373634338, "ENTITY_TYPE": "COMPANY NAME"}, {"ENTITY_ID": "16e42f8d-57f9-40b8-bcfa-6bc705014b93", "PAGE": 5, "CONTENT": {"CONTENT": {"word_ids": ["word_522_133", "word_522_134", "word_522_135", "word_522_136"], "coordinates": {"y0": 1448, "x0": 409, "y1": 1516, "x1": 1047}, "raw_text_unformatted": "Consumer Financial Protection Bureau", "value": "Consumer Financial Protection Bureau"}}, "CONFIDENCE": 0.9872362017631531, "ENTITY_TYPE": "COMPANY NAME"}, {"ENTITY_ID": "40e25b5c-c205-45c2-a572-b2b8ac2144e7", "PAGE": 5, "CONTENT": {"CONTENT": {"word_ids": ["word_522_394"], "coordinates": {"y0": 1768, "x0": 213, "y1": 1799, "x1": 295}, "raw_text_unformatted": "s", "value": "s"}}, "CONFIDENCE": 0.610028862953186, "ENTITY_TYPE": "COMPANY NAME"}, {"ENTITY_ID": "0ab363dc-5ece-4a33-88e6-6210dacd733b", "PAGE": 5, "CONTENT": {"CONTENT": {"word_ids": ["word_522_395"], "coordinates": {"y0": 1758, "x0": 291, "y1": 1803, "x1": 314}, "raw_text_unformatted": "R", "value": "R"}}, "CONFIDENCE": 0.32477694749832153, "ENTITY_TYPE": "COMPANY NAME"}, {"ENTITY_ID": "27c99459-dcfa-4247-835a-4b405ab614b0", "PAGE": 5, "CONTENT": {"CONTENT": {"word_ids": ["word_522_398"], "coordinates": {"y0": 1761, "x0": 586, "y1": 1793, "x1": 705}, "raw_text_unformatted": "ender", "value": "ender"}}, "CONFIDENCE": 0.3730323612689972, "ENTITY_TYPE": "COMPANY NAME"}, {"ENTITY_ID": "caff7658-5485-437b-bb5d-5f41ec3044a9", "PAGE": 5, "CONTENT": {"CONTENT": {"word_ids": ["word_522_402", "word_522_403", "word_522_404"], "coordinates": {"y0": 1844, "x0": 592, "y1": 1889, "x1": 833}, "raw_text_unformatted": "Ark Mortgage, Inc.", "value": "Ark Mortgage, Inc."}}, "CONFIDENCE": 0.9936752319335938, "ENTITY_TYPE": "COMPANY NAME"}, {"ENTITY_ID": "a7f0099c-6810-432c-a896-191bb5f5d050", "PAGE": 5, "CONTENT": {"CONTENT": {"word_ids": ["word_522_455", "word_522_456", "word_522_457"], "coordinates": {"y0": 1845, "x0": 1979, "y1": 1885, "x1": 2226}, "raw_text_unformatted": "Fink & Zelmanovitz", "value": "Fink & Zelmanovitz"}}, "CONFIDENCE": 0.838141143321991, "ENTITY_TYPE": "COMPANY NAME"}, {"ENTITY_ID": "96ed081b-d50a-4994-b70c-382d004870db", "PAGE": 1, "CONTENT": {"CONTENT": {"word_ids": ["word_118_63"], "coordinates": {"y0": 638, "x0": 532, "y1": 664, "x1": 592}, "raw_text_unformatted": "Fink", "value": "Fink"}}, "CONFIDENCE": 0.7589947581291199, "ENTITY_TYPE": "COMPANY NAME"}, {"ENTITY_ID": "c739641a-2de7-461d-965b-4aaf56895df4", "PAGE": 1, "CONTENT": {"CONTENT": {"word_ids": ["word_118_65"], "coordinates": {"y0": 638, "x0": 629, "y1": 665, "x1": 874}, "raw_text_unformatted": "ZelmanovitzP.C.", "value": "ZelmanovitzP.C."}}, "CONFIDENCE": 0.44004055857658386, "ENTITY_TYPE": "COMPANY NAME"}, {"ENTITY_ID": "71b5a94d-7189-4e9e-9d26-125f60cde704", "PAGE": 1, "CONTENT": {"CONTENT": {"word_ids": ["word_118_68", "word_118_69", "word_118_70"], "coordinates": {"y0": 642, "x0": 1096, "y1": 675, "x1": 1399}, "raw_text_unformatted": "Teverya Equities LLC", "value": "Teverya Equities LLC"}}, "CONFIDENCE": 0.9852740168571472, "ENTITY_TYPE": "COMPANY NAME"}, {"ENTITY_ID": "c7f6f008-8550-4836-a169-7f89c2aefd27", "PAGE": 1, "CONTENT": {"CONTENT": {"word_ids": ["word_118_96", "word_118_97", "word_118_98", "word_118_99"], "coordinates": {"y0": 766, "x0": 950, "y1": 805, "x1": 1365}, "raw_text_unformatted": "Lender Ark Mortgage, Inc.", "value": "Lender Ark Mortgage, Inc."}}, "CONFIDENCE": 0.9504830241203308, "ENTITY_TYPE": "COMPANY NAME"}, {"ENTITY_ID": "605857dd-ed85-4025-be2f-7710a294114f", "PAGE": 1, "CONTENT": {"CONTENT": {"word_ids": ["word_118_301"], "coordinates": {"y0": 3130, "x0": 518, "y1": 3157, "x1": 721}, "raw_text_unformatted": "GTRIDCDWS_S", "value": "GTRIDCDWS_S"}}, "CONFIDENCE": 0.5881713628768921, "ENTITY_TYPE": "COMPANY NAME"}, {"ENTITY_ID": "8bcff38a-cb3b-4f44-902e-b0b70423ee11", "PAGE": 4, "CONTENT": {"CONTENT": {"word_ids": ["word_421_54", "word_421_55"], "coordinates": {"y0": 782, "x0": 190, "y1": 856, "x1": 331}, "raw_text_unformatted": "foan J", "value": "foan J"}}, "CONFIDENCE": 0.6465355753898621, "ENTITY_TYPE": "COMPANY NAME"}, {"ENTITY_ID": "7900c5ec-e514-4fc1-9c0c-fcbe9206feff", "PAGE": 4, "CONTENT": {"CONTENT": {"word_ids": ["word_421_413"], "coordinates": {"y0": 829, "x0": 1312, "y1": 853, "x1": 1402}, "raw_text_unformatted": "Escrow", "value": "Escrow"}}, "CONFIDENCE": 0.6027410626411438, "ENTITY_TYPE": "COMPANY NAME"}, {"ENTITY_ID": "5c0c9273-f0f1-4189-85d2-e94c05968b24", "PAGE": 3, "CONTENT": {"CONTENT": {"word_ids": ["word_320_119", "word_320_120"], "coordinates": {"y0": 859, "x0": 1548, "y1": 883, "x1": 1675}, "raw_text_unformatted": "Sectvon K", "value": "Sectvon K"}}, "CONFIDENCE": 0.8978972434997559, "ENTITY_TYPE": "COMPANY NAME"}, {"ENTITY_ID": "d9a373c5-5f9c-4830-a4ae-6c326f825092", "PAGE": 3, "CONTENT": {"CONTENT": {"word_ids": ["word_320_235"], "coordinates": {"y0": 1561, "x0": 637, "y1": 1585, "x1": 732}, "raw_text_unformatted": "Se!!er", "value": "Se!!er"}}, "CONFIDENCE": 0.7300944328308105, "ENTITY_TYPE": "COMPANY NAME"}, {"ENTITY_ID": "61d92f3c-8cd2-4e60-9a2a-83c8517ea42e", "PAGE": 3, "CONTENT": {"CONTENT": {"word_ids": ["word_320_276"], "coordinates": {"y0": 1721, "x0": 265, "y1": 1768, "x1": 424}, "raw_text_unformatted": "Schooltax", "value": "Schooltax"}}, "CONFIDENCE": 0.3725542724132538, "ENTITY_TYPE": "COMPANY NAME"}, {"ENTITY_ID": "7107e903-025d-4bc3-8184-fa4f7485b0c4", "PAGE": 3, "CONTENT": {"CONTENT": {"word_ids": ["word_320_288"], "coordinates": {"y0": 1765, "x0": 273, "y1": 1804, "x1": 386}, "raw_text_unformatted": "Villagetax", "value": "Villagetax"}}, "CONFIDENCE": 0.39449259638786316, "ENTITY_TYPE": "COMPANY NAME"}, {"ENTITY_ID": "2e967b72-6ef2-4707-8676-31452262cdb1", "PAGE": 3, "CONTENT": {"CONTENT": {"word_ids": ["word_320_513"], "coordinates": {"y0": 3128, "x0": 517, "y1": 3157, "x1": 720}, "raw_text_unformatted": "GTRIDCDWS_S", "value": "GTRIDCDWS_S"}}, "CONFIDENCE": 0.48714324831962585, "ENTITY_TYPE": "COMPANY NAME"}, {"ENTITY_ID": "028ffc71-3903-42c7-a2a0-5afa40a24f88", "PAGE": 2, "CONTENT": {"CONTENT": {"word_ids": ["word_219_76", "word_219_77", "word_219_78"], "coordinates": {"y0": 775, "x0": 676, "y1": 816, "x1": 1015}, "raw_text_unformatted": "toNadlan Valuatron, Inc.", "value": "toNadlan Valuatron, Inc."}}, "CONFIDENCE": 0.901807963848114, "ENTITY_TYPE": "COMPANY NAME"}, {"ENTITY_ID": "8e7a9519-11ab-450c-9115-5deb229325d0", "PAGE": 2, "CONTENT": {"CONTENT": {"word_ids": ["word_219_91"], "coordinates": {"y0": 857, "x0": 732, "y1": 887, "x1": 864}, "raw_text_unformatted": "CoreLogrc", "value": "CoreLogrc"}}, "CONFIDENCE": 0.6217892169952393, "ENTITY_TYPE": "COMPANY NAME"}, {"ENTITY_ID": "b75df3b9-ee9f-4676-96b5-ae3068723182", "PAGE": 2, "CONTENT": {"CONTENT": {"word_ids": ["word_219_99", "word_219_100", "word_219_101", "word_219_102", "word_219_103", "word_219_104"], "coordinates": {"y0": 896, "x0": 733, "y1": 929, "x1": 1221}, "raw_text_unformatted": "First American Real Estate Tax Service", "value": "First American Real Estate Tax Service"}}, "CONFIDENCE": 0.9367718696594238, "ENTITY_TYPE": "COMPANY NAME"}, {"ENTITY_ID": "82a6071a-6780-49f1-8991-c99b0e8a7e71", "PAGE": 2, "CONTENT": {"CONTENT": {"word_ids": ["word_219_143", "word_219_144"], "coordinates": {"y0": 1256, "x0": 797, "y1": 1289, "x1": 961}, "raw_text_unformatted": "Abstract LLC", "value": "Abstract LLC"}}, "CONFIDENCE": 0.8489004373550415, "ENTITY_TYPE": "COMPANY NAME"}, {"ENTITY_ID": "5b05b0f3-8680-497a-895b-91c631577b1b", "PAGE": 2, "CONTENT": {"CONTENT": {"word_ids": ["word_219_150", "word_219_151", "word_219_152", "word_219_153"], "coordinates": {"y0": 1295, "x0": 729, "y1": 1327, "x1": 1059}, "raw_text_unformatted": "Kunstlmger Law Frrm LLC", "value": "Kunstlmger Law Frrm LLC"}}, "CONFIDENCE": 0.9439439177513123, "ENTITY_TYPE": "COMPANY NAME"}, {"ENTITY_ID": "83071f96-ab42-4bd6-aa2b-6e123cc7bf55", "PAGE": 2, "CONTENT": {"CONTENT": {"word_ids": ["word_219_156"], "coordinates": {"y0": 1331, "x0": 238, "y1": 1355, "x1": 312}, "raw_text_unformatted": "Trtle", "value": "Trtle"}}, "CONFIDENCE": 0.5305159091949463, "ENTITY_TYPE": "COMPANY NAME"}, {"ENTITY_ID": "64d64ba6-29d4-4595-864f-397d2b856891", "PAGE": 2, "CONTENT": {"CONTENT": {"word_ids": ["word_219_162", "word_219_163"], "coordinates": {"y0": 1334, "x0": 796, "y1": 1367, "x1": 960}, "raw_text_unformatted": "Abstract LLC", "value": "Abstract LLC"}}, "CONFIDENCE": 0.9816463589668274, "ENTITY_TYPE": "COMPANY NAME"}, {"ENTITY_ID": "c503fe1d-dc05-4915-8efd-61344d8b46fa", "PAGE": 2, "CONTENT": {"CONTENT": {"word_ids": ["word_219_166", "word_219_167"], "coordinates": {"y0": 1367, "x0": 238, "y1": 1409, "x1": 429}, "raw_text_unformatted": "Trtle Lender's", "value": "Trtle Lender's"}}, "CONFIDENCE": 0.8274675607681274, "ENTITY_TYPE": "COMPANY NAME"}, {"ENTITY_ID": "6e2acc34-675d-4ae4-9355-1df4d939f8e4", "PAGE": 2, "CONTENT": {"CONTENT": {"word_ids": ["word_219_171", "word_219_172", "word_219_173"], "coordinates": {"y0": 1373, "x0": 727, "y1": 1405, "x1": 960}, "raw_text_unformatted": "Joda Abstract LLC", "value": "Joda Abstract LLC"}}, "CONFIDENCE": 0.7428431510925293, "ENTITY_TYPE": "COMPANY NAME"}, {"ENTITY_ID": "065f3447-552b-4e8b-b6d2-a304579ebf57", "PAGE": 2, "CONTENT": {"CONTENT": {"word_ids": ["word_219_182"], "coordinates": {"y0": 1412, "x0": 728, "y1": 1436, "x1": 782}, "raw_text_unformatted": "Fink", "value": "Fink"}}, "CONFIDENCE": 0.7850790619850159, "ENTITY_TYPE": "COMPANY NAME"}, {"ENTITY_ID": "65e5a1fe-57a5-46ee-bf5d-d09785e98d2f", "PAGE": 2, "CONTENT": {"CONTENT": {"word_ids": ["word_219_184"], "coordinates": {"y0": 1413, "x0": 815, "y1": 1437, "x1": 978}, "raw_text_unformatted": "Zelmanovitz", "value": "Zelmanovitz"}}, "CONFIDENCE": 0.48230698704719543, "ENTITY_TYPE": "COMPANY NAME"}, {"ENTITY_ID": "1d2822db-93f4-4a5d-994a-87338544cb35", "PAGE": 2, "CONTENT": {"CONTENT": {"word_ids": ["word_219_249", "word_219_250"], "coordinates": {"y0": 1851, "x0": 724, "y1": 1881, "x1": 924}, "raw_text_unformatted": "Orange County", "value": "Orange County"}}, "CONFIDENCE": 0.8763887286186218, "ENTITY_TYPE": "COMPANY NAME"}, {"ENTITY_ID": "2a16622b-5463-4731-a11d-3c0c38ecffd6", "PAGE": 2, "CONTENT": {"CONTENT": {"word_ids": ["word_219_262", "word_219_263"], "coordinates": {"y0": 1935, "x0": 225, "y1": 1968, "x1": 577}, "raw_text_unformatted": "Homeowner's Insurance", "value": "Homeowner's Insurance"}}, "CONFIDENCE": 0.6873031854629517, "ENTITY_TYPE": "COMPANY NAME"}, {"ENTITY_ID": "5a73a658-863e-4bc7-82ec-904320fb5694", "PAGE": 2, "CONTENT": {"CONTENT": {"word_ids": ["word_219_268", "word_219_269", "word_219_270"], "coordinates": {"y0": 1931, "x0": 839, "y1": 1974, "x1": 1093}, "raw_text_unformatted": "P&G Brokerage, Inc.", "value": "P&G Brokerage, Inc."}}, "CONFIDENCE": 0.9928956627845764, "ENTITY_TYPE": "COMPANY NAME"}, {"ENTITY_ID": "dd157dc6-44e7-4a37-995e-34bcb49fbc64", "PAGE": 2, "CONTENT": {"CONTENT": {"word_ids": ["word_219_380", "word_219_381"], "coordinates": {"y0": 2543, "x0": 772, "y1": 2573, "x1": 906}, "raw_text_unformatted": "to Teverya", "value": "to Teverya"}}, "CONFIDENCE": 0.7567583322525024, "ENTITY_TYPE": "COMPANY NAME"}, {"ENTITY_ID": "18fbe7cd-45e0-41cb-a36c-6e7e1417cf54", "PAGE": 2, "CONTENT": {"CONTENT": {"word_ids": ["word_219_391", "word_219_392", "word_219_393", "word_219_394"], "coordinates": {"y0": 2581, "x0": 490, "y1": 2615, "x1": 865}, "raw_text_unformatted": "Insurance optional to Joda", "value": "Insurance optional to Joda"}}, "CONFIDENCE": 0.7201289534568787, "ENTITY_TYPE": "COMPANY NAME"}, {"ENTITY_ID": "eb2f5ab5-ffa8-4056-bf6f-af514b7ef290", "PAGE": 2, "CONTENT": {"CONTENT": {"word_ids": ["word_219_401", "word_219_402", "word_219_403"], "coordinates": {"y0": 2619, "x0": 347, "y1": 2654, "x1": 906}, "raw_text_unformatted": "Capital to Teverya", "value": "Capital to Teverya"}}, "CONFIDENCE": 0.8306255340576172, "ENTITY_TYPE": "COMPANY NAME"}, {"ENTITY_ID": "c08609fb-92d2-48bf-bf28-8b9c00f7894d", "PAGE": 2, "CONTENT": {"CONTENT": {"word_ids": ["word_219_460"], "coordinates": {"y0": 3130, "x0": 493, "y1": 3138, "x1": 499}, "raw_text_unformatted": "+", "value": "+"}}, "CONFIDENCE": 0.649516761302948, "ENTITY_TYPE": "COMPANY NAME"}, {"ENTITY_ID": "e86109eb-0fa5-46c0-a244-fe7c1da658fe", "PAGE": 2, "CONTENT": {"CONTENT": {"word_ids": ["word_219_478"], "coordinates": {"y0": 3164, "x0": 2018, "y1": 3189, "x1": 2191}, "raw_text_unformatted": "GTRIDCDWSS", "value": "GTRIDCDWSS"}}, "CONFIDENCE": 0.6960687041282654, "ENTITY_TYPE": "COMPANY NAME"}, {"ENTITY_ID": "99952edd-39f8-4585-af30-e4bb2f745057", "PAGE": 7, "CONTENT": {"CONTENT": {"word_ids": ["word_724_47"], "coordinates": {"y0": 3107, "x0": 545, "y1": 3136, "x1": 782}, "raw_text_unformatted": "GTRIDCDWSSC_S", "value": "GTRIDCDWSSC_S"}}, "CONFIDENCE": 0.5542671084403992, "ENTITY_TYPE": "COMPANY NAME"}, {"ENTITY_ID": "bf1c4fc9-55e9-4e04-b949-78e622380a78", "PAGE": 2, "CONTENT": {"CONTENT": {"word_ids": ["word_219_361", "word_219_362", "word_219_363", "word_219_364"], "coordinates": {"y0": 2405, "x0": 183, "y1": 2436, "x1": 529}, "raw_text_unformatted": "?\u0080\u0094?\u0080\u0094 - 07 B", "value": "?\u0080\u0094?\u0080\u0094 - 07 B"}}, "CONFIDENCE": 0.6528298854827881, "ENTITY_TYPE": "TITLE"}]