[{"ENTITY_ID": "f4870386-68ca-449c-8d89-3c0adeb4cdd5", "PAGE": 5, "CONTENT": {"CONTENT": {"word_ids": ["word_5_26"], "coordinates": {"y0": 400, "x0": 1039, "y1": 429, "x1": 1205}, "raw_text_unformatted": "$159,722.24", "value": "159722.24"}}, "CONFIDENCE": 0.999938428401947, "ENTITY_TYPE": "CURRENCY"}, {"ENTITY_ID": "3a5ce9e7-b60b-41f0-b00a-42067a83ed73", "PAGE": 5, "CONTENT": {"CONTENT": {"word_ids": ["word_5_38"], "coordinates": {"y0": 536, "x0": 1054, "y1": 566, "x1": 1204}, "raw_text_unformatted": "$54,977.24", "value": "54977.24"}}, "CONFIDENCE": 0.999825119972229, "ENTITY_TYPE": "CURRENCY"}, {"ENTITY_ID": "e42510ec-acaa-465a-b02b-c560ce920cff", "PAGE": 5, "CONTENT": {"CONTENT": {"word_ids": ["word_5_52"], "coordinates": {"y0": 665, "x0": 1036, "y1": 695, "x1": 1203}, "raw_text_unformatted": "$102,173.30", "value": "102173.30"}}, "CONFIDENCE": 0.9998117685317993, "ENTITY_TYPE": "CURRENCY"}, {"ENTITY_ID": "56708ad3-bc9e-4f4a-9a39-726d334443ef", "PAGE": 5, "CONTENT": {"CONTENT": {"word_ids": ["word_5_74"], "coordinates": {"y0": 822, "x0": 1092, "y1": 846, "x1": 1201}, "raw_text_unformatted": "4652%", "value": "4652"}}, "CONFIDENCE": 0.996023952960968, "ENTITY_TYPE": "CURRENCY"}, {"ENTITY_ID": "0741e1a8-cc10-4ef4-a8c7-b50c49b8044b", "PAGE": 5, "CONTENT": {"CONTENT": {"word_ids": ["word_5_100"], "coordinates": {"y0": 999, "x0": 1075, "y1": 1023, "x1": 1166}, "raw_text_unformatted": "52.086", "value": "52.086"}}, "CONFIDENCE": 0.998923659324646, "ENTITY_TYPE": "CURRENCY"}, {"ENTITY_ID": "ec8a536c-8b02-4a11-8450-be362abbebaa", "PAGE": 5, "CONTENT": {"CONTENT": {"word_ids": ["word_5_188"], "coordinates": {"y0": 440, "x0": 1874, "y1": 464, "x1": 1889}, "raw_text_unformatted": "3", "value": "3"}}, "CONFIDENCE": 0.9894710779190063, "ENTITY_TYPE": "CURRENCY"}, {"ENTITY_ID": "4f4e8e27-9a4e-454e-8dc4-b8c89cb94396", "PAGE": 5, "CONTENT": {"CONTENT": {"word_ids": ["word_5_284"], "coordinates": {"y0": 988, "x0": 1245, "y1": 1020, "x1": 1277}, "raw_text_unformatted": "3", "value": "3"}}, "CONFIDENCE": 0.9610909819602966, "ENTITY_TYPE": "CURRENCY"}, {"ENTITY_ID": "ab7e0d4c-e9d7-41e8-a446-0f20174af8a5", "PAGE": 5, "CONTENT": {"CONTENT": {"word_ids": ["word_5_422"], "coordinates": {"y0": 1961, "x0": 607, "y1": 1984, "x1": 698}, "raw_text_unformatted": "522998", "value": "522998"}}, "CONFIDENCE": 0.8815001249313354, "ENTITY_TYPE": "CURRENCY"}, {"ENTITY_ID": "2baa99c9-ab36-48ca-93b5-f11856ccf3aa", "PAGE": 5, "CONTENT": {"CONTENT": {"word_ids": ["word_5_427"], "coordinates": {"y0": 2139, "x0": 605, "y1": 2162, "x1": 696}, "raw_text_unformatted": "578436", "value": "578436"}}, "CONFIDENCE": 0.5890857577323914, "ENTITY_TYPE": "CURRENCY"}, {"ENTITY_ID": "65e369ab-c224-4657-b94f-a4ec68d1a16a", "PAGE": 5, "CONTENT": {"CONTENT": {"word_ids": ["word_5_448"], "coordinates": {"y0": 1838, "x0": 1258, "y1": 1860, "x1": 1313}, "raw_text_unformatted": "2741", "value": "2741"}}, "CONFIDENCE": 0.5756699442863464, "ENTITY_TYPE": "CURRENCY"}, {"ENTITY_ID": "32df7546-cf44-44e8-911c-cc863b4a9fdb", "PAGE": 5, "CONTENT": {"CONTENT": {"word_ids": ["word_5_454"], "coordinates": {"y0": 1873, "x0": 1400, "y1": 1895, "x1": 1475}, "raw_text_unformatted": "67212", "value": "67212"}}, "CONFIDENCE": 0.5741761326789856, "ENTITY_TYPE": "CURRENCY"}, {"ENTITY_ID": "1e862f29-2781-4dfc-a605-b8bcff24c244", "PAGE": 5, "CONTENT": {"CONTENT": {"word_ids": ["word_5_565"], "coordinates": {"y0": 2977, "x0": 1738, "y1": 2998, "x1": 1752}, "raw_text_unformatted": "5", "value": "5"}}, "CONFIDENCE": 0.9600873589515686, "ENTITY_TYPE": "CURRENCY"}, {"ENTITY_ID": "e05b4085-dc6f-4e19-b076-eae03b802880", "PAGE": 5, "CONTENT": {"CONTENT": {"word_ids": ["word_5_567"], "coordinates": {"y0": 2971, "x0": 1787, "y1": 3011, "x1": 1807}, "raw_text_unformatted": "5", "value": "5"}}, "CONFIDENCE": 0.4340277314186096, "ENTITY_TYPE": "CURRENCY"}, {"ENTITY_ID": "006ac879-fb3f-4804-8dba-c5ee8c6a77f7", "PAGE": 2, "CONTENT": {"CONTENT": {"word_ids": ["word_2_47"], "coordinates": {"y0": 385, "x0": 1411, "y1": 411, "x1": 1516}, "raw_text_unformatted": "$465.00", "value": "465.00"}}, "CONFIDENCE": 0.9997681379318237, "ENTITY_TYPE": "CURRENCY"}, {"ENTITY_ID": "72a5a391-b41a-4c51-a3a6-6b832f058aa2", "PAGE": 2, "CONTENT": {"CONTENT": {"word_ids": ["word_2_57"], "coordinates": {"y0": 462, "x0": 1359, "y1": 487, "x1": 1456}, "raw_text_unformatted": "$465.00", "value": "465.00"}}, "CONFIDENCE": 0.9997876286506653, "ENTITY_TYPE": "CURRENCY"}, {"ENTITY_ID": "a164b74b-41b7-4859-90a5-48bf61066f81", "PAGE": 2, "CONTENT": {"CONTENT": {"word_ids": ["word_2_59", "word_2_60", "word_2_61", "word_2_62"], "coordinates": {"y0": 530, "x0": 285, "y1": 662, "x1": 316}, "raw_text_unformatted": "04 05 06 07", "value": "04050607"}}, "CONFIDENCE": 0.7210033535957336, "ENTITY_TYPE": "CURRENCY"}, {"ENTITY_ID": "62050c3b-b462-4819-abb8-f3913193e14b", "PAGE": 2, "CONTENT": {"CONTENT": {"word_ids": ["word_2_71"], "coordinates": {"y0": 725, "x0": 1396, "y1": 752, "x1": 1526}, "raw_text_unformatted": "$1,847.95", "value": "1847.95"}}, "CONFIDENCE": 0.9998884201049805, "ENTITY_TYPE": "CURRENCY"}, {"ENTITY_ID": "040c3802-8a0a-4210-b91b-a75fdbf28936", "PAGE": 2, "CONTENT": {"CONTENT": {"word_ids": ["word_2_79"], "coordinates": {"y0": 767, "x0": 1559, "y1": 791, "x1": 1655}, "raw_text_unformatted": "$425.00", "value": "425.00"}}, "CONFIDENCE": 0.9997853636741638, "ENTITY_TYPE": "CURRENCY"}, {"ENTITY_ID": "0fd84ac1-9331-467c-961a-8465b1842626", "PAGE": 2, "CONTENT": {"CONTENT": {"word_ids": ["word_2_87"], "coordinates": {"y0": 801, "x0": 1357, "y1": 827, "x1": 1453}, "raw_text_unformatted": "$135.00", "value": "135.00"}}, "CONFIDENCE": 0.9997096657752991, "ENTITY_TYPE": "CURRENCY"}, {"ENTITY_ID": "a0af0bcb-8267-4820-9de0-b206459b5342", "PAGE": 2, "CONTENT": {"CONTENT": {"word_ids": ["word_2_95"], "coordinates": {"y0": 839, "x0": 1371, "y1": 863, "x1": 1452}, "raw_text_unformatted": "$11.00", "value": "11.00"}}, "CONFIDENCE": 0.9775528907775879, "ENTITY_TYPE": "CURRENCY"}, {"ENTITY_ID": "050428ae-dc1c-45d8-be4a-ddea50dc22ea", "PAGE": 2, "CONTENT": {"CONTENT": {"word_ids": ["word_2_101"], "coordinates": {"y0": 875, "x0": 1371, "y1": 900, "x1": 1451}, "raw_text_unformatted": "$11.95", "value": "11.95"}}, "CONFIDENCE": 0.999427855014801, "ENTITY_TYPE": "CURRENCY"}, {"ENTITY_ID": "27c2d46e-9f39-4aea-a527-77ac666b8f2b", "PAGE": 2, "CONTENT": {"CONTENT": {"word_ids": ["word_2_108"], "coordinates": {"y0": 913, "x0": 1371, "y1": 937, "x1": 1452}, "raw_text_unformatted": "$80.00", "value": "80.00"}}, "CONFIDENCE": 0.9997111558914185, "ENTITY_TYPE": "CURRENCY"}, {"ENTITY_ID": "8bcd6b12-edde-4c34-9470-c23fcf12b8f5", "PAGE": 2, "CONTENT": {"CONTENT": {"word_ids": ["word_2_119"], "coordinates": {"y0": 950, "x0": 1355, "y1": 975, "x1": 1452}, "raw_text_unformatted": "$695.00", "value": "695.00"}}, "CONFIDENCE": 0.9991357326507568, "ENTITY_TYPE": "CURRENCY"}, {"ENTITY_ID": "9d630ec0-20ef-4097-9a37-1e84040376fd", "PAGE": 2, "CONTENT": {"CONTENT": {"word_ids": ["word_2_129"], "coordinates": {"y0": 987, "x0": 1356, "y1": 1012, "x1": 1452}, "raw_text_unformatted": "$490.00", "value": "490.00"}}, "CONFIDENCE": 0.9992544651031494, "ENTITY_TYPE": "CURRENCY"}, {"ENTITY_ID": "e95dbdf9-ed32-4810-8a9f-7ee8ad60afb4", "PAGE": 2, "CONTENT": {"CONTENT": {"word_ids": ["word_2_152"], "coordinates": {"y0": 1478, "x0": 1391, "y1": 1505, "x1": 1520}, "raw_text_unformatted": "$2,312.95", "value": "2312.95"}}, "CONFIDENCE": 0.9998928904533386, "ENTITY_TYPE": "CURRENCY"}, {"ENTITY_ID": "4460644e-bd5d-48e8-8eaa-631bd18d95a5", "PAGE": 2, "CONTENT": {"CONTENT": {"word_ids": ["word_2_161"], "coordinates": {"y0": 1509, "x0": 1553, "y1": 1556, "x1": 1649}, "raw_text_unformatted": "$425.00", "value": "425.00"}}, "CONFIDENCE": 0.9911729097366333, "ENTITY_TYPE": "CURRENCY"}, {"ENTITY_ID": "0dfdbcf4-d5c3-4c19-85e7-51af5caeb73b", "PAGE": 2, "CONTENT": {"CONTENT": {"word_ids": ["word_2_172"], "coordinates": {"y0": 1663, "x0": 1401, "y1": 1688, "x1": 1505}, "raw_text_unformatted": "$324.75", "value": "324.75"}}, "CONFIDENCE": 0.9998332858085632, "ENTITY_TYPE": "CURRENCY"}, {"ENTITY_ID": "1dcdd040-a3b4-4ea7-b5f9-088ef87566be", "PAGE": 2, "CONTENT": {"CONTENT": {"word_ids": ["word_2_178"], "coordinates": {"y0": 1702, "x0": 1087, "y1": 1726, "x1": 1182}, "raw_text_unformatted": "$242.00", "value": "242.00"}}, "CONFIDENCE": 0.9998194575309753, "ENTITY_TYPE": "CURRENCY"}, {"ENTITY_ID": "523e74d1-f0c3-4073-9c87-652018b16689", "PAGE": 2, "CONTENT": {"CONTENT": {"word_ids": ["word_2_179"], "coordinates": {"y0": 1703, "x0": 1350, "y1": 1729, "x1": 1445}, "raw_text_unformatted": "$273.00", "value": "273.00"}}, "CONFIDENCE": 0.998476505279541, "ENTITY_TYPE": "CURRENCY"}, {"ENTITY_ID": "1e700fea-9099-4022-81cc-7686add3d8e0", "PAGE": 2, "CONTENT": {"CONTENT": {"word_ids": ["word_2_189"], "coordinates": {"y0": 1741, "x0": 1364, "y1": 1766, "x1": 1444}, "raw_text_unformatted": "$51.75", "value": "51.75"}}, "CONFIDENCE": 0.999790370464325, "ENTITY_TYPE": "CURRENCY"}, {"ENTITY_ID": "0d1d3d0b-03a3-4b11-b2c2-a0a482a025a8", "PAGE": 2, "CONTENT": {"CONTENT": {"word_ids": ["word_2_192"], "coordinates": {"y0": 1781, "x0": 1388, "y1": 1809, "x1": 1518}, "raw_text_unformatted": "$2,391.04", "value": "2391.04"}}, "CONFIDENCE": 0.9997594952583313, "ENTITY_TYPE": "CURRENCY"}, {"ENTITY_ID": "8f1294fc-2412-466c-9e86-0b3a30d3d267", "PAGE": 2, "CONTENT": {"CONTENT": {"word_ids": ["word_2_197"], "coordinates": {"y0": 1818, "x0": 741, "y1": 1844, "x1": 778}, "raw_text_unformatted": "12", "value": "12"}}, "CONFIDENCE": 0.9753209948539734, "ENTITY_TYPE": "CURRENCY"}, {"ENTITY_ID": "78f99a6c-5780-4756-94a9-2a0c7f1e51dc", "PAGE": 2, "CONTENT": {"CONTENT": {"word_ids": ["word_2_202"], "coordinates": {"y0": 1822, "x0": 1327, "y1": 1848, "x1": 1444}, "raw_text_unformatted": "$2,132.29", "value": "2132.29"}}, "CONFIDENCE": 0.9997434616088867, "ENTITY_TYPE": "CURRENCY"}, {"ENTITY_ID": "397a8824-0fb9-43fb-ab2d-22143691f192", "PAGE": 2, "CONTENT": {"CONTENT": {"word_ids": ["word_2_213"], "coordinates": {"y0": 1889, "x0": 536, "y1": 1913, "x1": 645}, "raw_text_unformatted": "$12.9375", "value": "12.9375"}}, "CONFIDENCE": 0.835759162902832, "ENTITY_TYPE": "CURRENCY"}, {"ENTITY_ID": "215077c3-fa23-47e1-affa-78e44ae8e400", "PAGE": 2, "CONTENT": {"CONTENT": {"word_ids": ["word_2_220"], "coordinates": {"y0": 1894, "x0": 1348, "y1": 1920, "x1": 1443}, "raw_text_unformatted": "$258.75", "value": "258.75"}}, "CONFIDENCE": 0.9984430074691772, "ENTITY_TYPE": "CURRENCY"}, {"ENTITY_ID": "2d5441d8-8e36-43c8-80e2-0d212f7b456a", "PAGE": 2, "CONTENT": {"CONTENT": {"word_ids": ["word_2_232"], "coordinates": {"y0": 2010, "x0": 1386, "y1": 2038, "x1": 1516}, "raw_text_unformatted": "$1,310.78", "value": "1310.78"}}, "CONFIDENCE": 0.9989377856254578, "ENTITY_TYPE": "CURRENCY"}, {"ENTITY_ID": "c6153bad-f047-497f-9ced-3563114262a9", "PAGE": 2, "CONTENT": {"CONTENT": {"word_ids": ["word_2_236"], "coordinates": {"y0": 2046, "x0": 652, "y1": 2070, "x1": 747}, "raw_text_unformatted": "$177.69", "value": "177.69"}}, "CONFIDENCE": 0.9705630540847778, "ENTITY_TYPE": "CURRENCY"}, {"ENTITY_ID": "7054d9fc-d34a-478b-b68f-9e5be2423dde", "PAGE": 2, "CONTENT": {"CONTENT": {"word_ids": ["word_2_240"], "coordinates": {"y0": 2049, "x0": 933, "y1": 2071, "x1": 947}, "raw_text_unformatted": "3", "value": "3"}}, "CONFIDENCE": 0.9770307540893555, "ENTITY_TYPE": "CURRENCY"}, {"ENTITY_ID": "deb88d2d-6efd-4ebd-9eec-b16225c8971d", "PAGE": 2, "CONTENT": {"CONTENT": {"word_ids": ["word_2_242", "word_2_243"], "coordinates": {"y0": 2051, "x0": 272, "y1": 2103, "x1": 1441}, "raw_text_unformatted": "$533.07 02", "value": "533.0702"}}, "CONFIDENCE": 0.7946758270263672, "ENTITY_TYPE": "CURRENCY"}, {"ENTITY_ID": "e19200c6-c520-4dd6-a0d4-a2235a6f8921", "PAGE": 2, "CONTENT": {"CONTENT": {"word_ids": ["word_2_253"], "coordinates": {"y0": 2120, "x0": 651, "y1": 2144, "x1": 747}, "raw_text_unformatted": "$161.87", "value": "161.87"}}, "CONFIDENCE": 0.9039822816848755, "ENTITY_TYPE": "CURRENCY"}, {"ENTITY_ID": "798d8794-8275-4873-935a-d9b210f207ac", "PAGE": 2, "CONTENT": {"CONTENT": {"word_ids": ["word_2_257"], "coordinates": {"y0": 2124, "x0": 933, "y1": 2145, "x1": 947}, "raw_text_unformatted": "8", "value": "8"}}, "CONFIDENCE": 0.9855741262435913, "ENTITY_TYPE": "CURRENCY"}, {"ENTITY_ID": "1bbff43e-6705-42fe-a7f0-0949f0b23822", "PAGE": 2, "CONTENT": {"CONTENT": {"word_ids": ["word_2_259"], "coordinates": {"y0": 2125, "x0": 1324, "y1": 2151, "x1": 1442}, "raw_text_unformatted": "$1,294.96", "value": "1294.96"}}, "CONFIDENCE": 0.9876430034637451, "ENTITY_TYPE": "CURRENCY"}, {"ENTITY_ID": "7a6f6d5a-b34a-4232-893b-e2a9409d8574", "PAGE": 2, "CONTENT": {"CONTENT": {"word_ids": ["word_2_261", "word_2_262", "word_2_263"], "coordinates": {"y0": 2192, "x0": 270, "y1": 2286, "x1": 300}, "raw_text_unformatted": "05 06 07", "value": "050607"}}, "CONFIDENCE": 0.7061132788658142, "ENTITY_TYPE": "CURRENCY"}, {"ENTITY_ID": "15c625c1-307e-4d78-a892-455a72d69e83", "PAGE": 2, "CONTENT": {"CONTENT": {"word_ids": ["word_2_270"], "coordinates": {"y0": 2349, "x0": 1395, "y1": 2376, "x1": 1500}, "raw_text_unformatted": "$460.00", "value": "460.00"}}, "CONFIDENCE": 0.9995903968811035, "ENTITY_TYPE": "CURRENCY"}, {"ENTITY_ID": "5b55649a-6b90-45ea-bc50-6819e8a60911", "PAGE": 2, "CONTENT": {"CONTENT": {"word_ids": ["word_2_280"], "coordinates": {"y0": 2390, "x0": 1344, "y1": 2416, "x1": 1439}, "raw_text_unformatted": "$150.00", "value": "150.00"}}, "CONFIDENCE": 0.9994687438011169, "ENTITY_TYPE": "CURRENCY"}, {"ENTITY_ID": "120fa73f-ef39-4b31-9a51-27afe75f8203", "PAGE": 2, "CONTENT": {"CONTENT": {"word_ids": ["word_2_288"], "coordinates": {"y0": 2432, "x0": 1725, "y1": 2458, "x1": 1843}, "raw_text_unformatted": "$4,905.00", "value": "4905.00"}}, "CONFIDENCE": 0.9997640252113342, "ENTITY_TYPE": "CURRENCY"}, {"ENTITY_ID": "91ca3d48-d1ac-43a2-bcd8-16e274783163", "PAGE": 2, "CONTENT": {"CONTENT": {"word_ids": ["word_2_296"], "coordinates": {"y0": 2468, "x0": 1724, "y1": 2495, "x1": 1843}, "raw_text_unformatted": "$4,905.00", "value": "4905.00"}}, "CONFIDENCE": 0.9996474981307983, "ENTITY_TYPE": "CURRENCY"}, {"ENTITY_ID": "2aa4f704-f630-480a-b960-5d1c5a6b0458", "PAGE": 2, "CONTENT": {"CONTENT": {"word_ids": ["word_2_308", "word_2_309", "word_2_310", "word_2_311"], "coordinates": {"y0": 2503, "x0": 268, "y1": 2627, "x1": 1438}, "raw_text_unformatted": "$310.00 05 06 07", "value": "310.00050607"}}, "CONFIDENCE": 0.8409316539764404, "ENTITY_TYPE": "CURRENCY"}, {"ENTITY_ID": "2b7e1a04-c42f-4370-8234-c2a53249995c", "PAGE": 2, "CONTENT": {"CONTENT": {"word_ids": ["word_2_318"], "coordinates": {"y0": 2690, "x0": 1379, "y1": 2717, "x1": 1510}, "raw_text_unformatted": "$4,486.57", "value": "4486.57"}}, "CONFIDENCE": 0.9998412132263184, "ENTITY_TYPE": "CURRENCY"}, {"ENTITY_ID": "78068706-82a5-406b-8ef6-441f15c69bdf", "PAGE": 2, "CONTENT": {"CONTENT": {"word_ids": ["word_2_334"], "coordinates": {"y0": 2815, "x0": 1378, "y1": 2844, "x1": 1509}, "raw_text_unformatted": "$6,549.52", "value": "6549.52"}}, "CONFIDENCE": 0.9976118803024292, "ENTITY_TYPE": "CURRENCY"}, {"ENTITY_ID": "83f51e0b-c0af-4782-8ce9-77f4890f783e", "PAGE": 2, "CONTENT": {"CONTENT": {"word_ids": ["word_2_340"], "coordinates": {"y0": 2853, "x0": 611, "y1": 2879, "x1": 625}, "raw_text_unformatted": "1", "value": "1"}}, "CONFIDENCE": 0.49610230326652527, "ENTITY_TYPE": "CURRENCY"}, {"ENTITY_ID": "d606f735-7e2b-4732-8334-ecbe35344182", "PAGE": 2, "CONTENT": {"CONTENT": {"word_ids": ["word_2_341"], "coordinates": {"y0": 2846, "x0": 1319, "y1": 2894, "x1": 1435}, "raw_text_unformatted": "$6,374.52", "value": "6374.52"}}, "CONFIDENCE": 0.9779394865036011, "ENTITY_TYPE": "CURRENCY"}, {"ENTITY_ID": "de9c7a7a-181d-4021-b6d3-ad48258aa4ee", "PAGE": 2, "CONTENT": {"CONTENT": {"word_ids": ["word_2_342"], "coordinates": {"y0": 2848, "x0": 1541, "y1": 2896, "x1": 1637}, "raw_text_unformatted": "$425.00", "value": "425.00"}}, "CONFIDENCE": 0.9899044036865234, "ENTITY_TYPE": "CURRENCY"}, {"ENTITY_ID": "89513ea0-7b76-4b1e-8556-614f5c9b39c2", "PAGE": 2, "CONTENT": {"CONTENT": {"word_ids": ["word_2_343"], "coordinates": {"y0": 2860, "x0": 1721, "y1": 2887, "x1": 1839}, "raw_text_unformatted": "$9,810.00", "value": "9810.00"}}, "CONFIDENCE": 0.9916620850563049, "ENTITY_TYPE": "CURRENCY"}, {"ENTITY_ID": "b78b25b0-185a-4f15-9c21-c30c961a694d", "PAGE": 2, "CONTENT": {"CONTENT": {"word_ids": ["word_2_351"], "coordinates": {"y0": 2971, "x0": 784, "y1": 2992, "x1": 842}, "raw_text_unformatted": "0617", "value": "0617"}}, "CONFIDENCE": 0.42252030968666077, "ENTITY_TYPE": "CURRENCY"}, {"ENTITY_ID": "e4861f0c-22b0-4fa5-ba3b-1781b893ea0c", "PAGE": 2, "CONTENT": {"CONTENT": {"word_ids": ["word_2_353"], "coordinates": {"y0": 2979, "x0": 1783, "y1": 3001, "x1": 1797}, "raw_text_unformatted": "2", "value": "2"}}, "CONFIDENCE": 0.745302677154541, "ENTITY_TYPE": "CURRENCY"}, {"ENTITY_ID": "c5996d9f-5fd8-4338-80e5-6390f8f69217", "PAGE": 2, "CONTENT": {"CONTENT": {"word_ids": ["word_2_355"], "coordinates": {"y0": 2973, "x0": 1832, "y1": 3012, "x1": 1852}, "raw_text_unformatted": "5", "value": "5"}}, "CONFIDENCE": 0.3173938989639282, "ENTITY_TYPE": "CURRENCY"}, {"ENTITY_ID": "017b9f10-85cd-479f-b82e-4d267ee48e0c", "PAGE": 3, "CONTENT": {"CONTENT": {"word_ids": ["word_3_35"], "coordinates": {"y0": 355, "x0": 851, "y1": 403, "x1": 969}, "raw_text_unformatted": "$5,808.00", "value": "5808.00"}}, "CONFIDENCE": 0.8888469934463501, "ENTITY_TYPE": "CURRENCY"}, {"ENTITY_ID": "c620a433-28ab-4d2d-b325-c66b19d93c46", "PAGE": 3, "CONTENT": {"CONTENT": {"word_ids": ["word_3_36"], "coordinates": {"y0": 367, "x0": 1073, "y1": 394, "x1": 1188}, "raw_text_unformatted": "$6,549.52", "value": "6549.52"}}, "CONFIDENCE": 0.9869562983512878, "ENTITY_TYPE": "CURRENCY"}, {"ENTITY_ID": "b9370e3c-eb2d-47e0-8930-9e4e6dcdd4d5", "PAGE": 3, "CONTENT": {"CONTENT": {"word_ids": ["word_3_54"], "coordinates": {"y0": 485, "x0": 1084, "y1": 511, "x1": 1189}, "raw_text_unformatted": "-5425.00", "value": "-5425.00"}}, "CONFIDENCE": 0.9705025553703308, "ENTITY_TYPE": "CURRENCY"}, {"ENTITY_ID": "670cc4c4-a6f7-4495-a111-5d59b7b8be30", "PAGE": 3, "CONTENT": {"CONTENT": {"word_ids": ["word_3_80"], "coordinates": {"y0": 615, "x0": 836, "y1": 653, "x1": 969}, "raw_text_unformatted": "$60,000.00", "value": "60000.00"}}, "CONFIDENCE": 0.9997090697288513, "ENTITY_TYPE": "CURRENCY"}, {"ENTITY_ID": "da201c58-90c7-4367-90e2-647eb7bec242", "PAGE": 3, "CONTENT": {"CONTENT": {"word_ids": ["word_3_81"], "coordinates": {"y0": 619, "x0": 1058, "y1": 645, "x1": 1188}, "raw_text_unformatted": "$60,000.00", "value": "60000.00"}}, "CONFIDENCE": 0.9808502793312073, "ENTITY_TYPE": "CURRENCY"}, {"ENTITY_ID": "cdc12bd6-bfd6-4f56-b539-4f519464af7f", "PAGE": 3, "CONTENT": {"CONTENT": {"word_ids": ["word_3_97"], "coordinates": {"y0": 774, "x0": 939, "y1": 800, "x1": 968}, "raw_text_unformatted": "$0", "value": "0"}}, "CONFIDENCE": 0.9982151985168457, "ENTITY_TYPE": "CURRENCY"}, {"ENTITY_ID": "fa19508d-e5b8-4aff-bb37-9cb3aa5fbce9", "PAGE": 3, "CONTENT": {"CONTENT": {"word_ids": ["word_3_119"], "coordinates": {"y0": 880, "x0": 822, "y1": 906, "x1": 968}, "raw_text_unformatted": "$64,148.00", "value": "64148.00"}}, "CONFIDENCE": 0.9974178671836853, "ENTITY_TYPE": "CURRENCY"}, {"ENTITY_ID": "adb43378-7ec8-4510-ba6b-d5a9af287b9d", "PAGE": 3, "CONTENT": {"CONTENT": {"word_ids": ["word_3_120"], "coordinates": {"y0": 880, "x0": 1044, "y1": 906, "x1": 1188}, "raw_text_unformatted": "$63,290.24", "value": "63290.24"}}, "CONFIDENCE": 0.9798776507377625, "ENTITY_TYPE": "CURRENCY"}, {"ENTITY_ID": "7647db18-c328-4f0b-8ef0-6e89e8a9351d", "PAGE": 3, "CONTENT": {"CONTENT": {"word_ids": ["word_3_144"], "coordinates": {"y0": 1116, "x0": 1002, "y1": 1157, "x1": 1160}, "raw_text_unformatted": "$169,966.91", "value": "169966.91"}}, "CONFIDENCE": 0.9998751282691956, "ENTITY_TYPE": "CURRENCY"}, {"ENTITY_ID": "1ac21916-073f-40c1-96f5-573987a923bf", "PAGE": 3, "CONTENT": {"CONTENT": {"word_ids": ["word_3_151"], "coordinates": {"y0": 1124, "x0": 2042, "y1": 1150, "x1": 2203}, "raw_text_unformatted": "$163,842.39", "value": "163842.39"}}, "CONFIDENCE": 0.9997544884681702, "ENTITY_TYPE": "CURRENCY"}, {"ENTITY_ID": "c5a122fb-845c-4526-9f42-be9e7940600b", "PAGE": 3, "CONTENT": {"CONTENT": {"word_ids": ["word_3_163"], "coordinates": {"y0": 1169, "x0": 2057, "y1": 1197, "x1": 2203}, "raw_text_unformatted": "$163,500.00", "value": "163500.00"}}, "CONFIDENCE": 0.9994787573814392, "ENTITY_TYPE": "CURRENCY"}, {"ENTITY_ID": "768347cc-0455-4c90-8636-b97999fd313c", "PAGE": 3, "CONTENT": {"CONTENT": {"word_ids": ["word_3_190"], "coordinates": {"y0": 1253, "x0": 657, "y1": 1275, "x1": 684}, "raw_text_unformatted": "1", "value": "1"}}, "CONFIDENCE": 0.9304028749465942, "ENTITY_TYPE": "CURRENCY"}, {"ENTITY_ID": "9ec5e24a-6c21-428d-b933-d9b092335587", "PAGE": 3, "CONTENT": {"CONTENT": {"word_ids": ["word_3_191"], "coordinates": {"y0": 1251, "x0": 1047, "y1": 1279, "x1": 1162}, "raw_text_unformatted": "$6,124.52", "value": "6124.52"}}, "CONFIDENCE": 0.9416608810424805, "ENTITY_TYPE": "CURRENCY"}, {"ENTITY_ID": "08a66dc8-0e83-414a-914d-9d745c32d427", "PAGE": 3, "CONTENT": {"CONTENT": {"word_ids": ["word_3_203"], "coordinates": {"y0": 1369, "x0": 1068, "y1": 1407, "x1": 1162}, "raw_text_unformatted": "$342.39", "value": "342.39"}}, "CONFIDENCE": 0.993220329284668, "ENTITY_TYPE": "CURRENCY"}, {"ENTITY_ID": "4a8f6797-2aef-451c-9e0d-cdf874b51953", "PAGE": 3, "CONTENT": {"CONTENT": {"word_ids": ["word_3_233"], "coordinates": {"y0": 1577, "x0": 240, "y1": 1598, "x1": 270}, "raw_text_unformatted": "09", "value": "09"}}, "CONFIDENCE": 0.463931143283844, "ENTITY_TYPE": "CURRENCY"}, {"ENTITY_ID": "3fec0cbb-db38-4560-bc65-4dee4136baa7", "PAGE": 3, "CONTENT": {"CONTENT": {"word_ids": ["word_3_237"], "coordinates": {"y0": 1579, "x0": 1283, "y1": 1601, "x1": 1310}, "raw_text_unformatted": "10", "value": "10"}}, "CONFIDENCE": 0.6212356090545654, "ENTITY_TYPE": "CURRENCY"}, {"ENTITY_ID": "14703cb0-449c-4ba5-b76f-9d0d1e82aff5", "PAGE": 3, "CONTENT": {"CONTENT": {"word_ids": ["word_3_248"], "coordinates": {"y0": 1661, "x0": 1283, "y1": 1681, "x1": 1309}, "raw_text_unformatted": "12", "value": "12"}}, "CONFIDENCE": 0.6809401512145996, "ENTITY_TYPE": "CURRENCY"}, {"ENTITY_ID": "e989a3ce-753e-4403-8756-5906c2fd9079", "PAGE": 3, "CONTENT": {"CONTENT": {"word_ids": ["word_3_254"], "coordinates": {"y0": 1663, "x0": 2107, "y1": 1688, "x1": 2203}, "raw_text_unformatted": "$342.39", "value": "342.39"}}, "CONFIDENCE": 0.9993798732757568, "ENTITY_TYPE": "CURRENCY"}, {"ENTITY_ID": "3d566cca-3a08-4393-ad75-a7d0e628d662", "PAGE": 3, "CONTENT": {"CONTENT": {"word_ids": ["word_3_258", "word_3_259", "word_3_260"], "coordinates": {"y0": 1742, "x0": 242, "y1": 1803, "x1": 1309}, "raw_text_unformatted": "14 4 15", "value": "14415"}}, "CONFIDENCE": 0.567375123500824, "ENTITY_TYPE": "CURRENCY"}, {"ENTITY_ID": "b26f7212-325f-4506-b244-43d8db3d0a01", "PAGE": 3, "CONTENT": {"CONTENT": {"word_ids": ["word_3_274"], "coordinates": {"y0": 1878, "x0": 1000, "y1": 1904, "x1": 1161}, "raw_text_unformatted": "$106,676.67", "value": "106676.67"}}, "CONFIDENCE": 0.9998493194580078, "ENTITY_TYPE": "CURRENCY"}, {"ENTITY_ID": "4b5a71f5-a329-45bb-8aff-9b9c88b435b8", "PAGE": 3, "CONTENT": {"CONTENT": {"word_ids": ["word_3_281"], "coordinates": {"y0": 1877, "x0": 2056, "y1": 1903, "x1": 2201}, "raw_text_unformatted": "$11,986.67", "value": "11986.67"}}, "CONFIDENCE": 0.99982750415802, "ENTITY_TYPE": "CURRENCY"}, {"ENTITY_ID": "403df0df-5214-46d8-8925-efccdc09425d", "PAGE": 3, "CONTENT": {"CONTENT": {"word_ids": ["word_3_284"], "coordinates": {"y0": 1915, "x0": 1045, "y1": 1951, "x1": 1161}, "raw_text_unformatted": "$1,000.00", "value": "1000.00"}}, "CONFIDENCE": 0.9993988275527954, "ENTITY_TYPE": "CURRENCY"}, {"ENTITY_ID": "154f865f-1796-4788-9455-3faf724fae85", "PAGE": 3, "CONTENT": {"CONTENT": {"word_ids": ["word_3_291"], "coordinates": {"y0": 1957, "x0": 1015, "y1": 1994, "x1": 1161}, "raw_text_unformatted": "$103,500.00", "value": "103500.00"}}, "CONFIDENCE": 0.9993649125099182, "ENTITY_TYPE": "CURRENCY"}, {"ENTITY_ID": "a37ca09a-e088-4651-9680-65d67f21f5d4", "PAGE": 3, "CONTENT": {"CONTENT": {"word_ids": ["word_3_299"], "coordinates": {"y0": 1964, "x0": 2086, "y1": 1992, "x1": 2202}, "raw_text_unformatted": "$9,810.00", "value": "9810.00"}}, "CONFIDENCE": 0.9976967573165894, "ENTITY_TYPE": "CURRENCY"}, {"ENTITY_ID": "67b82bab-4e2d-48bc-af7a-28ec5f963a58", "PAGE": 3, "CONTENT": {"CONTENT": {"word_ids": ["word_3_348"], "coordinates": {"y0": 2250, "x0": 2105, "y1": 2276, "x1": 2200}, "raw_text_unformatted": "$415,00", "value": "41500"}}, "CONFIDENCE": 0.9998092651367188, "ENTITY_TYPE": "CURRENCY"}, {"ENTITY_ID": "28bb9083-ad57-4211-86ce-d25b097ec6b3", "PAGE": 3, "CONTENT": {"CONTENT": {"word_ids": ["word_3_355"], "coordinates": {"y0": 2284, "x0": 1065, "y1": 2310, "x1": 1160}, "raw_text_unformatted": "$415.00", "value": "415.00"}}, "CONFIDENCE": 0.9997742176055908, "ENTITY_TYPE": "CURRENCY"}, {"ENTITY_ID": "77b87015-82d8-4e0a-8426-11189c85782b", "PAGE": 3, "CONTENT": {"CONTENT": {"word_ids": ["word_3_362", "word_3_363"], "coordinates": {"y0": 2290, "x0": 236, "y1": 2344, "x1": 2200}, "raw_text_unformatted": "$245.00 09", "value": "245.0009"}}, "CONFIDENCE": 0.935093879699707, "ENTITY_TYPE": "CURRENCY"}, {"ENTITY_ID": "4f46e3f4-8cf1-468c-9fad-9d5eaf72dfa9", "PAGE": 3, "CONTENT": {"CONTENT": {"word_ids": ["word_3_369"], "coordinates": {"y0": 2320, "x0": 1065, "y1": 2359, "x1": 1160}, "raw_text_unformatted": "$245,00", "value": "24500"}}, "CONFIDENCE": 0.9997888803482056, "ENTITY_TYPE": "CURRENCY"}, {"ENTITY_ID": "49279eda-fd46-485e-b1bb-ad89da30c109", "PAGE": 3, "CONTENT": {"CONTENT": {"word_ids": ["word_3_371"], "coordinates": {"y0": 2363, "x0": 239, "y1": 2384, "x1": 266}, "raw_text_unformatted": "10", "value": "10"}}, "CONFIDENCE": 0.8338283896446228, "ENTITY_TYPE": "CURRENCY"}, {"ENTITY_ID": "22b262a6-edab-4af4-b53b-879182d68df2", "PAGE": 3, "CONTENT": {"CONTENT": {"word_ids": ["word_3_374"], "coordinates": {"y0": 2406, "x0": 1280, "y1": 2428, "x1": 1307}, "raw_text_unformatted": "13", "value": "13"}}, "CONFIDENCE": 0.512726366519928, "ENTITY_TYPE": "CURRENCY"}, {"ENTITY_ID": "abf9ebc5-1f93-4553-a28b-6f9fa56bb9c9", "PAGE": 3, "CONTENT": {"CONTENT": {"word_ids": ["word_3_387"], "coordinates": {"y0": 2485, "x0": 238, "y1": 2506, "x1": 266}, "raw_text_unformatted": "12", "value": "12"}}, "CONFIDENCE": 0.9473857283592224, "ENTITY_TYPE": "CURRENCY"}, {"ENTITY_ID": "3650ffb3-42cc-4e0c-86a0-799117931ffd", "PAGE": 3, "CONTENT": {"CONTENT": {"word_ids": ["word_3_391"], "coordinates": {"y0": 2487, "x0": 1280, "y1": 2508, "x1": 1307}, "raw_text_unformatted": "14", "value": "14"}}, "CONFIDENCE": 0.8826152086257935, "ENTITY_TYPE": "CURRENCY"}, {"ENTITY_ID": "a73e7e54-a619-4a90-a07c-5274aab54e35", "PAGE": 3, "CONTENT": {"CONTENT": {"word_ids": ["word_3_401"], "coordinates": {"y0": 2524, "x0": 1044, "y1": 2550, "x1": 1160}, "raw_text_unformatted": "$1,516.67", "value": "1516.67"}}, "CONFIDENCE": 0.9990196228027344, "ENTITY_TYPE": "CURRENCY"}, {"ENTITY_ID": "239883d2-37c8-4e12-95ec-e91512462482", "PAGE": 3, "CONTENT": {"CONTENT": {"word_ids": ["word_3_408"], "coordinates": {"y0": 2530, "x0": 2085, "y1": 2555, "x1": 2200}, "raw_text_unformatted": "$1,516.67", "value": "1516.67"}}, "CONFIDENCE": 0.9986571669578552, "ENTITY_TYPE": "CURRENCY"}, {"ENTITY_ID": "36113911-0223-4e0d-8dee-8820c4145707", "PAGE": 3, "CONTENT": {"CONTENT": {"word_ids": ["word_3_409"], "coordinates": {"y0": 2566, "x0": 238, "y1": 2587, "x1": 264}, "raw_text_unformatted": "14", "value": "14"}}, "CONFIDENCE": 0.8576689958572388, "ENTITY_TYPE": "CURRENCY"}, {"ENTITY_ID": "5570b46f-22a4-483c-a93e-cfb2622bf06a", "PAGE": 3, "CONTENT": {"CONTENT": {"word_ids": ["word_3_412"], "coordinates": {"y0": 2568, "x0": 1280, "y1": 2589, "x1": 1307}, "raw_text_unformatted": "16", "value": "16"}}, "CONFIDENCE": 0.9925326704978943, "ENTITY_TYPE": "CURRENCY"}, {"ENTITY_ID": "95daf47d-3f80-4ea1-b8b6-b8992e69e12b", "PAGE": 3, "CONTENT": {"CONTENT": {"word_ids": ["word_3_415"], "coordinates": {"y0": 2607, "x0": 238, "y1": 2628, "x1": 265}, "raw_text_unformatted": "15", "value": "15"}}, "CONFIDENCE": 0.9228290319442749, "ENTITY_TYPE": "CURRENCY"}, {"ENTITY_ID": "fd30bbc3-4e45-47db-98b5-d79b1d60c0b0", "PAGE": 3, "CONTENT": {"CONTENT": {"word_ids": ["word_3_430"], "coordinates": {"y0": 2787, "x0": 1013, "y1": 2813, "x1": 1155}, "raw_text_unformatted": "$169,966.91", "value": "169966.91"}}, "CONFIDENCE": 0.998654305934906, "ENTITY_TYPE": "CURRENCY"}, {"ENTITY_ID": "3b0846dd-0e74-4c4d-99e7-ee43658c9395", "PAGE": 3, "CONTENT": {"CONTENT": {"word_ids": ["word_3_438"], "coordinates": {"y0": 2791, "x0": 2052, "y1": 2817, "x1": 2198}, "raw_text_unformatted": "$163,84239", "value": "16384239"}}, "CONFIDENCE": 0.9997042417526245, "ENTITY_TYPE": "CURRENCY"}, {"ENTITY_ID": "e4040300-2991-4c39-9d9a-c0f5a1106b31", "PAGE": 3, "CONTENT": {"CONTENT": {"word_ids": ["word_3_466"], "coordinates": {"y0": 2868, "x0": 999, "y1": 2916, "x1": 1159}, "raw_text_unformatted": "$63,290.24", "value": "63290.24"}}, "CONFIDENCE": 0.9999499320983887, "ENTITY_TYPE": "CURRENCY"}, {"ENTITY_ID": "73c77282-5873-4135-99b7-c1f5991f5dd7", "PAGE": 3, "CONTENT": {"CONTENT": {"word_ids": ["word_3_472"], "coordinates": {"y0": 2874, "x0": 2038, "y1": 2900, "x1": 2199}, "raw_text_unformatted": "$151,855.72", "value": "151855.72"}}, "CONFIDENCE": 0.9999538064002991, "ENTITY_TYPE": "CURRENCY"}, {"ENTITY_ID": "e1c42144-91da-442b-8051-eeca6a57473e", "PAGE": 3, "CONTENT": {"CONTENT": {"word_ids": ["word_3_484"], "coordinates": {"y0": 2970, "x0": 1747, "y1": 2992, "x1": 1760}, "raw_text_unformatted": "3", "value": "3"}}, "CONFIDENCE": 0.660467267036438, "ENTITY_TYPE": "CURRENCY"}, {"ENTITY_ID": "d1502c3b-e88d-4628-a54f-e181fa487c1f", "PAGE": 3, "CONTENT": {"CONTENT": {"word_ids": ["word_3_492"], "coordinates": {"y0": 2970, "x0": 2080, "y1": 2992, "x1": 2184}, "raw_text_unformatted": "10154027", "value": "10154027"}}, "CONFIDENCE": 0.8043798804283142, "ENTITY_TYPE": "CURRENCY"}, {"ENTITY_ID": "3213f0f9-d6b6-42af-88b5-2b57f690a3d5", "PAGE": 4, "CONTENT": {"CONTENT": {"word_ids": ["word_4_23"], "coordinates": {"y0": 537, "x0": 231, "y1": 570, "x1": 263}, "raw_text_unformatted": "3", "value": "3"}}, "CONFIDENCE": 0.9729149341583252, "ENTITY_TYPE": "CURRENCY"}, {"ENTITY_ID": "c8871a9f-f35a-469b-a1dc-3fb01da145c9", "PAGE": 4, "CONTENT": {"CONTENT": {"word_ids": ["word_4_93"], "coordinates": {"y0": 1007, "x0": 654, "y1": 1031, "x1": 685}, "raw_text_unformatted": "75", "value": "75"}}, "CONFIDENCE": 0.7178365588188171, "ENTITY_TYPE": "CURRENCY"}, {"ENTITY_ID": "18c6e3b7-7b3e-4bcd-9408-5ab2f9879c2b", "PAGE": 4, "CONTENT": {"CONTENT": {"word_ids": ["word_4_104"], "coordinates": {"y0": 1045, "x0": 374, "y1": 1068, "x1": 419}, "raw_text_unformatted": "5%", "value": "5"}}, "CONFIDENCE": 0.9988980889320374, "ENTITY_TYPE": "CURRENCY"}, {"ENTITY_ID": "bd84a8ff-cc2e-469e-926d-15341a42afb4", "PAGE": 4, "CONTENT": {"CONTENT": {"word_ids": ["word_4_230"], "coordinates": {"y0": 1639, "x0": 221, "y1": 1670, "x1": 254}, "raw_text_unformatted": "09", "value": "09"}}, "CONFIDENCE": 0.6744271516799927, "ENTITY_TYPE": "CURRENCY"}, {"ENTITY_ID": "d46f9506-b3ce-4375-8d0a-1c2a1ef78d90", "PAGE": 4, "CONTENT": {"CONTENT": {"word_ids": ["word_4_347"], "coordinates": {"y0": 2964, "x0": 740, "y1": 2985, "x1": 798}, "raw_text_unformatted": "0617", "value": "0617"}}, "CONFIDENCE": 0.7563800811767578, "ENTITY_TYPE": "CURRENCY"}, {"ENTITY_ID": "d9d3e1bb-6c86-4519-b39c-79d06891f546", "PAGE": 4, "CONTENT": {"CONTENT": {"word_ids": ["word_4_418"], "coordinates": {"y0": 874, "x0": 1580, "y1": 899, "x1": 1696}, "raw_text_unformatted": "$3.21057", "value": "3.21057"}}, "CONFIDENCE": 0.9997576475143433, "ENTITY_TYPE": "CURRENCY"}, {"ENTITY_ID": "54c5b1a5-f36f-4008-9dc4-d4209613d3d7", "PAGE": 4, "CONTENT": {"CONTENT": {"word_ids": ["word_4_424"], "coordinates": {"y0": 860, "x0": 2137, "y1": 882, "x1": 2144}, "raw_text_unformatted": "1", "value": "1"}}, "CONFIDENCE": 0.8744157552719116, "ENTITY_TYPE": "CURRENCY"}, {"ENTITY_ID": "dae6b2b3-db1d-423a-a4e5-885aaba8047d", "PAGE": 4, "CONTENT": {"CONTENT": {"word_ids": ["word_4_428"], "coordinates": {"y0": 876, "x0": 1595, "y1": 901, "x1": 1681}, "raw_text_unformatted": "3,2105", "value": "32105"}}, "CONFIDENCE": 0.8078429102897644, "ENTITY_TYPE": "CURRENCY"}, {"ENTITY_ID": "c5592586-be5e-48cf-b551-72737bc209dc", "PAGE": 4, "CONTENT": {"CONTENT": {"word_ids": ["word_4_435"], "coordinates": {"y0": 920, "x0": 1395, "y1": 942, "x1": 1404}, "raw_text_unformatted": "1", "value": "1"}}, "CONFIDENCE": 0.7371576428413391, "ENTITY_TYPE": "CURRENCY"}, {"ENTITY_ID": "6c38f64a-1bc4-49bd-9692-ff57a059e387", "PAGE": 4, "CONTENT": {"CONTENT": {"word_ids": ["word_4_441"], "coordinates": {"y0": 1020, "x0": 1579, "y1": 1045, "x1": 1696}, "raw_text_unformatted": "$1,320.00", "value": "1320.00"}}, "CONFIDENCE": 0.9987884163856506, "ENTITY_TYPE": "CURRENCY"}, {"ENTITY_ID": "fa00d6c8-67fa-4506-a7cd-08f5d4733d7b", "PAGE": 4, "CONTENT": {"CONTENT": {"word_ids": ["word_4_447"], "coordinates": {"y0": 1011, "x0": 2136, "y1": 1032, "x1": 2143}, "raw_text_unformatted": "1", "value": "1"}}, "CONFIDENCE": 0.5341301560401917, "ENTITY_TYPE": "CURRENCY"}, {"ENTITY_ID": "9bbbf1fb-b6a3-4755-b3fd-461edd638c77", "PAGE": 4, "CONTENT": {"CONTENT": {"word_ids": ["word_4_458"], "coordinates": {"y0": 1072, "x0": 1394, "y1": 1094, "x1": 1403}, "raw_text_unformatted": "1", "value": "1"}}, "CONFIDENCE": 0.9353432655334473, "ENTITY_TYPE": "CURRENCY"}, {"ENTITY_ID": "cb921173-4e1c-4afd-9a9d-0794425ab115", "PAGE": 4, "CONTENT": {"CONTENT": {"word_ids": ["word_4_469"], "coordinates": {"y0": 1217, "x0": 1578, "y1": 1241, "x1": 1694}, "raw_text_unformatted": "$1,310.78", "value": "1310.78"}}, "CONFIDENCE": 0.9995502829551697, "ENTITY_TYPE": "CURRENCY"}, {"ENTITY_ID": "31e60fae-b1ea-48c1-bbb8-7d32ec26b56b", "PAGE": 4, "CONTENT": {"CONTENT": {"word_ids": ["word_4_488"], "coordinates": {"y0": 1242, "x0": 2181, "y1": 1264, "x1": 2201}, "raw_text_unformatted": "2.", "value": "2."}}, "CONFIDENCE": 0.8348871469497681, "ENTITY_TYPE": "CURRENCY"}, {"ENTITY_ID": "903a766f-6326-435c-b22c-83b422f3b4c0", "PAGE": 4, "CONTENT": {"CONTENT": {"word_ids": ["word_4_490"], "coordinates": {"y0": 1343, "x0": 1598, "y1": 1369, "x1": 1693}, "raw_text_unformatted": "$339.56", "value": "339.56"}}, "CONFIDENCE": 0.9993839859962463, "ENTITY_TYPE": "CURRENCY"}, {"ENTITY_ID": "4ffb15c5-f0c5-4143-b41d-b33fafbf813d", "PAGE": 4, "CONTENT": {"CONTENT": {"word_ids": ["word_4_564"], "coordinates": {"y0": 1708, "x0": 2130, "y1": 1729, "x1": 2148}, "raw_text_unformatted": "1.", "value": "1."}}, "CONFIDENCE": 0.675595760345459, "ENTITY_TYPE": "CURRENCY"}, {"ENTITY_ID": "76e0a50b-4d00-46ea-9478-6645e581058a", "PAGE": 4, "CONTENT": {"CONTENT": {"word_ids": ["word_4_576"], "coordinates": {"y0": 1768, "x0": 1390, "y1": 1789, "x1": 1397}, "raw_text_unformatted": "1", "value": "1"}}, "CONFIDENCE": 0.5847994685173035, "ENTITY_TYPE": "CURRENCY"}, {"ENTITY_ID": "e22ea2e1-503f-4795-90f4-35e3becc83c3", "PAGE": 4, "CONTENT": {"CONTENT": {"word_ids": ["word_4_646"], "coordinates": {"y0": 2091, "x0": 1664, "y1": 2119, "x1": 1698}, "raw_text_unformatted": "2", "value": "2"}}, "CONFIDENCE": 0.8752059936523438, "ENTITY_TYPE": "CURRENCY"}, {"ENTITY_ID": "008b8c38-3c28-49cf-9fc0-cf13d9c7bea0", "PAGE": 4, "CONTENT": {"CONTENT": {"word_ids": ["word_4_667"], "coordinates": {"y0": 2132, "x0": 2058, "y1": 2161, "x1": 2093}, "raw_text_unformatted": "1", "value": "1"}}, "CONFIDENCE": 0.820055365562439, "ENTITY_TYPE": "CURRENCY"}, {"ENTITY_ID": "056f906d-28f2-472c-9a7d-f833486ba70a", "PAGE": 4, "CONTENT": {"CONTENT": {"word_ids": ["word_4_675"], "coordinates": {"y0": 2168, "x0": 1730, "y1": 2198, "x1": 1763}, "raw_text_unformatted": "2", "value": "2"}}, "CONFIDENCE": 0.6744881272315979, "ENTITY_TYPE": "CURRENCY"}, {"ENTITY_ID": "3d9dcf51-6688-434e-903f-248b9d9d8f4a", "PAGE": 4, "CONTENT": {"CONTENT": {"word_ids": ["word_4_684"], "coordinates": {"y0": 2204, "x0": 1361, "y1": 2233, "x1": 1394}, "raw_text_unformatted": "3", "value": "3"}}, "CONFIDENCE": 0.753466010093689, "ENTITY_TYPE": "CURRENCY"}, {"ENTITY_ID": "e170c2f3-e3c9-4dc0-9505-c8ccf17ece45", "PAGE": 4, "CONTENT": {"CONTENT": {"word_ids": ["word_4_717"], "coordinates": {"y0": 2972, "x0": 1739, "y1": 2994, "x1": 1753}, "raw_text_unformatted": "4", "value": "4"}}, "CONFIDENCE": 0.7887974977493286, "ENTITY_TYPE": "CURRENCY"}, {"ENTITY_ID": "80402a52-a756-4667-ab0d-f42885919ad0", "PAGE": 1, "CONTENT": {"CONTENT": {"word_ids": ["word_1_48"], "coordinates": {"y0": 508, "x0": 1894, "y1": 532, "x1": 1928}, "raw_text_unformatted": "20", "value": "20"}}, "CONFIDENCE": 0.9979475736618042, "ENTITY_TYPE": "CURRENCY"}, {"ENTITY_ID": "f26319db-8e06-429d-9a66-63ccff976e97", "PAGE": 1, "CONTENT": {"CONTENT": {"word_ids": ["word_1_79", "word_1_80"], "coordinates": {"y0": 658, "x0": 591, "y1": 690, "x1": 1187}, "raw_text_unformatted": "2277024 3127", "value": "22770243127"}}, "CONFIDENCE": 0.7286048531532288, "ENTITY_TYPE": "CURRENCY"}, {"ENTITY_ID": "96bfe4ca-801e-4fa6-a88f-572ffee85367", "PAGE": 1, "CONTENT": {"CONTENT": {"word_ids": ["word_1_90"], "coordinates": {"y0": 701, "x0": 591, "y1": 727, "x1": 658}, "raw_text_unformatted": "3127", "value": "3127"}}, "CONFIDENCE": 0.5737501978874207, "ENTITY_TYPE": "CURRENCY"}, {"ENTITY_ID": "0d9d1517-1442-47ba-8620-72b25f883daf", "PAGE": 1, "CONTENT": {"CONTENT": {"word_ids": ["word_1_97"], "coordinates": {"y0": 708, "x0": 1286, "y1": 732, "x1": 1369}, "raw_text_unformatted": "67205", "value": "67205"}}, "CONFIDENCE": 0.3289512097835541, "ENTITY_TYPE": "CURRENCY"}, {"ENTITY_ID": "ee26ec32-5433-4d3a-8407-61afd784bee7", "PAGE": 1, "CONTENT": {"CONTENT": {"word_ids": ["word_1_102"], "coordinates": {"y0": 743, "x0": 756, "y1": 768, "x1": 839}, "raw_text_unformatted": "67205", "value": "67205"}}, "CONFIDENCE": 0.3440806269645691, "ENTITY_TYPE": "CURRENCY"}, {"ENTITY_ID": "529668dc-6e1d-41d9-af5a-0a0acaffa6cf", "PAGE": 1, "CONTENT": {"CONTENT": {"word_ids": ["word_1_110"], "coordinates": {"y0": 797, "x0": 590, "y1": 827, "x1": 715}, "raw_text_unformatted": "$163,500", "value": "163500"}}, "CONFIDENCE": 0.9996266961097717, "ENTITY_TYPE": "CURRENCY"}, {"ENTITY_ID": "3690ae73-6688-458c-95a4-e5cd3f16474f", "PAGE": 1, "CONTENT": {"CONTENT": {"word_ids": ["word_1_120"], "coordinates": {"y0": 954, "x0": 834, "y1": 1001, "x1": 1027}, "raw_text_unformatted": "$103,500", "value": "103500"}}, "CONFIDENCE": 0.9996697306632996, "ENTITY_TYPE": "CURRENCY"}, {"ENTITY_ID": "ea10f44f-3347-4ab5-87e0-5772e3dba493", "PAGE": 1, "CONTENT": {"CONTENT": {"word_ids": ["word_1_124"], "coordinates": {"y0": 1059, "x0": 830, "y1": 1096, "x1": 891}, "raw_text_unformatted": "4.5", "value": "4.5"}}, "CONFIDENCE": 0.9991117119789124, "ENTITY_TYPE": "CURRENCY"}, {"ENTITY_ID": "a97e4102-07d4-4619-a8ab-960cd1c9b564", "PAGE": 1, "CONTENT": {"CONTENT": {"word_ids": ["word_1_131"], "coordinates": {"y0": 1208, "x0": 831, "y1": 1252, "x1": 997}, "raw_text_unformatted": "$654.79", "value": "654.79"}}, "CONFIDENCE": 0.9996256828308105, "ENTITY_TYPE": "CURRENCY"}, {"ENTITY_ID": "e733c9b4-0f00-4629-a5bb-896d0dd612e6", "PAGE": 1, "CONTENT": {"CONTENT": {"word_ids": ["word_1_172"], "coordinates": {"y0": 1843, "x0": 1473, "y1": 1874, "x1": 1591}, "raw_text_unformatted": "$654.79", "value": "654.79"}}, "CONFIDENCE": 0.9983338117599487, "ENTITY_TYPE": "CURRENCY"}, {"ENTITY_ID": "5b464ec8-1e04-4921-bbfa-395e714dd77e", "PAGE": 1, "CONTENT": {"CONTENT": {"word_ids": ["word_1_176"], "coordinates": {"y0": 1920, "x0": 1527, "y1": 1945, "x1": 1546}, "raw_text_unformatted": "0", "value": "0"}}, "CONFIDENCE": 0.5988297462463379, "ENTITY_TYPE": "CURRENCY"}, {"ENTITY_ID": "08037b1a-9978-4b21-8512-22453138c15e", "PAGE": 1, "CONTENT": {"CONTENT": {"word_ids": ["word_1_180"], "coordinates": {"y0": 1993, "x0": 1489, "y1": 2020, "x1": 1591}, "raw_text_unformatted": "339.56", "value": "339.56"}}, "CONFIDENCE": 0.6655687093734741, "ENTITY_TYPE": "CURRENCY"}, {"ENTITY_ID": "5e8f2f2d-699f-4fec-b5b5-cfbe29780034", "PAGE": 1, "CONTENT": {"CONTENT": {"word_ids": ["word_1_190"], "coordinates": {"y0": 2110, "x0": 1430, "y1": 2155, "x1": 1594}, "raw_text_unformatted": "$994.35", "value": "994.35"}}, "CONFIDENCE": 0.9996470212936401, "ENTITY_TYPE": "CURRENCY"}, {"ENTITY_ID": "cec20921-06c0-4e40-bb21-d4da06ea6190", "PAGE": 1, "CONTENT": {"CONTENT": {"word_ids": ["word_1_205"], "coordinates": {"y0": 2294, "x0": 847, "y1": 2338, "x1": 1014}, "raw_text_unformatted": "$459.56", "value": "459.56"}}, "CONFIDENCE": 0.9981278777122498, "ENTITY_TYPE": "CURRENCY"}, {"ENTITY_ID": "f35cc13a-36d4-49ed-86dc-462b54efe234", "PAGE": 1, "CONTENT": {"CONTENT": {"word_ids": ["word_1_221"], "coordinates": {"y0": 2409, "x0": 417, "y1": 2432, "x1": 433}, "raw_text_unformatted": "4", "value": "4"}}, "CONFIDENCE": 0.927131175994873, "ENTITY_TYPE": "CURRENCY"}, {"ENTITY_ID": "7c18b166-2f7d-46a2-814f-9646f8c757f8", "PAGE": 1, "CONTENT": {"CONTENT": {"word_ids": ["word_1_229"], "coordinates": {"y0": 2420, "x0": 1566, "y1": 2443, "x1": 1582}, "raw_text_unformatted": "4", "value": "4"}}, "CONFIDENCE": 0.983512818813324, "ENTITY_TYPE": "CURRENCY"}, {"ENTITY_ID": "694159b4-fb6f-43ed-b04e-d0ca760b0b55", "PAGE": 1, "CONTENT": {"CONTENT": {"word_ids": ["word_1_248"], "coordinates": {"y0": 2688, "x0": 798, "y1": 2733, "x1": 1000}, "raw_text_unformatted": "$6,549.52", "value": "6549.52"}}, "CONFIDENCE": 0.9993271231651306, "ENTITY_TYPE": "CURRENCY"}, {"ENTITY_ID": "e5e20d1d-2d4f-4e59-b8e6-c052280e9aad", "PAGE": 1, "CONTENT": {"CONTENT": {"word_ids": ["word_1_250"], "coordinates": {"y0": 2697, "x0": 1281, "y1": 2730, "x1": 1425}, "raw_text_unformatted": "$2,312.95", "value": "2312.95"}}, "CONFIDENCE": 0.999446451663971, "ENTITY_TYPE": "CURRENCY"}, {"ENTITY_ID": "ee5bde4c-b528-4d9e-85d8-79491d5bcff7", "PAGE": 1, "CONTENT": {"CONTENT": {"word_ids": ["word_1_255"], "coordinates": {"y0": 2701, "x0": 1678, "y1": 2734, "x1": 1824}, "raw_text_unformatted": "$4,486.57", "value": "4486.57"}}, "CONFIDENCE": 0.9936231970787048, "ENTITY_TYPE": "CURRENCY"}, {"ENTITY_ID": "4779a4eb-86e0-474b-9487-86bfeb809aab", "PAGE": 1, "CONTENT": {"CONTENT": {"word_ids": ["word_1_260"], "coordinates": {"y0": 2704, "x0": 2079, "y1": 2737, "x1": 2200}, "raw_text_unformatted": "$250.00", "value": "250.00"}}, "CONFIDENCE": 0.9993104338645935, "ENTITY_TYPE": "CURRENCY"}, {"ENTITY_ID": "58d2e41b-dd86-45ac-8fa4-25525f127b18", "PAGE": 1, "CONTENT": {"CONTENT": {"word_ids": ["word_1_266"], "coordinates": {"y0": 2743, "x0": 1568, "y1": 2769, "x1": 1589}, "raw_text_unformatted": "2", "value": "2"}}, "CONFIDENCE": 0.9668988585472107, "ENTITY_TYPE": "CURRENCY"}, {"ENTITY_ID": "3542b313-a0b8-4ef4-bf4e-0a2561708a55", "PAGE": 1, "CONTENT": {"CONTENT": {"word_ids": ["word_1_273"], "coordinates": {"y0": 2818, "x0": 797, "y1": 2866, "x1": 1028}, "raw_text_unformatted": "$63,290.24", "value": "63290.24"}}, "CONFIDENCE": 0.9998841881752014, "ENTITY_TYPE": "CURRENCY"}, {"ENTITY_ID": "45b9001e-ed7e-400e-b54c-a61ea2ecd995", "PAGE": 1, "CONTENT": {"CONTENT": {"word_ids": ["word_1_284"], "coordinates": {"y0": 2843, "x0": 2034, "y1": 2867, "x1": 2052}, "raw_text_unformatted": "3", "value": "3"}}, "CONFIDENCE": 0.9858042597770691, "ENTITY_TYPE": "CURRENCY"}, {"ENTITY_ID": "9293fcb8-8155-43d4-be0e-80be468140b7", "PAGE": 1, "CONTENT": {"CONTENT": {"word_ids": ["word_1_293"], "coordinates": {"y0": 2971, "x0": 778, "y1": 2992, "x1": 835}, "raw_text_unformatted": "0617", "value": "0617"}}, "CONFIDENCE": 0.47599726915359497, "ENTITY_TYPE": "CURRENCY"}, {"ENTITY_ID": "3f70a98b-17f0-4df2-a4fe-df1e293e5b25", "PAGE": 1, "CONTENT": {"CONTENT": {"word_ids": ["word_1_295"], "coordinates": {"y0": 2982, "x0": 1779, "y1": 3003, "x1": 1787}, "raw_text_unformatted": "1", "value": "1"}}, "CONFIDENCE": 0.7974606156349182, "ENTITY_TYPE": "CURRENCY"}, {"ENTITY_ID": "eb551c39-5523-47cf-87ea-34c895e7d510-ROUTE", "PAGE": 5, "CONTENT": {"CONTENT": {"word_ids": ["word_5_415", "word_5_416", "word_5_417", "word_5_418"], "coordinates": {"y0": 1833, "x0": 609, "y1": 1856, "x1": 814}, "raw_text_unformatted": "7555 W 21st StN", "value": "7555 W 21st StN"}}, "CONFIDENCE": 0.802750825881958, "ENTITY_TYPE": "ROUTE"}, {"ENTITY_ID": "e0509e03-0a71-4e61-bbb2-40fcd4523ecb-ROUTE", "PAGE": 5, "CONTENT": {"CONTENT": {"word_ids": ["word_5_493", "word_5_494", "word_5_495"], "coordinates": {"y0": 1831, "x0": 1968, "y1": 1876, "x1": 2118}, "raw_text_unformatted": "N Ridge Rd,", "value": "N Ridge Rd,"}}, "CONFIDENCE": 0.8247308135032654, "ENTITY_TYPE": "ROUTE"}, {"ENTITY_ID": "30b0521a-3e15-4890-bf5c-7c7a9541a37c-ROUTE", "PAGE": 4, "CONTENT": {"CONTENT": {"word_ids": ["word_4_316", "word_4_317", "word_4_318", "word_4_319", "word_4_320"], "coordinates": {"y0": 2189, "x0": 219, "y1": 2222, "x1": 560}, "raw_text_unformatted": "3127 N Westwind Bay St,", "value": "3127 N Westwind Bay St,"}}, "CONFIDENCE": 0.9919405579566956, "ENTITY_TYPE": "ROUTE"}, {"ENTITY_ID": "3c13d7d5-eb71-4518-bc23-3c4c3ca1e7bd-ROUTE", "PAGE": 1, "CONTENT": {"CONTENT": {"word_ids": ["word_1_54", "word_1_55", "word_1_56"], "coordinates": {"y0": 542, "x0": 1213, "y1": 568, "x1": 1358}, "raw_text_unformatted": "W Birch Ln", "value": "W Birch Ln"}}, "CONFIDENCE": 0.569457471370697, "ENTITY_TYPE": "ROUTE"}, {"ENTITY_ID": "6b3ebe2f-20e1-4f05-bce9-ac4af49b5a07-ROUTE", "PAGE": 1, "CONTENT": {"CONTENT": {"word_ids": ["word_1_82", "word_1_83", "word_1_84"], "coordinates": {"y0": 665, "x0": 1223, "y1": 698, "x1": 1453}, "raw_text_unformatted": "Westwind Bay St", "value": "Westwind Bay St"}}, "CONFIDENCE": 0.9547657370567322, "ENTITY_TYPE": "ROUTE"}, {"ENTITY_ID": "d550c8ff-b9c3-4ef1-9b35-60a38e65b420", "PAGE": 5, "CONTENT": {"CONTENT": {"word_ids": ["word_5_550", "word_5_551", "word_5_552", "word_5_553"], "coordinates": {"y0": 2996, "x0": 211, "y1": 3021, "x1": 520}, "raw_text_unformatted": "10/04/2018 01:57 PM PST", "value": "10/04/2018"}}, "CONFIDENCE": 0.9314621686935425, "ENTITY_TYPE": "DATE"}, {"ENTITY_ID": "d94f9a26-f991-4ee2-9ec2-41bd7f65d7d9", "PAGE": 2, "CONTENT": {"CONTENT": {"word_ids": ["word_2_217"], "coordinates": {"y0": 1892, "x0": 819, "y1": 1915, "x1": 927}, "raw_text_unformatted": "10/12/18", "value": "10/12/2018"}}, "CONFIDENCE": 0.9954800605773926, "ENTITY_TYPE": "DATE"}, {"ENTITY_ID": "d00e25db-c450-44f0-bd44-9c52b5f44390", "PAGE": 2, "CONTENT": {"CONTENT": {"word_ids": ["word_2_219"], "coordinates": {"y0": 1893, "x0": 968, "y1": 1919, "x1": 1076}, "raw_text_unformatted": "11/1/18", "value": "11/01/2018"}}, "CONFIDENCE": 0.9893093109130859, "ENTITY_TYPE": "DATE"}, {"ENTITY_ID": "5d814bf5-5640-4f60-a3a3-964430f5ebaa", "PAGE": 2, "CONTENT": {"CONTENT": {"word_ids": ["word_2_361", "word_2_362", "word_2_363", "word_2_364"], "coordinates": {"y0": 3002, "x0": 259, "y1": 3026, "x1": 568}, "raw_text_unformatted": "10/04/2018 01:57 PM PST", "value": "10/04/2018"}}, "CONFIDENCE": 0.9401480555534363, "ENTITY_TYPE": "DATE"}, {"ENTITY_ID": "e564815c-e2bd-4620-878a-32a13eae2150", "PAGE": 3, "CONTENT": {"CONTENT": {"word_ids": ["word_3_200"], "coordinates": {"y0": 1374, "x0": 423, "y1": 1396, "x1": 561}, "raw_text_unformatted": "10/13/2018", "value": "10/13/2018"}}, "CONFIDENCE": 0.9709521532058716, "ENTITY_TYPE": "DATE"}, {"ENTITY_ID": "9f715830-d3d4-4c68-b199-bd4e848c1623", "PAGE": 3, "CONTENT": {"CONTENT": {"word_ids": ["word_3_202"], "coordinates": {"y0": 1375, "x0": 630, "y1": 1397, "x1": 768}, "raw_text_unformatted": "12/31/2018", "value": "12/31/2018"}}, "CONFIDENCE": 0.9676195383071899, "ENTITY_TYPE": "DATE"}, {"ENTITY_ID": "b92de6c8-c338-40ec-bb38-823ae09ce2e6", "PAGE": 3, "CONTENT": {"CONTENT": {"word_ids": ["word_3_251"], "coordinates": {"y0": 1658, "x0": 1481, "y1": 1681, "x1": 1618}, "raw_text_unformatted": "10/13/2018", "value": "10/13/2018"}}, "CONFIDENCE": 0.8165705800056458, "ENTITY_TYPE": "DATE"}, {"ENTITY_ID": "4c240528-fc81-4fa5-8c74-a4c065b87740", "PAGE": 3, "CONTENT": {"CONTENT": {"word_ids": ["word_3_253"], "coordinates": {"y0": 1659, "x0": 1688, "y1": 1682, "x1": 1825}, "raw_text_unformatted": "12/31/2018", "value": "12/31/2018"}}, "CONFIDENCE": 0.9785984754562378, "ENTITY_TYPE": "DATE"}, {"ENTITY_ID": "13d040c5-6db5-4a49-9822-c7be9bfe90ba", "PAGE": 3, "CONTENT": {"CONTENT": {"word_ids": ["word_3_398"], "coordinates": {"y0": 2526, "x0": 528, "y1": 2549, "x1": 639}, "raw_text_unformatted": "01/01/18", "value": "01/01/2018"}}, "CONFIDENCE": 0.9891306161880493, "ENTITY_TYPE": "DATE"}, {"ENTITY_ID": "f5d1bcc8-a1b9-4755-a9ce-8f393747e46d", "PAGE": 3, "CONTENT": {"CONTENT": {"word_ids": ["word_3_400"], "coordinates": {"y0": 2527, "x0": 686, "y1": 2549, "x1": 793}, "raw_text_unformatted": "10/12/18", "value": "10/12/2018"}}, "CONFIDENCE": 0.9495164752006531, "ENTITY_TYPE": "DATE"}, {"ENTITY_ID": "e661c3c7-cd1a-4c63-a354-2aed91a4a581", "PAGE": 3, "CONTENT": {"CONTENT": {"word_ids": ["word_3_405"], "coordinates": {"y0": 2527, "x0": 1568, "y1": 2549, "x1": 1679}, "raw_text_unformatted": "01/01/18", "value": "01/01/2018"}}, "CONFIDENCE": 0.9872931241989136, "ENTITY_TYPE": "DATE"}, {"ENTITY_ID": "bb85f0df-6fc0-415b-bbf3-33445332c26a", "PAGE": 3, "CONTENT": {"CONTENT": {"word_ids": ["word_3_407"], "coordinates": {"y0": 2528, "x0": 1727, "y1": 2551, "x1": 1835}, "raw_text_unformatted": "10/12/18", "value": "10/12/2018"}}, "CONFIDENCE": 0.8525967597961426, "ENTITY_TYPE": "DATE"}, {"ENTITY_ID": "e5752998-5122-43ab-ae37-f611e53f4ae6", "PAGE": 3, "CONTENT": {"CONTENT": {"word_ids": ["word_3_479", "word_3_480", "word_3_481", "word_3_482"], "coordinates": {"y0": 3001, "x0": 222, "y1": 3026, "x1": 532}, "raw_text_unformatted": "10/04/2018 01:57 PM PST", "value": "10/04/2018"}}, "CONFIDENCE": 0.9240185022354126, "ENTITY_TYPE": "DATE"}, {"ENTITY_ID": "6bb6a275-87c6-4dc1-ba25-30e829d74011", "PAGE": 4, "CONTENT": {"CONTENT": {"word_ids": ["word_4_348"], "coordinates": {"y0": 2994, "x0": 212, "y1": 3017, "x1": 351}, "raw_text_unformatted": "10/04/2018", "value": "10/04/2018"}}, "CONFIDENCE": 0.9800198078155518, "ENTITY_TYPE": "DATE"}, {"ENTITY_ID": "f21a15a6-afa5-4a42-8ec9-77f862ae6481", "PAGE": 4, "CONTENT": {"CONTENT": {"word_ids": ["word_4_349", "word_4_350", "word_4_351"], "coordinates": {"y0": 2995, "x0": 358, "y1": 3019, "x1": 523}, "raw_text_unformatted": "01:57 PM PST", "value": "08/25/2020"}}, "CONFIDENCE": 0.8448100090026855, "ENTITY_TYPE": "DATE"}, {"ENTITY_ID": "264de2e8-7f25-41c0-9056-da0fe3d31ffd", "PAGE": 1, "CONTENT": {"CONTENT": {"word_ids": ["word_1_38"], "coordinates": {"y0": 498, "x0": 595, "y1": 524, "x1": 733}, "raw_text_unformatted": "10/4/2018", "value": "10/04/2018"}}, "CONFIDENCE": 0.9987632036209106, "ENTITY_TYPE": "DATE"}, {"ENTITY_ID": "0e31f753-b845-4206-b03d-f2baed90a06a", "PAGE": 1, "CONTENT": {"CONTENT": {"word_ids": ["word_1_52"], "coordinates": {"y0": 537, "x0": 595, "y1": 564, "x1": 750}, "raw_text_unformatted": "10/12/2018", "value": "10/12/2018"}}, "CONFIDENCE": 0.9981911778450012, "ENTITY_TYPE": "DATE"}, {"ENTITY_ID": "634c2ab9-8c7b-4696-8f09-3c4af0f55dbd", "PAGE": 1, "CONTENT": {"CONTENT": {"word_ids": ["word_1_61"], "coordinates": {"y0": 579, "x0": 594, "y1": 605, "x1": 750}, "raw_text_unformatted": "10/12/2018", "value": "10/12/2018"}}, "CONFIDENCE": 0.9951025247573853, "ENTITY_TYPE": "DATE"}, {"ENTITY_ID": "66fdd4f8-c89f-47e9-8e08-46446fb0d0a2", "PAGE": 1, "CONTENT": {"CONTENT": {"word_ids": ["word_1_302", "word_1_303", "word_1_304"], "coordinates": {"y0": 3000, "x0": 250, "y1": 3025, "x1": 508}, "raw_text_unformatted": "10/04/2018 01:57 PM", "value": "10/04/2018"}}, "CONFIDENCE": 0.8712682127952576, "ENTITY_TYPE": "DATE"}, {"ENTITY_ID": "eb551c39-5523-47cf-87ea-34c895e7d510-CITY", "PAGE": 5, "CONTENT": {"CONTENT": {"word_ids": ["word_5_419"], "coordinates": {"y0": 1865, "x0": 608, "y1": 1892, "x1": 706}, "raw_text_unformatted": "Wichita,", "value": "Wichita,"}}, "CONFIDENCE": 0.802750825881958, "ENTITY_TYPE": "CITY"}, {"ENTITY_ID": "9ccc81e8-3a0d-4cb2-9477-e52d1b05c97d-CITY", "PAGE": 5, "CONTENT": {"CONTENT": {"word_ids": ["word_5_475"], "coordinates": {"y0": 1873, "x0": 1582, "y1": 1900, "x1": 1680}, "raw_text_unformatted": "Wichita,", "value": "Wichita,"}}, "CONFIDENCE": 0.786299467086792, "ENTITY_TYPE": "CITY"}, {"ENTITY_ID": "2a72cb9c-946d-489d-a03b-2113ff0ac3d8-CITY", "PAGE": 5, "CONTENT": {"CONTENT": {"word_ids": ["word_5_491"], "coordinates": {"y0": 1785, "x0": 2056, "y1": 1808, "x1": 2112}, "raw_text_unformatted": "Title", "value": "Title"}}, "CONFIDENCE": 0.6520243883132935, "ENTITY_TYPE": "CITY"}, {"ENTITY_ID": "e0509e03-0a71-4e61-bbb2-40fcd4523ecb-CITY", "PAGE": 5, "CONTENT": {"CONTENT": {"word_ids": ["word_5_498"], "coordinates": {"y0": 1908, "x0": 1908, "y1": 1935, "x1": 2005}, "raw_text_unformatted": "Wichita,", "value": "Wichita,"}}, "CONFIDENCE": 0.8247308135032654, "ENTITY_TYPE": "CITY"}, {"ENTITY_ID": "30b0521a-3e15-4890-bf5c-7c7a9541a37c-CITY", "PAGE": 4, "CONTENT": {"CONTENT": {"word_ids": ["word_4_321"], "coordinates": {"y0": 2190, "x0": 573, "y1": 2220, "x1": 678}, "raw_text_unformatted": "Wichita,", "value": "Wichita,"}}, "CONFIDENCE": 0.9919405579566956, "ENTITY_TYPE": "CITY"}, {"ENTITY_ID": "f7c5326c-51d1-4343-bfae-e30cb80e22c8-CITY", "PAGE": 1, "CONTENT": {"CONTENT": {"word_ids": ["word_1_62"], "coordinates": {"y0": 582, "x0": 1120, "y1": 612, "x1": 1230}, "raw_text_unformatted": "Wichita,", "value": "Wichita,"}}, "CONFIDENCE": 0.9760974049568176, "ENTITY_TYPE": "CITY"}, {"ENTITY_ID": "ebc01b05-3fec-48d3-b0e6-5cba52463ed7-CITY", "PAGE": 1, "CONTENT": {"CONTENT": {"word_ids": ["word_1_94", "word_1_95"], "coordinates": {"y0": 703, "x0": 895, "y1": 734, "x1": 1230}, "raw_text_unformatted": "St Wichita,", "value": "St Wichita,"}}, "CONFIDENCE": 0.9686533212661743, "ENTITY_TYPE": "CITY"}, {"ENTITY_ID": "4b011087-c2f9-4a0e-9250-919f6bd05384", "PAGE": 5, "CONTENT": {"CONTENT": {"word_ids": ["word_5_562"], "coordinates": {"y0": 2825, "x0": 2070, "y1": 2870, "x1": 2211}, "raw_text_unformatted": "2008", "value": "2008"}}, "CONFIDENCE": 0.7761712670326233, "ENTITY_TYPE": "YEAR"}, {"ENTITY_ID": "eb551c39-5523-47cf-87ea-34c895e7d510-ZIPCODE", "PAGE": 5, "CONTENT": {"CONTENT": {"word_ids": ["word_5_421"], "coordinates": {"y0": 1867, "x0": 750, "y1": 1890, "x1": 825}, "raw_text_unformatted": "67205", "value": "67205"}}, "CONFIDENCE": 0.802750825881958, "ENTITY_TYPE": "ZIPCODE"}, {"ENTITY_ID": "9ccc81e8-3a0d-4cb2-9477-e52d1b05c97d-ZIPCODE", "PAGE": 5, "CONTENT": {"CONTENT": {"word_ids": ["word_5_477"], "coordinates": {"y0": 1876, "x0": 1725, "y1": 1897, "x1": 1801}, "raw_text_unformatted": "67212", "value": "67212"}}, "CONFIDENCE": 0.786299467086792, "ENTITY_TYPE": "ZIPCODE"}, {"ENTITY_ID": "e0509e03-0a71-4e61-bbb2-40fcd4523ecb-ZIPCODE", "PAGE": 5, "CONTENT": {"CONTENT": {"word_ids": ["word_5_500"], "coordinates": {"y0": 1911, "x0": 2049, "y1": 1933, "x1": 2126}, "raw_text_unformatted": "67205", "value": "67205"}}, "CONFIDENCE": 0.8247308135032654, "ENTITY_TYPE": "ZIPCODE"}, {"ENTITY_ID": "30b0521a-3e15-4890-bf5c-7c7a9541a37c-ZIPCODE", "PAGE": 4, "CONTENT": {"CONTENT": {"word_ids": ["word_4_323"], "coordinates": {"y0": 2193, "x0": 728, "y1": 2217, "x1": 815}, "raw_text_unformatted": "67205", "value": "67205"}}, "CONFIDENCE": 0.9919405579566956, "ENTITY_TYPE": "ZIPCODE"}, {"ENTITY_ID": "3f7ea1c9-dc2e-4a2a-b74d-a525345c9d39-ZIPCODE", "PAGE": 1, "CONTENT": {"CONTENT": {"word_ids": ["word_1_53"], "coordinates": {"y0": 543, "x0": 1123, "y1": 567, "x1": 1205}, "raw_text_unformatted": "11706", "value": "11706"}}, "CONFIDENCE": 0.6900041699409485, "ENTITY_TYPE": "ZIPCODE"}, {"ENTITY_ID": "f7c5326c-51d1-4343-bfae-e30cb80e22c8-ZIPCODE", "PAGE": 1, "CONTENT": {"CONTENT": {"word_ids": ["word_1_64"], "coordinates": {"y0": 584, "x0": 1279, "y1": 609, "x1": 1364}, "raw_text_unformatted": "67212", "value": "67212"}}, "CONFIDENCE": 0.9760974049568176, "ENTITY_TYPE": "ZIPCODE"}, {"ENTITY_ID": "3c503da2-ff34-40f6-9aef-47c730a85804_1", "PAGE": 5, "CONTENT": {"CONTENT": {"word_ids": ["word_5_146"], "coordinates": {"y0": 2017, "x0": 235, "y1": 2042, "x1": 270}, "raw_text_unformatted": "KS", "value": "KS"}}, "CONFIDENCE": 0.4055367410182953, "ENTITY_TYPE": "PERSON NAME"}, {"ENTITY_ID": "a2f0cab3-de7f-4725-b69b-395e4a9ed1ba_1", "PAGE": 5, "CONTENT": {"CONTENT": {"word_ids": ["word_5_424"], "coordinates": {"y0": 2080, "x0": 604, "y1": 2103, "x1": 672}, "raw_text_unformatted": "Janet", "value": "Janet"}}, "CONFIDENCE": 0.9964419603347778, "ENTITY_TYPE": "PERSON NAME"}, {"ENTITY_ID": "a2f0cab3-de7f-4725-b69b-395e4a9ed1ba_2", "PAGE": 5, "CONTENT": {"CONTENT": {"word_ids": ["word_5_425"], "coordinates": {"y0": 2081, "x0": 679, "y1": 2103, "x1": 692}, "raw_text_unformatted": "L", "value": "L"}}, "CONFIDENCE": 0.9964419603347778, "ENTITY_TYPE": "PERSON NAME"}, {"ENTITY_ID": "a2f0cab3-de7f-4725-b69b-395e4a9ed1ba_3", "PAGE": 5, "CONTENT": {"CONTENT": {"word_ids": ["word_5_426"], "coordinates": {"y0": 2081, "x0": 699, "y1": 2103, "x1": 772}, "raw_text_unformatted": "Wetta", "value": "Wetta"}}, "CONFIDENCE": 0.9964419603347778, "ENTITY_TYPE": "PERSON NAME"}, {"ENTITY_ID": "496546dd-18e1-4293-ae38-15c398265bdb-PERSON_1", "PAGE": 5, "CONTENT": {"CONTENT": {"word_ids": ["word_5_434"], "coordinates": {"y0": 1776, "x0": 934, "y1": 1799, "x1": 981}, "raw_text_unformatted": "N/A", "value": "N/A"}}, "CONFIDENCE": 0.5061681866645813, "ENTITY_TYPE": "PERSON NAME"}, {"ENTITY_ID": "6b36831d-3bbc-48de-99c1-737e1a0fcfa9-PERSON_1", "PAGE": 5, "CONTENT": {"CONTENT": {"word_ids": ["word_5_435"], "coordinates": {"y0": 1835, "x0": 934, "y1": 1858, "x1": 980}, "raw_text_unformatted": "N/A", "value": "N/A"}}, "CONFIDENCE": 0.4409335255622864, "ENTITY_TYPE": "PERSON NAME"}, {"ENTITY_ID": "b403e88b-50bb-4ef9-be56-fb6a2e2ad720_1", "PAGE": 5, "CONTENT": {"CONTENT": {"word_ids": ["word_5_446"], "coordinates": {"y0": 1778, "x0": 1258, "y1": 1801, "x1": 1322}, "raw_text_unformatted": "Theis", "value": "Theis"}}, "CONFIDENCE": 0.9315842390060425, "ENTITY_TYPE": "PERSON NAME"}, {"ENTITY_ID": "b403e88b-50bb-4ef9-be56-fb6a2e2ad720_2", "PAGE": 5, "CONTENT": {"CONTENT": {"word_ids": ["word_5_447"], "coordinates": {"y0": 1779, "x0": 1330, "y1": 1808, "x1": 1406}, "raw_text_unformatted": "Reaity", "value": "Reaity"}}, "CONFIDENCE": 0.9315842390060425, "ENTITY_TYPE": "PERSON NAME"}, {"ENTITY_ID": "d7f978c6-ffa9-4090-8870-114c0976b916_1", "PAGE": 5, "CONTENT": {"CONTENT": {"word_ids": ["word_5_450"], "coordinates": {"y0": 1838, "x0": 1351, "y1": 1861, "x1": 1414}, "raw_text_unformatted": "Keith", "value": "Keith"}}, "CONFIDENCE": 0.5199297070503235, "ENTITY_TYPE": "PERSON NAME"}, {"ENTITY_ID": "efc106cf-8f6e-437e-9615-a1daa5caef72_1", "PAGE": 5, "CONTENT": {"CONTENT": {"word_ids": ["word_5_457"], "coordinates": {"y0": 2080, "x0": 1254, "y1": 2120, "x1": 1300}, "raw_text_unformatted": "Jeff", "value": "Jeff"}}, "CONFIDENCE": 0.9971674680709839, "ENTITY_TYPE": "PERSON NAME"}, {"ENTITY_ID": "efc106cf-8f6e-437e-9615-a1daa5caef72_2", "PAGE": 5, "CONTENT": {"CONTENT": {"word_ids": ["word_5_458"], "coordinates": {"y0": 2080, "x0": 1303, "y1": 2120, "x1": 1367}, "raw_text_unformatted": "Theis", "value": "Theis"}}, "CONFIDENCE": 0.9971674680709839, "ENTITY_TYPE": "PERSON NAME"}, {"ENTITY_ID": "cf915163-a6f3-43aa-8695-eb5ab96824bc_1", "PAGE": 5, "CONTENT": {"CONTENT": {"word_ids": ["word_5_473"], "coordinates": {"y0": 1841, "x0": 1677, "y1": 1864, "x1": 1739}, "raw_text_unformatted": "Keith", "value": "Keith"}}, "CONFIDENCE": 0.4963740408420563, "ENTITY_TYPE": "PERSON NAME"}, {"ENTITY_ID": "cf915163-a6f3-43aa-8695-eb5ab96824bc_2", "PAGE": 5, "CONTENT": {"CONTENT": {"word_ids": ["word_5_474"], "coordinates": {"y0": 1842, "x0": 1747, "y1": 1864, "x1": 1773}, "raw_text_unformatted": "Ct", "value": "Ct"}}, "CONFIDENCE": 0.4963740408420563, "ENTITY_TYPE": "PERSON NAME"}, {"ENTITY_ID": "9ec85982-cc85-4657-859d-e04b14e6e837_1", "PAGE": 5, "CONTENT": {"CONTENT": {"word_ids": ["word_5_480"], "coordinates": {"y0": 2087, "x0": 1580, "y1": 2111, "x1": 1625}, "raw_text_unformatted": "Jeff", "value": "Jeff"}}, "CONFIDENCE": 0.9986324906349182, "ENTITY_TYPE": "PERSON NAME"}, {"ENTITY_ID": "9ec85982-cc85-4657-859d-e04b14e6e837_2", "PAGE": 5, "CONTENT": {"CONTENT": {"word_ids": ["word_5_481"], "coordinates": {"y0": 2088, "x0": 1629, "y1": 2111, "x1": 1694}, "raw_text_unformatted": "Thels", "value": "Thels"}}, "CONFIDENCE": 0.9986324906349182, "ENTITY_TYPE": "PERSON NAME"}, {"ENTITY_ID": "8a4eecfa-ab4c-4b77-b3ab-dc0b8459ca7b_1", "PAGE": 5, "CONTENT": {"CONTENT": {"word_ids": ["word_5_503"], "coordinates": {"y0": 2089, "x0": 1906, "y1": 2114, "x1": 1986}, "raw_text_unformatted": "Shellie", "value": "Shellie"}}, "CONFIDENCE": 0.9725180268287659, "ENTITY_TYPE": "PERSON NAME"}, {"ENTITY_ID": "8a4eecfa-ab4c-4b77-b3ab-dc0b8459ca7b_2", "PAGE": 5, "CONTENT": {"CONTENT": {"word_ids": ["word_5_504"], "coordinates": {"y0": 2091, "x0": 1992, "y1": 2115, "x1": 2092}, "raw_text_unformatted": "Wolcott", "value": "Wolcott"}}, "CONFIDENCE": 0.9725180268287659, "ENTITY_TYPE": "PERSON NAME"}, {"ENTITY_ID": "ba91aa45-63c2-4c28-9232-6f2d3006794f_1", "PAGE": 5, "CONTENT": {"CONTENT": {"word_ids": ["word_5_541"], "coordinates": {"y0": 2867, "x0": 210, "y1": 2892, "x1": 279}, "raw_text_unformatted": "Keith", "value": "Keith"}}, "CONFIDENCE": 0.8975593447685242, "ENTITY_TYPE": "PERSON NAME"}, {"ENTITY_ID": "ba91aa45-63c2-4c28-9232-6f2d3006794f_2", "PAGE": 5, "CONTENT": {"CONTENT": {"word_ids": ["word_5_542"], "coordinates": {"y0": 2868, "x0": 288, "y1": 2893, "x1": 303}, "raw_text_unformatted": "S", "value": "S"}}, "CONFIDENCE": 0.8975593447685242, "ENTITY_TYPE": "PERSON NAME"}, {"ENTITY_ID": "ba91aa45-63c2-4c28-9232-6f2d3006794f_3", "PAGE": 5, "CONTENT": {"CONTENT": {"word_ids": ["word_5_543"], "coordinates": {"y0": 2867, "x0": 312, "y1": 2894, "x1": 396}, "raw_text_unformatted": "Befort", "value": "Befort"}}, "CONFIDENCE": 0.8975593447685242, "ENTITY_TYPE": "PERSON NAME"}, {"ENTITY_ID": "5d289b47-914f-435f-bb76-dd127abc9774_1", "PAGE": 5, "CONTENT": {"CONTENT": {"word_ids": ["word_5_554"], "coordinates": {"y0": 2871, "x0": 1227, "y1": 2902, "x1": 1339}, "raw_text_unformatted": "Annette", "value": "Annette"}}, "CONFIDENCE": 0.985998809337616, "ENTITY_TYPE": "PERSON NAME"}, {"ENTITY_ID": "5d289b47-914f-435f-bb76-dd127abc9774_2", "PAGE": 5, "CONTENT": {"CONTENT": {"word_ids": ["word_5_555"], "coordinates": {"y0": 2876, "x0": 1347, "y1": 2902, "x1": 1366}, "raw_text_unformatted": "C", "value": "C"}}, "CONFIDENCE": 0.985998809337616, "ENTITY_TYPE": "PERSON NAME"}, {"ENTITY_ID": "5d289b47-914f-435f-bb76-dd127abc9774", "PAGE": 5, "CONTENT": {"CONTENT": {"word_ids": ["word_5_554", "word_5_555"], "coordinates": {"y0": 2871, "x0": 1227, "y1": 2902, "x1": 1366}, "raw_text_unformatted": "AnnetteC", "value": "Annette C"}}, "CONFIDENCE": 0.985998809337616, "ENTITY_TYPE": "PERSON NAME"}, {"ENTITY_ID": "8a4eecfa-ab4c-4b77-b3ab-dc0b8459ca7b", "PAGE": 5, "CONTENT": {"CONTENT": {"word_ids": ["word_5_503", "word_5_504"], "coordinates": {"y0": 2089, "x0": 1906, "y1": 2115, "x1": 2092}, "raw_text_unformatted": "ShellieWolcott", "value": "Shellie Wolcott"}}, "CONFIDENCE": 0.9725180268287659, "ENTITY_TYPE": "PERSON NAME"}, {"ENTITY_ID": "9ec85982-cc85-4657-859d-e04b14e6e837", "PAGE": 5, "CONTENT": {"CONTENT": {"word_ids": ["word_5_480", "word_5_481"], "coordinates": {"y0": 2087, "x0": 1580, "y1": 2111, "x1": 1694}, "raw_text_unformatted": "JeffThels", "value": "Jeff Thels"}}, "CONFIDENCE": 0.9986324906349182, "ENTITY_TYPE": "PERSON NAME"}, {"ENTITY_ID": "a2f0cab3-de7f-4725-b69b-395e4a9ed1ba", "PAGE": 5, "CONTENT": {"CONTENT": {"word_ids": ["word_5_424", "word_5_425", "word_5_426"], "coordinates": {"y0": 2080, "x0": 604, "y1": 2103, "x1": 772}, "raw_text_unformatted": "JanetLWetta", "value": "Janet L Wetta"}}, "CONFIDENCE": 0.9964419603347778, "ENTITY_TYPE": "PERSON NAME"}, {"ENTITY_ID": "b403e88b-50bb-4ef9-be56-fb6a2e2ad720", "PAGE": 5, "CONTENT": {"CONTENT": {"word_ids": ["word_5_446", "word_5_447"], "coordinates": {"y0": 1778, "x0": 1258, "y1": 1808, "x1": 1406}, "raw_text_unformatted": "TheisReaity", "value": "Theis Reaity"}}, "CONFIDENCE": 0.9315842390060425, "ENTITY_TYPE": "PERSON NAME"}, {"ENTITY_ID": "ba91aa45-63c2-4c28-9232-6f2d3006794f", "PAGE": 5, "CONTENT": {"CONTENT": {"word_ids": ["word_5_541", "word_5_542", "word_5_543"], "coordinates": {"y0": 2867, "x0": 210, "y1": 2894, "x1": 396}, "raw_text_unformatted": "KeithSBefort", "value": "Keith S Befort"}}, "CONFIDENCE": 0.8975593447685242, "ENTITY_TYPE": "PERSON NAME"}, {"ENTITY_ID": "cf915163-a6f3-43aa-8695-eb5ab96824bc", "PAGE": 5, "CONTENT": {"CONTENT": {"word_ids": ["word_5_473", "word_5_474"], "coordinates": {"y0": 1841, "x0": 1677, "y1": 1864, "x1": 1773}, "raw_text_unformatted": "KeithCt", "value": "Keith Ct"}}, "CONFIDENCE": 0.4963740408420563, "ENTITY_TYPE": "PERSON NAME"}, {"ENTITY_ID": "efc106cf-8f6e-437e-9615-a1daa5caef72", "PAGE": 5, "CONTENT": {"CONTENT": {"word_ids": ["word_5_457", "word_5_458"], "coordinates": {"y0": 2080, "x0": 1254, "y1": 2120, "x1": 1367}, "raw_text_unformatted": "JeffTheis", "value": "Jeff Theis"}}, "CONFIDENCE": 0.9971674680709839, "ENTITY_TYPE": "PERSON NAME"}, {"ENTITY_ID": "9643f634-128c-48ac-9191-ef787cf0b6f5_1", "PAGE": 1, "CONTENT": {"CONTENT": {"word_ids": ["word_1_40"], "coordinates": {"y0": 501, "x0": 1121, "y1": 527, "x1": 1192}, "raw_text_unformatted": "Keith", "value": "Keith"}}, "CONFIDENCE": 0.9979235529899597, "ENTITY_TYPE": "PERSON NAME"}, {"ENTITY_ID": "9643f634-128c-48ac-9191-ef787cf0b6f5_2", "PAGE": 1, "CONTENT": {"CONTENT": {"word_ids": ["word_1_41"], "coordinates": {"y0": 502, "x0": 1200, "y1": 527, "x1": 1215}, "raw_text_unformatted": "S", "value": "S"}}, "CONFIDENCE": 0.9979235529899597, "ENTITY_TYPE": "PERSON NAME"}, {"ENTITY_ID": "9643f634-128c-48ac-9191-ef787cf0b6f5_3", "PAGE": 1, "CONTENT": {"CONTENT": {"word_ids": ["word_1_42"], "coordinates": {"y0": 501, "x0": 1224, "y1": 527, "x1": 1307}, "raw_text_unformatted": "Befort", "value": "Befort"}}, "CONFIDENCE": 0.9979235529899597, "ENTITY_TYPE": "PERSON NAME"}, {"ENTITY_ID": "1f546fdb-54ed-4f8e-973f-d09382a9c550_1", "PAGE": 1, "CONTENT": {"CONTENT": {"word_ids": ["word_1_44"], "coordinates": {"y0": 503, "x0": 1375, "y1": 529, "x1": 1487}, "raw_text_unformatted": "Annette", "value": "Annette"}}, "CONFIDENCE": 0.9650100469589233, "ENTITY_TYPE": "PERSON NAME"}, {"ENTITY_ID": "1f546fdb-54ed-4f8e-973f-d09382a9c550_2", "PAGE": 1, "CONTENT": {"CONTENT": {"word_ids": ["word_1_45"], "coordinates": {"y0": 505, "x0": 1495, "y1": 529, "x1": 1513}, "raw_text_unformatted": "C", "value": "C"}}, "CONFIDENCE": 0.9650100469589233, "ENTITY_TYPE": "PERSON NAME"}, {"ENTITY_ID": "1f546fdb-54ed-4f8e-973f-d09382a9c550_3", "PAGE": 1, "CONTENT": {"CONTENT": {"word_ids": ["word_1_46"], "coordinates": {"y0": 504, "x0": 1521, "y1": 530, "x1": 1604}, "raw_text_unformatted": "Befort", "value": "Befort"}}, "CONFIDENCE": 0.9650100469589233, "ENTITY_TYPE": "PERSON NAME"}, {"ENTITY_ID": "861955fd-516c-4835-b95f-cbeadffdd2e2_1", "PAGE": 1, "CONTENT": {"CONTENT": {"word_ids": ["word_1_74"], "coordinates": {"y0": 623, "x0": 1121, "y1": 656, "x1": 1239}, "raw_text_unformatted": "Geoffrey", "value": "Geoffrey"}}, "CONFIDENCE": 0.9971224069595337, "ENTITY_TYPE": "PERSON NAME"}, {"ENTITY_ID": "861955fd-516c-4835-b95f-cbeadffdd2e2_2", "PAGE": 1, "CONTENT": {"CONTENT": {"word_ids": ["word_1_75"], "coordinates": {"y0": 625, "x0": 1246, "y1": 650, "x1": 1275}, "raw_text_unformatted": "W", "value": "W"}}, "CONFIDENCE": 0.9971224069595337, "ENTITY_TYPE": "PERSON NAME"}, {"ENTITY_ID": "861955fd-516c-4835-b95f-cbeadffdd2e2_3", "PAGE": 1, "CONTENT": {"CONTENT": {"word_ids": ["word_1_76"], "coordinates": {"y0": 625, "x0": 1282, "y1": 651, "x1": 1397}, "raw_text_unformatted": "Harrison", "value": "Harrison"}}, "CONFIDENCE": 0.9971224069595337, "ENTITY_TYPE": "PERSON NAME"}, {"ENTITY_ID": "ebc01b05-3fec-48d3-b0e6-5cba52463ed7-PERSON_1", "PAGE": 1, "CONTENT": {"CONTENT": {"word_ids": ["word_1_92"], "coordinates": {"y0": 702, "x0": 694, "y1": 728, "x1": 831}, "raw_text_unformatted": "Westwind", "value": "Westwind"}}, "CONFIDENCE": 0.9686533212661743, "ENTITY_TYPE": "PERSON NAME"}, {"ENTITY_ID": "ebc01b05-3fec-48d3-b0e6-5cba52463ed7-PERSON_2", "PAGE": 1, "CONTENT": {"CONTENT": {"word_ids": ["word_1_93"], "coordinates": {"y0": 703, "x0": 840, "y1": 734, "x1": 888}, "raw_text_unformatted": "Bay", "value": "Bay"}}, "CONFIDENCE": 0.9686533212661743, "ENTITY_TYPE": "PERSON NAME"}, {"ENTITY_ID": "0eab706d-9375-4a52-994b-45f130437341-PERSON_1", "PAGE": 1, "CONTENT": {"CONTENT": {"word_ids": ["word_1_99"], "coordinates": {"y0": 705, "x0": 2000, "y1": 733, "x1": 2029}, "raw_text_unformatted": "O", "value": "O"}}, "CONFIDENCE": 0.8479515314102173, "ENTITY_TYPE": "PERSON NAME"}, {"ENTITY_ID": "0eab706d-9375-4a52-994b-45f130437341-PERSON_2", "PAGE": 1, "CONTENT": {"CONTENT": {"word_ids": ["word_1_100"], "coordinates": {"y0": 741, "x0": 590, "y1": 771, "x1": 700}, "raw_text_unformatted": "Wichita,", "value": "Wichita,"}}, "CONFIDENCE": 0.8479515314102173, "ENTITY_TYPE": "PERSON NAME"}, {"ENTITY_ID": "0eab706d-9375-4a52-994b-45f130437341-PERSON_3", "PAGE": 1, "CONTENT": {"CONTENT": {"word_ids": ["word_1_101"], "coordinates": {"y0": 742, "x0": 709, "y1": 767, "x1": 741}, "raw_text_unformatted": "KS", "value": "KS"}}, "CONFIDENCE": 0.8479515314102173, "ENTITY_TYPE": "PERSON NAME"}, {"ENTITY_ID": "0eab706d-9375-4a52-994b-45f130437341-PERSON", "PAGE": 1, "CONTENT": {"CONTENT": {"word_ids": ["word_1_99", "word_1_100", "word_1_101"], "coordinates": {"y0": 705, "x0": 2000, "y1": 771, "x1": 741}, "raw_text_unformatted": "OWichita,KS", "value": "O Wichita, KS"}}, "CONFIDENCE": 0.8479515314102173, "ENTITY_TYPE": "PERSON NAME"}, {"ENTITY_ID": "1f546fdb-54ed-4f8e-973f-d09382a9c550", "PAGE": 1, "CONTENT": {"CONTENT": {"word_ids": ["word_1_44", "word_1_45", "word_1_46"], "coordinates": {"y0": 503, "x0": 1375, "y1": 530, "x1": 1604}, "raw_text_unformatted": "AnnetteCBefort", "value": "Annette C Befort"}}, "CONFIDENCE": 0.9650100469589233, "ENTITY_TYPE": "PERSON NAME"}, {"ENTITY_ID": "861955fd-516c-4835-b95f-cbeadffdd2e2", "PAGE": 1, "CONTENT": {"CONTENT": {"word_ids": ["word_1_74", "word_1_75", "word_1_76"], "coordinates": {"y0": 623, "x0": 1121, "y1": 656, "x1": 1397}, "raw_text_unformatted": "GeoffreyWHarrison", "value": "Geoffrey W Harrison"}}, "CONFIDENCE": 0.9971224069595337, "ENTITY_TYPE": "PERSON NAME"}, {"ENTITY_ID": "9643f634-128c-48ac-9191-ef787cf0b6f5", "PAGE": 1, "CONTENT": {"CONTENT": {"word_ids": ["word_1_40", "word_1_41", "word_1_42"], "coordinates": {"y0": 501, "x0": 1121, "y1": 527, "x1": 1307}, "raw_text_unformatted": "KeithSBefort", "value": "Keith S Befort"}}, "CONFIDENCE": 0.9979235529899597, "ENTITY_TYPE": "PERSON NAME"}, {"ENTITY_ID": "ebc01b05-3fec-48d3-b0e6-5cba52463ed7-PERSON", "PAGE": 1, "CONTENT": {"CONTENT": {"word_ids": ["word_1_92", "word_1_93"], "coordinates": {"y0": 702, "x0": 694, "y1": 734, "x1": 888}, "raw_text_unformatted": "WestwindBay", "value": "Westwind Bay"}}, "CONFIDENCE": 0.9686533212661743, "ENTITY_TYPE": "PERSON NAME"}, {"ENTITY_ID": "eb551c39-5523-47cf-87ea-34c895e7d510-STATE", "PAGE": 5, "CONTENT": {"CONTENT": {"word_ids": ["word_5_420"], "coordinates": {"y0": 1866, "x0": 714, "y1": 1889, "x1": 743}, "raw_text_unformatted": "KS", "value": "KS"}}, "CONFIDENCE": 0.802750825881958, "ENTITY_TYPE": "STATE"}, {"ENTITY_ID": "9ccc81e8-3a0d-4cb2-9477-e52d1b05c97d-STATE", "PAGE": 5, "CONTENT": {"CONTENT": {"word_ids": ["word_5_476"], "coordinates": {"y0": 1875, "x0": 1689, "y1": 1897, "x1": 1718}, "raw_text_unformatted": "KS", "value": "KS"}}, "CONFIDENCE": 0.786299467086792, "ENTITY_TYPE": "STATE"}, {"ENTITY_ID": "e0509e03-0a71-4e61-bbb2-40fcd4523ecb-STATE", "PAGE": 5, "CONTENT": {"CONTENT": {"word_ids": ["word_5_499"], "coordinates": {"y0": 1910, "x0": 2013, "y1": 1933, "x1": 2041}, "raw_text_unformatted": "KS", "value": "KS"}}, "CONFIDENCE": 0.8247308135032654, "ENTITY_TYPE": "STATE"}, {"ENTITY_ID": "30b0521a-3e15-4890-bf5c-7c7a9541a37c-STATE", "PAGE": 4, "CONTENT": {"CONTENT": {"word_ids": ["word_4_322"], "coordinates": {"y0": 2192, "x0": 687, "y1": 2217, "x1": 723}, "raw_text_unformatted": "KS", "value": "KS"}}, "CONFIDENCE": 0.9919405579566956, "ENTITY_TYPE": "STATE"}, {"ENTITY_ID": "f7c5326c-51d1-4343-bfae-e30cb80e22c8-STATE", "PAGE": 1, "CONTENT": {"CONTENT": {"word_ids": ["word_1_63"], "coordinates": {"y0": 583, "x0": 1239, "y1": 608, "x1": 1272}, "raw_text_unformatted": "KS", "value": "KS"}}, "CONFIDENCE": 0.9760974049568176, "ENTITY_TYPE": "STATE"}, {"ENTITY_ID": "ebc01b05-3fec-48d3-b0e6-5cba52463ed7-STATE", "PAGE": 1, "CONTENT": {"CONTENT": {"word_ids": ["word_1_96"], "coordinates": {"y0": 707, "x0": 1238, "y1": 731, "x1": 1271}, "raw_text_unformatted": "KS", "value": "KS"}}, "CONFIDENCE": 0.9686533212661743, "ENTITY_TYPE": "STATE"}, {"ENTITY_ID": "f6916854-5621-4e65-8f0e-c92af7f69c21", "PAGE": 5, "CONTENT": {"CONTENT": {"word_ids": ["word_5_133", "word_5_134", "word_5_135", "word_5_136"], "coordinates": {"y0": 1389, "x0": 439, "y1": 1453, "x1": 1037}, "raw_text_unformatted": "Consumer Financial Protection Bureau", "value": "Consumer Financial Protection Bureau"}}, "CONFIDENCE": 0.9821372032165527, "ENTITY_TYPE": "COMPANY NAME"}, {"ENTITY_ID": "f6ab4fdf-b720-48f6-b514-7e0b6112693a", "PAGE": 5, "CONTENT": {"CONTENT": {"word_ids": ["word_5_144"], "coordinates": {"y0": 1958, "x0": 236, "y1": 1984, "x1": 319}, "raw_text_unformatted": "NMLS", "value": "NMLS"}}, "CONFIDENCE": 0.7168290019035339, "ENTITY_TYPE": "COMPANY NAME"}, {"ENTITY_ID": "4155c04c-01b1-4e89-9c3e-323a2d27a641", "PAGE": 5, "CONTENT": {"CONTENT": {"word_ids": ["word_5_151"], "coordinates": {"y0": 2137, "x0": 355, "y1": 2163, "x1": 439}, "raw_text_unformatted": "NMLS", "value": "NMLS"}}, "CONFIDENCE": 0.935526430606842, "ENTITY_TYPE": "COMPANY NAME"}, {"ENTITY_ID": "1535d8c2-ccd4-4e46-8ee6-728b7ca8f99e", "PAGE": 5, "CONTENT": {"CONTENT": {"word_ids": ["word_5_154"], "coordinates": {"y0": 2197, "x0": 355, "y1": 2221, "x1": 391}, "raw_text_unformatted": "KS", "value": "KS"}}, "CONFIDENCE": 0.7247439026832581, "ENTITY_TYPE": "COMPANY NAME"}, {"ENTITY_ID": "3e706f15-b263-4e6c-a8fc-cec95631f8ff", "PAGE": 5, "CONTENT": {"CONTENT": {"word_ids": ["word_5_413", "word_5_414"], "coordinates": {"y0": 1774, "x0": 610, "y1": 1803, "x1": 763}, "raw_text_unformatted": "Legacy Bank", "value": "Legacy Bank"}}, "CONFIDENCE": 0.8985095024108887, "ENTITY_TYPE": "COMPANY NAME"}, {"ENTITY_ID": "b350bbbe-ea42-4f89-b4bf-2769ea7575d4", "PAGE": 5, "CONTENT": {"CONTENT": {"word_ids": ["word_5_487"], "coordinates": {"y0": 1692, "x0": 1910, "y1": 1720, "x1": 2075}, "raw_text_unformatted": "Settlement", "value": "Settlement"}}, "CONFIDENCE": 0.48447975516319275, "ENTITY_TYPE": "COMPANY NAME"}, {"ENTITY_ID": "331e7507-d699-4c82-b9e7-5d59bc08449a", "PAGE": 2, "CONTENT": {"CONTENT": {"word_ids": ["word_2_84", "word_2_85", "word_2_86"], "coordinates": {"y0": 797, "x0": 782, "y1": 829, "x1": 1205}, "raw_text_unformatted": "SettlementOne Credit Corporation", "value": "SettlementOne Credit Corporation"}}, "CONFIDENCE": 0.8532541990280151, "ENTITY_TYPE": "COMPANY NAME"}, {"ENTITY_ID": "cb8fa498-fc11-464b-9696-de661b5ef603", "PAGE": 2, "CONTENT": {"CONTENT": {"word_ids": ["word_2_93"], "coordinates": {"y0": 835, "x0": 913, "y1": 858, "x1": 981}, "raw_text_unformatted": "Flood", "value": "Flood"}}, "CONFIDENCE": 0.803539514541626, "ENTITY_TYPE": "COMPANY NAME"}, {"ENTITY_ID": "bcd2777e-a062-4dce-820f-40ce04f4f93e", "PAGE": 2, "CONTENT": {"CONTENT": {"word_ids": ["word_2_106", "word_2_107"], "coordinates": {"y0": 909, "x0": 781, "y1": 938, "x1": 934}, "raw_text_unformatted": "Legacy Bank", "value": "Legacy Bank"}}, "CONFIDENCE": 0.9198209643363953, "ENTITY_TYPE": "COMPANY NAME"}, {"ENTITY_ID": "d29b604e-f926-409a-a88b-d2f2b73f729a", "PAGE": 2, "CONTENT": {"CONTENT": {"word_ids": ["word_2_148", "word_2_149"], "coordinates": {"y0": 1470, "x0": 314, "y1": 1494, "x1": 484}, "raw_text_unformatted": "TOTAL LOAN", "value": "TOTAL LOAN"}}, "CONFIDENCE": 0.6286524534225464, "ENTITY_TYPE": "COMPANY NAME"}, {"ENTITY_ID": "201bea24-f778-4e26-a4bc-35e6ba6046ac", "PAGE": 2, "CONTENT": {"CONTENT": {"word_ids": ["word_2_184", "word_2_185"], "coordinates": {"y0": 1736, "x0": 774, "y1": 1764, "x1": 930}, "raw_text_unformatted": "Sedgwick Co", "value": "Sedgwick Co"}}, "CONFIDENCE": 0.9682096242904663, "ENTITY_TYPE": "COMPANY NAME"}, {"ENTITY_ID": "12b00667-2a92-4825-8fb3-dab13bb0132f", "PAGE": 2, "CONTENT": {"CONTENT": {"word_ids": ["word_2_282", "word_2_283", "word_2_284", "word_2_285", "word_2_286", "word_2_287"], "coordinates": {"y0": 2421, "x0": 313, "y1": 2455, "x1": 995}, "raw_text_unformatted": "Real Estate Commission to Theis Realty", "value": "Real Estate Commission to Theis Realty"}}, "CONFIDENCE": 0.6992936134338379, "ENTITY_TYPE": "COMPANY NAME"}, {"ENTITY_ID": "8968d115-bb71-4545-861b-d4a974dbddcd", "PAGE": 2, "CONTENT": {"CONTENT": {"word_ids": ["word_2_290", "word_2_291", "word_2_292", "word_2_293", "word_2_294", "word_2_295"], "coordinates": {"y0": 2458, "x0": 313, "y1": 2492, "x1": 995}, "raw_text_unformatted": "Real Estate Commission to Theis Realty", "value": "Real Estate Commission to Theis Realty"}}, "CONFIDENCE": 0.6839974522590637, "ENTITY_TYPE": "COMPANY NAME"}, {"ENTITY_ID": "0978d9da-fd00-49a2-a632-0db623a280a3", "PAGE": 2, "CONTENT": {"CONTENT": {"word_ids": ["word_2_365"], "coordinates": {"y0": 3014, "x0": 1975, "y1": 3037, "x1": 2142}, "raw_text_unformatted": "GTRIDCDWSS", "value": "GTRIDCDWSS"}}, "CONFIDENCE": 0.5195257067680359, "ENTITY_TYPE": "COMPANY NAME"}, {"ENTITY_ID": "bf9a044e-a77e-429e-bf81-dafb0016d069", "PAGE": 3, "CONTENT": {"CONTENT": {"word_ids": ["word_3_134", "word_3_135", "word_3_136", "word_3_137"], "coordinates": {"y0": 1062, "x0": 242, "y1": 1090, "x1": 1650}, "raw_text_unformatted": "BORROWER'?\u0080\u0099S TRANSACTION SELLER?\u0080\u0099'S TRANSACTION", "value": "BORROWER'?\u0080\u0099S TRANSACTION SELLER?\u0080\u0099'S TRANSACTION"}}, "CONFIDENCE": 0.9723222255706787, "ENTITY_TYPE": "COMPANY NAME"}, {"ENTITY_ID": "1b1c68db-3f71-4f27-ae63-7fcbd35f6370", "PAGE": 4, "CONTENT": {"CONTENT": {"word_ids": ["word_4_416"], "coordinates": {"y0": 801, "x0": 1277, "y1": 824, "x1": 1364}, "raw_text_unformatted": "Escrow", "value": "Escrow"}}, "CONFIDENCE": 0.47142037749290466, "ENTITY_TYPE": "COMPANY NAME"}, {"ENTITY_ID": "8f0010f5-8fc5-4d76-82d2-e45766172b5f", "PAGE": 1, "CONTENT": {"CONTENT": {"word_ids": ["word_1_23"], "coordinates": {"y0": 311, "x0": 520, "y1": 363, "x1": 662}, "raw_text_unformatted": "DlSCI", "value": "DlSCI"}}, "CONFIDENCE": 0.6961856484413147, "ENTITY_TYPE": "COMPANY NAME"}, {"ENTITY_ID": "ccab0a3a-fb6b-4041-b7fe-d7cf36ab93b7", "PAGE": 1, "CONTENT": {"CONTENT": {"word_ids": ["word_1_104", "word_1_105"], "coordinates": {"y0": 746, "x0": 1120, "y1": 779, "x1": 1292}, "raw_text_unformatted": "Legacy Bank", "value": "Legacy Bank"}}, "CONFIDENCE": 0.7237860560417175, "ENTITY_TYPE": "COMPANY NAME"}, {"ENTITY_ID": "62c29104-1d90-4daa-a185-7c25b31833d7", "PAGE": 1, "CONTENT": {"CONTENT": {"word_ids": ["word_1_292"], "coordinates": {"y0": 2968, "x0": 572, "y1": 2992, "x1": 761}, "raw_text_unformatted": "GTRIDCDWS_S", "value": "GTRIDCDWS_S"}}, "CONFIDENCE": 0.781182587146759, "ENTITY_TYPE": "COMPANY NAME"}, {"ENTITY_ID": "0b8a18dd-c25f-41b7-a2dc-99d3d43c91a3", "PAGE": 1, "CONTENT": {"CONTENT": {"word_ids": ["word_1_306"], "coordinates": {"y0": 3016, "x0": 1969, "y1": 3040, "x1": 2137}, "raw_text_unformatted": "GTRIDCDWSS", "value": "GTRIDCDWSS"}}, "CONFIDENCE": 0.868590772151947, "ENTITY_TYPE": "COMPANY NAME"}, {"ENTITY_ID": "1e68743b-a14b-4355-94ee-fc655e918640", "PAGE": 2, "CONTENT": {"CONTENT": {"word_ids": ["word_2_113", "word_2_114", "word_2_115", "word_2_116", "word_2_117", "word_2_118"], "coordinates": {"y0": 943, "x0": 510, "y1": 975, "x1": 980}, "raw_text_unformatted": "Title Insurance to Security 1st Title", "value": "Title Insurance to Security 1st Title"}}, "CONFIDENCE": 0.775867223739624, "ENTITY_TYPE": "TITLE"}, {"ENTITY_ID": "d05755a0-697b-44e6-8b35-889cb4914a9a", "PAGE": 3, "CONTENT": {"CONTENT": {"word_ids": ["word_3_241", "word_3_242"], "coordinates": {"y0": 1618, "x0": 242, "y1": 1640, "x1": 479}, "raw_text_unformatted": "10 Assessments", "value": "10 Assessments"}}, "CONFIDENCE": 0.608047366142273, "ENTITY_TYPE": "TITLE"}, {"ENTITY_ID": "50c87560-257a-4c4e-8de6-f10ebd91057a", "PAGE": 3, "CONTENT": {"CONTENT": {"word_ids": ["word_3_244", "word_3_245"], "coordinates": {"y0": 1620, "x0": 1283, "y1": 1642, "x1": 1505}, "raw_text_unformatted": "11 Assessments", "value": "11 Assessments"}}, "CONFIDENCE": 0.8199182152748108, "ENTITY_TYPE": "TITLE"}]